Workbook

Sheet Cover
B3: International Business Machines (NYSE: IBM)
B4: Equity Research | Initiating Coverage | October 2026
B5: IT Services & Software · Quantum Computing | Francisco Rodriguez
B7: ="RATING"&CHAR(10)&DCF!C44 | D7: ="PRICE TARGET"&CHAR(10)&TEXT(DCF!C41,"$#,##0") | F7: ="CURRENT PRICE"&CHAR(10)&TEXT(DCF!C36,"$#,##0.00") | H7: ="UPSIDE"&CHAR(10)&TEXT(DCF!C42,"+0.0%;-0.0%")
B9: KEY STATISTICS | F9: VALUATION SUMMARY
B10: Market Cap | D10: ="$"&TEXT(DCF!C36*DCF!C34/1000,"#,##0")&"B" | F10: Base DCF Value | H10: =TEXT(DCF!C35,"$#,##0")
B11: Core Net Debt | D11: ="$"&TEXT((DCF!C32-DCF!C31)/1000,"0.0")&"B" | F11: of which Quantum | H11: =TEXT(DCF!C38,"$#,##0")
B12: FY2025A Revenue | D12: ="$"&TEXT('Operating Model'!D10/1000,"0.0")&"B" | F12: Bear / Bull (core) | H12: =TEXT(Sensitivity!C63,"$0")&" / "&TEXT(Sensitivity!C95,"$0")
B13: FY2026E Revenue | D13: ="$"&TEXT('Operating Model'!E10/1000,"0.0")&"B" | F13: Quantum Dominant | H13: =TEXT(Sensitivity!C159,"$#,##0")
B14: FY2025A Reported FCF | D14: ="$"&TEXT(Assumptions!$C$40/1000,"0.0")&"B" | F14: Prob.-Weighted Value | H14: =TEXT(Sensitivity!C40,"$#,##0")
B15: Dividend Yield | D15: =TEXT(Assumptions!$C$55/DCF!C36,"0.0%") | F15: WACC / g | H15: =TEXT(DCF!C14,"0.0%")&" / "&TEXT(DCF!C25,"0.0%")
B16: 52-Wk High / Low | D16: =TEXT(Assumptions!$C$48,"$0")&" / "&TEXT(Assumptions!$C$49,"$0") | F16: Total Return incl. Div. | H16: =TEXT(DCF!C43,"+0.0%;-0.0%")
B17: Consensus PT | D17: =TEXT(Assumptions!$C$56,"$0.00") | F17: TV % of EV | H17: =TEXT(DCF!C29,"0%")
B19: INVESTMENT THESIS
B20: ="IBM is a cash-generative software and mainframe franchise with a real — but early — quantum call option. Our 10-year segment DCF values the core business at "&TEXT(DCF!C39,"$#,##0")&" and quantum at "&TEXT(DCF!C38,"$#,##0")&" per share; probability-weighting four quantum outcomes gives a "&TEXT(DCF!C41,"$#,##0")&" price target vs. "&TEXT(DCF!C36,"$#,##0")&" today. Rating: "&DCF!C44&"."
B21: 1. Software Compounder | D21: Software (44% of FY2025A revenue, 33% segment margin) grew 11% in 2025; Red Hat +11% and Data +19% in Q2'26. Confluent (closed Mar 2026) adds real-time data streaming for AI.
B22: 2. 2026 Is a Mainframe Air-Pocket | D22: IBM Z fell 42% in Q2'26 against the z17 peak; guidance cut to 4–5% cc growth. We model Infrastructure −4% in FY2026E and −2% in FY2027E before the next cycle.
B23: 3. Quantum: Real Roadmap, Small Revenue | D23: Starling fault-tolerant system targeted 2H 2029; $10B+ program incl. the Anderon foundry. Quantum is loss-making until ~FY2030E in our base case — the value is in the tail.
B24: 4. What the Price Implies | D24: =IF(Sensitivity!C42=0,"At "&TEXT(DCF!C36,"$0")&" the stock trades below our core-only value of "&TEXT(DCF!C39,"$0")&" — quantum is priced at zero. The debate is the discount rate: the price implies a ~"&TEXT(Sensitivity!C43,"0.0%")&" WACC vs. our "&TEXT(DCF!C14,"0.0%")&".","At "&TEXT(DCF!C36,"$0")&" the market needs about "&TEXT(Sensitivity!C42,"$0")&" per share of quantum value on top of our core DCF.")
B26: KEY RISKS
B27: ▪ Quantum timeline | D27: Starling slips past 2029 or competitors (Google, Quantinuum) reach fault tolerance first
B28: ▪ Consulting / AI disruption | D28: GenAI compresses consulting hours faster than IBM can reprice
B29: ▪ Mainframe cycle | D29: z18 cycle timing and customer capex shifts drive lumpy Infrastructure revenue
B30: ▪ Leverage & pension | D30: $49B core debt after Confluent; pension obligations not modeled separately
B32: Price as of Oct 14, 2026; balance sheet Jun 30, 2026. $M unless noted. Every number on this page is formula-linked — change inputs on the Assumptions tab only.
B34: Francisco Rodriguez | Financial Modeling Portfolio | github.com/Azyo1

Sheet Assumptions
B2: IBM — Model Assumptions (ALL HARDCODED INPUTS = BLUE CELLS) · $M unless noted
B3: Metric | C3: FY2024A | D3: FY2025A | E3: FY2026E | F3: FY2027E | G3: FY2028E | H3: FY2029E | I3: FY2030E | J3: FY2031E | K3: FY2032E | L3: FY2033E | M3: FY2034E | N3: FY2035E
B4: SEGMENT REVENUE GROWTH (historical = formula, forecast = input)
B5: Software | C5: — | D5: =D11/C11-1 | E5: 0.095 | F5: 0.08 | G5: 0.075 | H5: 0.07 | I5: 0.065 | J5: 0.06 | K5: 0.055 | L5: 0.05 | M5: 0.045 | N5: 0.04
B6: Consulting | C6: — | D6: =D12/C12-1 | E6: 0.02 | F6: 0.03 | G6: 0.03 | H6: 0.03 | I6: 0.03 | J6: 0.03 | K6: 0.03 | L6: 0.03 | M6: 0.03 | N6: 0.03
B7: Infrastructure | C7: — | D7: =D13/C13-1 | E7: -0.04 | F7: -0.02 | G7: 0.06 | H7: 0.03 | I7: 0.02 | J7: 0.02 | K7: 0.02 | L7: 0.02 | M7: 0.02 | N7: 0.02
B8: Financing | C8: — | D8: =D14/C14-1 | E8: 0.1 | F8: 0.03 | G8: 0.03 | H8: 0.03 | I8: 0.03 | J8: 0.03 | K8: 0.03 | L8: 0.03 | M8: 0.03 | N8: 0.03
B10: SEGMENT REVENUE ($M)
B11: Software | C11: 27085 | D11: 29962 | E11: =D11*(1+E5) | F11: =E11*(1+F5) | G11: =F11*(1+G5) | H11: =G11*(1+H5) | I11: =H11*(1+I5) | J11: =I11*(1+J5) | K11: =J11*(1+K5) | L11: =K11*(1+L5) | ... N11: =M11*(1+N5)
B12: Consulting | C12: 20692 | D12: 21055 | E12: =D12*(1+E6) | F12: =E12*(1+F6) | G12: =F12*(1+G6) | H12: =G12*(1+H6) | I12: =H12*(1+I6) | J12: =I12*(1+J6) | K12: =J12*(1+K6) | L12: =K12*(1+L6) | ... N12: =M12*(1+N6)
B13: Infrastructure | C13: 14020 | D13: 15718 | E13: =D13*(1+E7) | F13: =E13*(1+F7) | G13: =F13*(1+G7) | H13: =G13*(1+H7) | I13: =H13*(1+I7) | J13: =I13*(1+J7) | K13: =J13*(1+K7) | L13: =K13*(1+L7) | ... N13: =M13*(1+N7)
B14: Financing | C14: 714 | D14: 737 | E14: =D14*(1+E8) | F14: =E14*(1+F8) | G14: =F14*(1+G8) | H14: =G14*(1+H8) | I14: =H14*(1+I8) | J14: =I14*(1+J8) | K14: =J14*(1+K8) | L14: =K14*(1+L8) | ... N14: =M14*(1+N8)
B15: Quantum — incremental revenue (base case) | C15: — | D15: — | E15: 150 | F15: 250 | G15: 400 | H15: 700 | I15: 1200 | J15: 2000 | K15: 3000 | L15: 4200 | M15: 5500 | N15: 7000
B16: Total Revenue | C16: =C11+C12+C13+C14+N(C15) | D16: =D11+D12+D13+D14+N(D15) | E16: =E11+E12+E13+E14+N(E15) | F16: =F11+F12+F13+F14+N(F15) | G16: =G11+G12+G13+G14+N(G15) | H16: =H11+H12+H13+H14+N(H15) | I16: =I11+I12+I13+I14+N(I15) | J16: =J11+J12+J13+J14+N(J15) | ... N16: =N11+N12+N13+N14+N(N15)
B17: YoY Growth % | D17: =D16/C16-1 | E17: =E16/D16-1 | F17: =F16/E16-1 | G17: =G16/F16-1 | H17: =H16/G16-1 | I17: =I16/H16-1 | J17: =J16/I16-1 | K17: =K16/J16-1 | ... N17: =N16/M16-1
B18: SEGMENT PROFIT (pre-tax) & CORPORATE (FY2025A margins as reported; Financing est.)
B19: Software segment profit margin | C19: — | D19: 0.331 | E19: 0.335 | F19: 0.34 | G19: 0.345 | H19: 0.35 | I19: 0.35 | J19: 0.35 | K19: 0.35 | L19: 0.35 | M19: 0.35 | N19: 0.35
B20: Consulting segment profit margin | C20: — | D20: 0.117 | E20: 0.115 | F20: 0.12 | G20: 0.122 | H20: 0.125 | I20: 0.125 | J20: 0.125 | K20: 0.125 | L20: 0.125 | M20: 0.125 | N20: 0.125
B21: Infrastructure segment profit margin | C21: — | D21: 0.22 | E21: 0.19 | F21: 0.18 | G21: 0.2 | H21: 0.2 | I21: 0.2 | J21: 0.2 | K21: 0.2 | L21: 0.2 | M21: 0.2 | N21: 0.2
B22: Financing segment profit margin | C22: — | D22: 0.4 | E22: 0.4 | F22: 0.4 | G22: 0.4 | H22: 0.4 | I22: 0.4 | J22: 0.4 | K22: 0.4 | L22: 0.4 | M22: 0.4 | N22: 0.4
B23: Quantum contribution margin (before program opex) | C23: — | D23: — | E23: 0.6 | F23: 0.6 | G23: 0.6 | H23: 0.6 | I23: 0.6 | J23: 0.6 | K23: 0.6 | L23: 0.6 | M23: 0.6 | N23: 0.6
B24: Quantum incremental program opex above 2025 run-rate ($M) | C24: — | D24: — | E24: 200 | F24: 400 | G24: 600 | H24: 700 | I24: 800 | J24: 900 | K24: 1000 | L24: 1100 | M24: 1200 | N24: 1300
B25: Unallocated corporate, acquired-intangible amort. & other (% rev) | C25: — | E25: 0.058 | F25: 0.057 | G25: 0.056 | H25: 0.055 | I25: 0.055 | J25: 0.055 | K25: 0.055 | L25: 0.055 | M25: 0.055 | N25: 0.055
B26: CASH FLOW & TAX
B27: D&A incl. acquired-intangible amortization (% rev) | C27: — | D27: =C38/D16 | E27: 0.072 | F27: 0.07 | G27: 0.066 | H27: 0.062 | I27: 0.058 | J27: 0.054 | K27: 0.05 | L27: 0.046 | M27: 0.042 | N27: 0.038
B28: Core capex incl. capitalized software (% rev) | C28: — | D28: =C39/D16 | E28: 0.025 | F28: 0.026 | G28: 0.027 | H28: 0.028 | I28: 0.029 | J28: 0.03 | K28: 0.03 | L28: 0.03 | M28: 0.03 | N28: 0.03
B29: Quantum / Anderon foundry capex, net of CHIPS ($M) | C29: — | D29: — | E29: 200 | F29: 600 | G29: 600 | H29: 500 | I29: 300 | J29: 300 | K29: 300 | L29: 300 | M29: 300 | N29: 300
B30: Δ Working capital (% of Δ revenue) | C30: — | D30: — | E30: 0.05 | F30: 0.05 | G30: 0.05 | H30: 0.05 | I30: 0.05 | J30: 0.05 | K30: 0.05 | L30: 0.05 | M30: 0.05 | N30: 0.05
B31: Cash tax rate | C31: — | D31: — | E31: 0.15 | F31: 0.15 | G31: 0.15 | H31: 0.15 | I31: 0.15 | J31: 0.15 | K31: 0.15 | L31: 0.15 | M31: 0.15 | N31: 0.15
B34: FY2025A REPORTED (calibration)
B35: GAAP pre-tax income | C35: 10328 | D35: FY2025 release, Jan 28 2026
B36: Interest expense | C36: 1935 | D36: 2025 Annual Report
B37: GAAP EBIT (pre-tax + interest) | C37: =C35+C36 | D37: Formula
B38: Depreciation & amortization | C38: 5021
B39: Capital expenditures | C39: 1617
B40: Reported free cash flow (IBM definition) | C40: 14734 | D40: Adds back SBC; we treat SBC as a cost
B41: Stock-based compensation | C41: 1715
B43: VALUATION DATE, MARKET DATA & BALANCE SHEET
B44: Valuation date | C44: 46309 | D44: Oct 14, 2026 close
B45: FY2026 fiscal year end | C45: 46387
B46: Stub — fraction of FY2026E remaining | C46: =MAX(0,MIN(1,(C45-C44)/365)) | D46: Formula
B47: Current share price ($) | C47: 227.88 | D47: NYSE: IBM, Oct 14 2026 close
B48: 52-week high ($) | C48: 332.46
B49: 52-week low ($) | C49: 199.19
B50: Cash & marketable securities | C50: 8177 | D50: Jun 30, 2026
B51: Total debt | C51: 62000 | D51: Jun 30, 2026
B52: of which IBM Financing debt (self-funding receivables) | C52: 13000 | D52: Jun 30, 2026
B53: Core debt (total − Financing) | C53: =C51-C52 | D53: Formula — Financing profit is in segment profit
B54: Diluted shares (M) | C54: 953.3 | D54: Q2 2026 diluted
B55: Annual dividend per share ($) | C55: 6.76
B56: Analyst consensus PT ($) | C56: 242.65 | D56: 25 analysts, Oct 2026
B58: WACC, TERMINAL VALUE, RATING & SENSITIVITY
B59: Risk-free rate (10-yr UST) | C59: 0.051 | D59: ~5.1%, mid-Oct 2026
B60: Equity risk premium | C60: 0.043
B61: Levered beta (Blume-adjusted) | C61: 0.81 | D61: Raw 5-yr beta 0.72
B62: Pre-tax cost of debt | C62: 0.048 | D62: IBM senior notes
B63: Tax rate (debt shield) | C63: 0.15
B64: Core debt / total capital | C64: =C53/(C53+C47*C54) | D64: Formula — market weights
B65: Terminal growth rate | C65: 0.025
B66: Overweight if PT upside ≥ | C66: 0.1
B67: Underweight if PT upside ≤ | C67: -0.1 | D67: Otherwise Equal-Weight
B68: Round PT to nearest ($) | C68: 5
B69: Sensitivity step — WACC | C69: 0.005
B70: Sensitivity step — terminal growth | C70: 0.005
B72: SCENARIO PARAMETERS (core adjustments apply FY2027E+; quantum scale multiplies quantum revenue)
B73: Parameter | C73: Bear | D73: Base | E73: Bull | F73: Q Stalls | G73: Q Base | H73: Q Breakout | I73: Q Dominant
B74: Revenue growth adj. — Software, Consulting, Infrastructure (pp) | C74: -0.03 | D74: 0 | E74: 0.02 | F74: 0 | G74: 0 | H74: 0 | I74: 0
B75: Segment margin adj. — Software, Consulting, Infrastructure (pp) | C75: -0.02 | D75: 0 | E75: 0.015 | F75: 0 | G75: 0 | H75: 0 | I75: 0
B76: WACC adj. vs. base (pp) | C76: 0.005 | D76: 0 | E76: -0.005 | F76: 0 | G76: 0 | H76: 0 | I76: 0
B77: Terminal growth | C77: 0.02 | D77: =$C$65 | E77: 0.03 | F77: =$C$65 | G77: =$C$65 | H77: =$C$65 | I77: =$C$65
B78: Quantum revenue scale (× base path) | C78: 1 | D78: 1 | E78: 1 | F78: 0.25 | G78: 1 | H78: 3 | I78: 6
B79: Probability weight (quantum scenarios → Price Target) | F79: 0.25 | G79: 0.45 | H79: 0.22 | I79: 0.08
B80: Probability check (must = 100%) | F80: =SUM(F79:I79)
B82: Sources: IBM FY2025 results (Jan 28 2026) and 2025 Annual Report; Q2 2026 results (Jul 22 2026) and 10-Q; Confluent acquisition closed Mar 17 2026; $10B+ quantum investment plan and Anderon foundry (~$1B CHIPS + $1B IBM, Jun 2026); Starling fault-tolerant system targeted 2H 2029. Quantum revenue, margins and program costs are analyst estimates — IBM does not disclose quantum revenue (>$1B cumulative bookings since 2017).
B84: Francisco Rodriguez | Financial Modeling Portfolio | github.com/Azyo1

Sheet Operating Model
B2: IBM — Segment Operating Model & Unlevered Free Cash Flow ($M)
C3: FY2024A | D3: FY2025A | E3: FY2026E | F3: FY2027E | G3: FY2028E | H3: FY2029E | I3: FY2030E | J3: FY2031E | K3: FY2032E | L3: FY2033E | M3: FY2034E | N3: FY2035E
B4: REVENUE
B5: Software | C5: =Assumptions!C11 | D5: =Assumptions!D11 | E5: =Assumptions!E11 | F5: =Assumptions!F11 | G5: =Assumptions!G11 | H5: =Assumptions!H11 | I5: =Assumptions!I11 | J5: =Assumptions!J11 | ... N5: =Assumptions!N11
B6: Consulting | C6: =Assumptions!C12 | D6: =Assumptions!D12 | E6: =Assumptions!E12 | F6: =Assumptions!F12 | G6: =Assumptions!G12 | H6: =Assumptions!H12 | I6: =Assumptions!I12 | J6: =Assumptions!J12 | ... N6: =Assumptions!N12
B7: Infrastructure | C7: =Assumptions!C13 | D7: =Assumptions!D13 | E7: =Assumptions!E13 | F7: =Assumptions!F13 | G7: =Assumptions!G13 | H7: =Assumptions!H13 | I7: =Assumptions!I13 | J7: =Assumptions!J13 | ... N7: =Assumptions!N13
B8: Financing | C8: =Assumptions!C14 | D8: =Assumptions!D14 | E8: =Assumptions!E14 | F8: =Assumptions!F14 | G8: =Assumptions!G14 | H8: =Assumptions!H14 | I8: =Assumptions!I14 | J8: =Assumptions!J14 | ... N8: =Assumptions!N14
B9: Quantum (incremental) | C9: — | D9: — | E9: =Assumptions!E15 | F9: =Assumptions!F15 | G9: =Assumptions!G15 | H9: =Assumptions!H15 | I9: =Assumptions!I15 | J9: =Assumptions!J15 | K9: =Assumptions!K15 | L9: =Assumptions!L15 | ... N9: =Assumptions!N15
B10: Total Revenue | C10: =SUM(C5:C8)+N(C9) | D10: =SUM(D5:D8)+N(D9) | E10: =SUM(E5:E8)+N(E9) | F10: =SUM(F5:F8)+N(F9) | G10: =SUM(G5:G8)+N(G9) | H10: =SUM(H5:H8)+N(H9) | I10: =SUM(I5:I8)+N(I9) | J10: =SUM(J5:J8)+N(J9) | ... N10: =SUM(N5:N8)+N(N9)
B11: YoY Growth % | D11: =D10/C10-1 | E11: =E10/D10-1 | F11: =F10/E10-1 | G11: =G10/F10-1 | H11: =H10/G10-1 | I11: =I10/H10-1 | J11: =J10/I10-1 | K11: =K10/J10-1 | ... N11: =N10/M10-1
B12: SEGMENT PROFIT (pre-tax)
B13: Software | D13: =D5*Assumptions!D19 | E13: =E5*Assumptions!E19 | F13: =F5*Assumptions!F19 | G13: =G5*Assumptions!G19 | H13: =H5*Assumptions!H19 | I13: =I5*Assumptions!I19 | J13: =J5*Assumptions!J19 | K13: =K5*Assumptions!K19 | ... N13: =N5*Assumptions!N19
B14: Consulting | D14: =D6*Assumptions!D20 | E14: =E6*Assumptions!E20 | F14: =F6*Assumptions!F20 | G14: =G6*Assumptions!G20 | H14: =H6*Assumptions!H20 | I14: =I6*Assumptions!I20 | J14: =J6*Assumptions!J20 | K14: =K6*Assumptions!K20 | ... N14: =N6*Assumptions!N20
B15: Infrastructure | D15: =D7*Assumptions!D21 | E15: =E7*Assumptions!E21 | F15: =F7*Assumptions!F21 | G15: =G7*Assumptions!G21 | H15: =H7*Assumptions!H21 | I15: =I7*Assumptions!I21 | J15: =J7*Assumptions!J21 | K15: =K7*Assumptions!K21 | ... N15: =N7*Assumptions!N21
B16: Financing | D16: =D8*Assumptions!D22 | E16: =E8*Assumptions!E22 | F16: =F8*Assumptions!F22 | G16: =G8*Assumptions!G22 | H16: =H8*Assumptions!H22 | I16: =I8*Assumptions!I22 | J16: =J8*Assumptions!J22 | K16: =K8*Assumptions!K22 | ... N16: =N8*Assumptions!N22
B17: Quantum [rev × contribution margin − program opex] | D17: — | E17: =E9*Assumptions!E23-Assumptions!E24 | F17: =F9*Assumptions!F23-Assumptions!F24 | G17: =G9*Assumptions!G23-Assumptions!G24 | H17: =H9*Assumptions!H23-Assumptions!H24 | I17: =I9*Assumptions!I23-Assumptions!I24 | J17: =J9*Assumptions!J23-Assumptions!J24 | K17: =K9*Assumptions!K23-Assumptions!K24 | L17: =L9*Assumptions!L23-Assumptions!L24 | ... N17: =N9*Assumptions!N23-Assumptions!N24
B18: Total segment profit | D18: =SUM(D13:D16) | E18: =SUM(E13:E17) | F18: =SUM(F13:F17) | G18: =SUM(G13:G17) | H18: =SUM(H13:H17) | I18: =SUM(I13:I17) | J18: =SUM(J13:J17) | K18: =SUM(K13:K17) | L18: =SUM(L13:L17) | ... N18: =SUM(N13:N17)
B19: Less: unallocated corporate, amortization & other | D19: =-(D18-Assumptions!$C$37) | E19: =-E10*Assumptions!E25 | F19: =-F10*Assumptions!F25 | G19: =-G10*Assumptions!G25 | H19: =-H10*Assumptions!H25 | I19: =-I10*Assumptions!I25 | J19: =-J10*Assumptions!J25 | K19: =-K10*Assumptions!K25 | L19: =-L10*Assumptions!L25 | ... N19: =-N10*Assumptions!N25
B20: EBIT (GAAP basis) | D20: =D18+D19 | E20: =E18+E19 | F20: =F18+F19 | G20: =G18+G19 | H20: =H18+H19 | I20: =I18+I19 | J20: =J18+J19 | K20: =K18+K19 | ... N20: =N18+N19
B21: EBIT Margin % | D21: =D20/D10 | E21: =E20/E10 | F21: =F20/F10 | G21: =G20/G10 | H21: =H20/H10 | I21: =I20/I10 | J21: =J20/J10 | K21: =K20/K10 | ... N21: =N20/N10
B22: UNLEVERED FREE CASH FLOW (forecast; SBC treated as a cost)
B23: EBIT | E23: =E20 | F23: =F20 | G23: =G20 | H23: =H20 | I23: =I20 | J23: =J20 | K23: =K20 | L23: =L20 | ... N23: =N20
B24: Less: cash taxes | E24: =-MAX(0,E23)*Assumptions!E31 | F24: =-MAX(0,F23)*Assumptions!F31 | G24: =-MAX(0,G23)*Assumptions!G31 | H24: =-MAX(0,H23)*Assumptions!H31 | I24: =-MAX(0,I23)*Assumptions!I31 | J24: =-MAX(0,J23)*Assumptions!J31 | K24: =-MAX(0,K23)*Assumptions!K31 | L24: =-MAX(0,L23)*Assumptions!L31 | ... N24: =-MAX(0,N23)*Assumptions!N31
B25: NOPAT | E25: =E23+E24 | F25: =F23+F24 | G25: =G23+G24 | H25: =H23+H24 | I25: =I23+I24 | J25: =J23+J24 | K25: =K23+K24 | L25: =L23+L24 | ... N25: =N23+N24
B26: Plus: D&A | E26: =E10*Assumptions!E27 | F26: =F10*Assumptions!F27 | G26: =G10*Assumptions!G27 | H26: =H10*Assumptions!H27 | I26: =I10*Assumptions!I27 | J26: =J10*Assumptions!J27 | K26: =K10*Assumptions!K27 | L26: =L10*Assumptions!L27 | ... N26: =N10*Assumptions!N27
B27: Less: core capex | E27: =-E10*Assumptions!E28 | F27: =-F10*Assumptions!F28 | G27: =-G10*Assumptions!G28 | H27: =-H10*Assumptions!H28 | I27: =-I10*Assumptions!I28 | J27: =-J10*Assumptions!J28 | K27: =-K10*Assumptions!K28 | L27: =-L10*Assumptions!L28 | ... N27: =-N10*Assumptions!N28
B28: Less: quantum / Anderon capex | E28: =-Assumptions!E29 | F28: =-Assumptions!F29 | G28: =-Assumptions!G29 | H28: =-Assumptions!H29 | I28: =-Assumptions!I29 | J28: =-Assumptions!J29 | K28: =-Assumptions!K29 | L28: =-Assumptions!L29 | ... N28: =-Assumptions!N29
B29: Less: Δ working capital | E29: =-(E10-D10)*Assumptions!E30 | F29: =-(F10-E10)*Assumptions!F30 | G29: =-(G10-F10)*Assumptions!G30 | H29: =-(H10-G10)*Assumptions!H30 | I29: =-(I10-H10)*Assumptions!I30 | J29: =-(J10-I10)*Assumptions!J30 | K29: =-(K10-J10)*Assumptions!K30 | L29: =-(L10-K10)*Assumptions!L30 | ... N29: =-(N10-M10)*Assumptions!N30
B30: Unlevered Free Cash Flow | E30: =SUM(E25:E29) | F30: =SUM(F25:F29) | G30: =SUM(G25:G29) | H30: =SUM(H25:H29) | I30: =SUM(I25:I29) | J30: =SUM(J25:J29) | K30: =SUM(K25:K29) | L30: =SUM(L25:L29) | ... N30: =SUM(N25:N29)
B32: Memo: quantum standalone FCF [profit × (1 − t) − quantum capex] | E32: =E17*(1-Assumptions!E31)+E28 | F32: =F17*(1-Assumptions!F31)+F28 | G32: =G17*(1-Assumptions!G31)+G28 | H32: =H17*(1-Assumptions!H31)+H28 | I32: =I17*(1-Assumptions!I31)+I28 | J32: =J17*(1-Assumptions!J31)+J28 | K32: =K17*(1-Assumptions!K31)+K28 | L32: =L17*(1-Assumptions!L31)+L28 | ... N32: =N17*(1-Assumptions!N31)+N28
B34: FY2025A check: modeled EBIT = GAAP pre-tax + interest (corporate line is the residual)
B36: Francisco Rodriguez | Financial Modeling Portfolio | github.com/Azyo1

Sheet DCF
B2: IBM — Discounted Cash Flow Analysis ($M)
C3: Value | D3: FY2026E | E3: FY2027E | F3: FY2028E | G3: FY2029E | H3: FY2030E | I3: FY2031E | J3: FY2032E | K3: FY2033E | L3: FY2034E | M3: FY2035E
B4: WACC BUILD
B5: Risk-free rate | C5: =Assumptions!$C$59
B6: Equity risk premium | C6: =Assumptions!$C$60
B7: Levered beta | C7: =Assumptions!$C$61
B8: Cost of equity | C8: =C5+C7*C6
B9: Pre-tax cost of debt | C9: =Assumptions!$C$62
B10: Tax rate | C10: =Assumptions!$C$63
B11: After-tax cost of debt | C11: =C9*(1-C10)
B12: Core debt / total capital | C12: =Assumptions!$C$64
B13: Equity / total capital | C13: =1-C12
B14: WACC | C14: =C8*C13+C11*C12
B15: FREE CASH FLOW PROJECTION (stub + mid-year)
B16: Unlevered free cash flow | D16: ='Operating Model'!E30 | E16: ='Operating Model'!F30 | F16: ='Operating Model'!G30 | G16: ='Operating Model'!H30 | H16: ='Operating Model'!I30 | I16: ='Operating Model'!J30 | J16: ='Operating Model'!K30 | K16: ='Operating Model'!L30 | ... M16: ='Operating Model'!N30
B17: Fraction of year valued | D17: =Assumptions!$C$46 | E17: =1 | F17: =1 | G17: =1 | H17: =1 | I17: =1 | J17: =1 | K17: =1 | L17: =1 | M17: =1
B18: Discount period (years) | D18: =D17/2 | E18: =SUM($D$17:D17)+E17/2 | F18: =SUM($D$17:E17)+F17/2 | G18: =SUM($D$17:F17)+G17/2 | H18: =SUM($D$17:G17)+H17/2 | I18: =SUM($D$17:H17)+I17/2 | J18: =SUM($D$17:I17)+J17/2 | K18: =SUM($D$17:J17)+K17/2 | L18: =SUM($D$17:K17)+L17/2 | M18: =SUM($D$17:L17)+M17/2
B19: Discount factor | D19: =1/(1+$C$14)^D18 | E19: =1/(1+$C$14)^E18 | F19: =1/(1+$C$14)^F18 | G19: =1/(1+$C$14)^G18 | H19: =1/(1+$C$14)^H18 | I19: =1/(1+$C$14)^I18 | J19: =1/(1+$C$14)^J18 | K19: =1/(1+$C$14)^K18 | ... M19: =1/(1+$C$14)^M18
B20: PV of FCF | D20: =D16*D17*D19 | E20: =E16*E17*E19 | F20: =F16*F17*F19 | G20: =G16*G17*G19 | H20: =H16*H17*H19 | I20: =I16*I17*I19 | J20: =J16*J17*J19 | K20: =K16*K17*K19 | ... M20: =M16*M17*M19
B21: Quantum standalone FCF (memo) | D21: ='Operating Model'!E32 | E21: ='Operating Model'!F32 | F21: ='Operating Model'!G32 | G21: ='Operating Model'!H32 | H21: ='Operating Model'!I32 | I21: ='Operating Model'!J32 | J21: ='Operating Model'!K32 | K21: ='Operating Model'!L32 | ... M21: ='Operating Model'!N32
B22: PV of quantum FCF | D22: =D21*D17*D19 | E22: =E21*E17*E19 | F22: =F21*F17*F19 | G22: =G21*G17*G19 | H22: =H21*H17*H19 | I22: =I21*I17*I19 | J22: =J21*J17*J19 | K22: =K21*K17*K19 | ... M22: =M21*M17*M19
B23: TERMINAL VALUE & EQUITY BRIDGE
B24: Sum of PV (FCFs) | C24: =SUM(D20:M20)
B25: Terminal growth (g) | C25: =Assumptions!$C$65
B26: Terminal value [FCF × (1+g) / (WACC − g)] | C26: =M16*(1+C25)/(C14-C25)
B27: PV of terminal value | C27: =C26*M19
B28: Enterprise value | C28: =C24+C27
B29: TV as % of EV | C29: =C27/C28
B30: EV / FY2027E EBITDA (implied) | C30: =C28/('Operating Model'!F20+'Operating Model'!F26)
B31: Plus: cash & marketable securities | C31: =Assumptions!$C$50
B32: Less: core debt (ex-Financing) | C32: =Assumptions!$C$53
B33: Equity value | C33: =C28+C31-C32
B34: Diluted shares (M) | C34: =Assumptions!$C$54
B35: DCF value per share (Base) | C35: =C33/C34
B36: Current share price | C36: =Assumptions!$C$47
B37: DCF upside / (downside) | C37: =C35/C36-1
B38: Quantum value per share [PV quantum FCF + quantum TV] | C38: =(SUM(D22:M22)+M21*(1+C25)/(C14-C25)*M19)/C34
B39: Core IBM value per share (ex-quantum) | C39: =C35-C38
B40: Probability-weighted value (quantum scenarios) | C40: =Sensitivity!$C$40
B41: ★ PRICE TARGET | C41: =ROUND(C40/Assumptions!$C$68,0)*Assumptions!$C$68
B42: PT upside / (downside) | C42: =C41/C36-1
B43: Total return incl. dividend yield | C43: =C42+Assumptions!$C$55/C36
B44: ★ RATING | C44: =IF(C42>=Assumptions!$C$66,"OVERWEIGHT",IF(C42<=Assumptions!$C$67,"UNDERWEIGHT","EQUAL-WEIGHT"))
B47: Francisco Rodriguez | Financial Modeling Portfolio | github.com/Azyo1

Sheet Sensitivity
B2: IBM — Sensitivity & Scenario Analysis (live formulas)
B3: TABLE 1 — Base DCF value per share: WACC × terminal growth
B4: g ↓ | WACC → | C4: =DCF!$C$14+(-3)*Assumptions!$C$69 | D4: =DCF!$C$14+(-2)*Assumptions!$C$69 | E4: =DCF!$C$14+(-1)*Assumptions!$C$69 | F4: =DCF!$C$14+(0)*Assumptions!$C$69 | G4: =DCF!$C$14+(1)*Assumptions!$C$69 | H4: =DCF!$C$14+(2)*Assumptions!$C$69 | I4: =DCF!$C$14+(3)*Assumptions!$C$69
B5: =Assumptions!$C$65+(-2)*Assumptions!$C$70 | C5: =(DCF!D$16*DCF!D$17/(1+C$4)^DCF!D$18+DCF!E$16*DCF!E$17/(1+C$4)^DCF!E$18+DCF!F$16*DCF!F$17/(1+C$4)^DCF!F$18+DCF!G$16*DCF!G$17/(1+C$4)^DCF!G$18+DCF!H$16*DCF!H$17/(1+C$4)^DCF!H$18+DCF!I$16*DCF!I$17/(1+C$4)^DCF!I$18+DCF!J$16*DCF!J$17/(1+C$4)^DCF!J$18+DCF!K$16*DCF!K$17/(1+C$4)^DCF!K$18+DCF!L$16*DCF!L$17/(1+C$4)^DCF!L$18+DCF!M$16*DCF!M$17/(1+C$4)^DCF!M$18+DCF!$M$16*(1+$B5)/(C$4-$B5)/(1+C$4)^DCF!$M$18+DCF!$C$31-DCF!$C$32)/DCF!$C$34 | D5: =(DCF!D$16*DCF!D$17/(1+D$4)^DCF!D$18+DCF!E$16*DCF!E$17/(1+D$4)^DCF!E$18+DCF!F$16*DCF!F$17/(1+D$4)^DCF!F$18+DCF!G$16*DCF!G$17/(1+D$4)^DCF!G$18+DCF!H$16*DCF!H$17/(1+D$4)^DCF!H$18+DCF!I$16*DCF!I$17/(1+D$4)^DCF!I$18+DCF!J$16*DCF!J$17/(1+D$4)^DCF!J$18+DCF!K$16*DCF!K$17/(1+D$4)^DCF!K$18+DCF!L$16*DCF!L$17/(1+D$4)^DCF!L$18+DCF!M$16*DCF!M$17/(1+D$4)^DCF!M$18+DCF!$M$16*(1+$B5)/(D$4-$B5)/(1+D$4)^DCF!$M$18+DCF!$C$31-DCF!$C$32)/DCF!$C$34 | E5: =(DCF!D$16*DCF!D$17/(1+E$4)^DCF!D$18+DCF!E$16*DCF!E$17/(1+E$4)^DCF!E$18+DCF!F$16*DCF!F$17/(1+E$4)^DCF!F$18+DCF!G$16*DCF!G$17/(1+E$4)^DCF!G$18+DCF!H$16*DCF!H$17/(1+E$4)^DCF!H$18+DCF!I$16*DCF!I$17/(1+E$4)^DCF!I$18+DCF!J$16*DCF!J$17/(1+E$4)^DCF!J$18+DCF!K$16*DCF!K$17/(1+E$4)^DCF!K$18+DCF!L$16*DCF!L$17/(1+E$4)^DCF!L$18+DCF!M$16*DCF!M$17/(1+E$4)^DCF!M$18+DCF!$M$16*(1+$B5)/(E$4-$B5)/(1+E$4)^DCF!$M$18+DCF!$C$31-DCF!$C$32)/DCF!$C$34 | F5: =(DCF!D$16*DCF!D$17/(1+F$4)^DCF!D$18+DCF!E$16*DCF!E$17/(1+F$4)^DCF!E$18+DCF!F$16*DCF!F$17/(1+F$4)^DCF!F$18+DCF!G$16*DCF!G$17/(1+F$4)^DCF!G$18+DCF!H$16*DCF!H$17/(1+F$4)^DCF!H$18+DCF!I$16*DCF!I$17/(1+F$4)^DCF!I$18+DCF!J$16*DCF!J$17/(1+F$4)^DCF!J$18+DCF!K$16*DCF!K$17/(1+F$4)^DCF!K$18+DCF!L$16*DCF!L$17/(1+F$4)^DCF!L$18+DCF!M$16*DCF!M$17/(1+F$4)^DCF!M$18+DCF!$M$16*(1+$B5)/(F$4-$B5)/(1+F$4)^DCF!$M$18+DCF!$C$31-DCF!$C$32)/DCF!$C$34 | G5: =(DCF!D$16*DCF!D$17/(1+G$4)^DCF!D$18+DCF!E$16*DCF!E$17/(1+G$4)^DCF!E$18+DCF!F$16*DCF!F$17/(1+G$4)^DCF!F$18+DCF!G$16*DCF!G$17/(1+G$4)^DCF!G$18+DCF!H$16*DCF!H$17/(1+G$4)^DCF!H$18+DCF!I$16*DCF!I$17/(1+G$4)^DCF!I$18+DCF!J$16*DCF!J$17/(1+G$4)^DCF!J$18+DCF!K$16*DCF!K$17/(1+G$4)^DCF!K$18+DCF!L$16*DCF!L$17/(1+G$4)^DCF!L$18+DCF!M$16*DCF!M$17/(1+G$4)^DCF!M$18+DCF!$M$16*(1+$B5)/(G$4-$B5)/(1+G$4)^DCF!$M$18+DCF!$C$31-DCF!$C$32)/DCF!$C$34 | H5: =(DCF!D$16*DCF!D$17/(1+H$4)^DCF!D$18+DCF!E$16*DCF!E$17/(1+H$4)^DCF!E$18+DCF!F$16*DCF!F$17/(1+H$4)^DCF!F$18+DCF!G$16*DCF!G$17/(1+H$4)^DCF!G$18+DCF!H$16*DCF!H$17/(1+H$4)^DCF!H$18+DCF!I$16*DCF!I$17/(1+H$4)^DCF!I$18+DCF!J$16*DCF!J$17/(1+H$4)^DCF!J$18+DCF!K$16*DCF!K$17/(1+H$4)^DCF!K$18+DCF!L$16*DCF!L$17/(1+H$4)^DCF!L$18+DCF!M$16*DCF!M$17/(1+H$4)^DCF!M$18+DCF!$M$16*(1+$B5)/(H$4-$B5)/(1+H$4)^DCF!$M$18+DCF!$C$31-DCF!$C$32)/DCF!$C$34 | I5: =(DCF!D$16*DCF!D$17/(1+I$4)^DCF!D$18+DCF!E$16*DCF!E$17/(1+I$4)^DCF!E$18+DCF!F$16*DCF!F$17/(1+I$4)^DCF!F$18+DCF!G$16*DCF!G$17/(1+I$4)^DCF!G$18+DCF!H$16*DCF!H$17/(1+I$4)^DCF!H$18+DCF!I$16*DCF!I$17/(1+I$4)^DCF!I$18+DCF!J$16*DCF!J$17/(1+I$4)^DCF!J$18+DCF!K$16*DCF!K$17/(1+I$4)^DCF!K$18+DCF!L$16*DCF!L$17/(1+I$4)^DCF!L$18+DCF!M$16*DCF!M$17/(1+I$4)^DCF!M$18+DCF!$M$16*(1+$B5)/(I$4-$B5)/(1+I$4)^DCF!$M$18+DCF!$C$31-DCF!$C$32)/DCF!$C$34
B6: =Assumptions!$C$65+(-1)*Assumptions!$C$70 | C6: =(DCF!D$16*DCF!D$17/(1+C$4)^DCF!D$18+DCF!E$16*DCF!E$17/(1+C$4)^DCF!E$18+DCF!F$16*DCF!F$17/(1+C$4)^DCF!F$18+DCF!G$16*DCF!G$17/(1+C$4)^DCF!G$18+DCF!H$16*DCF!H$17/(1+C$4)^DCF!H$18+DCF!I$16*DCF!I$17/(1+C$4)^DCF!I$18+DCF!J$16*DCF!J$17/(1+C$4)^DCF!J$18+DCF!K$16*DCF!K$17/(1+C$4)^DCF!K$18+DCF!L$16*DCF!L$17/(1+C$4)^DCF!L$18+DCF!M$16*DCF!M$17/(1+C$4)^DCF!M$18+DCF!$M$16*(1+$B6)/(C$4-$B6)/(1+C$4)^DCF!$M$18+DCF!$C$31-DCF!$C$32)/DCF!$C$34 | D6: =(DCF!D$16*DCF!D$17/(1+D$4)^DCF!D$18+DCF!E$16*DCF!E$17/(1+D$4)^DCF!E$18+DCF!F$16*DCF!F$17/(1+D$4)^DCF!F$18+DCF!G$16*DCF!G$17/(1+D$4)^DCF!G$18+DCF!H$16*DCF!H$17/(1+D$4)^DCF!H$18+DCF!I$16*DCF!I$17/(1+D$4)^DCF!I$18+DCF!J$16*DCF!J$17/(1+D$4)^DCF!J$18+DCF!K$16*DCF!K$17/(1+D$4)^DCF!K$18+DCF!L$16*DCF!L$17/(1+D$4)^DCF!L$18+DCF!M$16*DCF!M$17/(1+D$4)^DCF!M$18+DCF!$M$16*(1+$B6)/(D$4-$B6)/(1+D$4)^DCF!$M$18+DCF!$C$31-DCF!$C$32)/DCF!$C$34 | E6: =(DCF!D$16*DCF!D$17/(1+E$4)^DCF!D$18+DCF!E$16*DCF!E$17/(1+E$4)^DCF!E$18+DCF!F$16*DCF!F$17/(1+E$4)^DCF!F$18+DCF!G$16*DCF!G$17/(1+E$4)^DCF!G$18+DCF!H$16*DCF!H$17/(1+E$4)^DCF!H$18+DCF!I$16*DCF!I$17/(1+E$4)^DCF!I$18+DCF!J$16*DCF!J$17/(1+E$4)^DCF!J$18+DCF!K$16*DCF!K$17/(1+E$4)^DCF!K$18+DCF!L$16*DCF!L$17/(1+E$4)^DCF!L$18+DCF!M$16*DCF!M$17/(1+E$4)^DCF!M$18+DCF!$M$16*(1+$B6)/(E$4-$B6)/(1+E$4)^DCF!$M$18+DCF!$C$31-DCF!$C$32)/DCF!$C$34 | F6: =(DCF!D$16*DCF!D$17/(1+F$4)^DCF!D$18+DCF!E$16*DCF!E$17/(1+F$4)^DCF!E$18+DCF!F$16*DCF!F$17/(1+F$4)^DCF!F$18+DCF!G$16*DCF!G$17/(1+F$4)^DCF!G$18+DCF!H$16*DCF!H$17/(1+F$4)^DCF!H$18+DCF!I$16*DCF!I$17/(1+F$4)^DCF!I$18+DCF!J$16*DCF!J$17/(1+F$4)^DCF!J$18+DCF!K$16*DCF!K$17/(1+F$4)^DCF!K$18+DCF!L$16*DCF!L$17/(1+F$4)^DCF!L$18+DCF!M$16*DCF!M$17/(1+F$4)^DCF!M$18+DCF!$M$16*(1+$B6)/(F$4-$B6)/(1+F$4)^DCF!$M$18+DCF!$C$31-DCF!$C$32)/DCF!$C$34 | G6: =(DCF!D$16*DCF!D$17/(1+G$4)^DCF!D$18+DCF!E$16*DCF!E$17/(1+G$4)^DCF!E$18+DCF!F$16*DCF!F$17/(1+G$4)^DCF!F$18+DCF!G$16*DCF!G$17/(1+G$4)^DCF!G$18+DCF!H$16*DCF!H$17/(1+G$4)^DCF!H$18+DCF!I$16*DCF!I$17/(1+G$4)^DCF!I$18+DCF!J$16*DCF!J$17/(1+G$4)^DCF!J$18+DCF!K$16*DCF!K$17/(1+G$4)^DCF!K$18+DCF!L$16*DCF!L$17/(1+G$4)^DCF!L$18+DCF!M$16*DCF!M$17/(1+G$4)^DCF!M$18+DCF!$M$16*(1+$B6)/(G$4-$B6)/(1+G$4)^DCF!$M$18+DCF!$C$31-DCF!$C$32)/DCF!$C$34 | H6: =(DCF!D$16*DCF!D$17/(1+H$4)^DCF!D$18+DCF!E$16*DCF!E$17/(1+H$4)^DCF!E$18+DCF!F$16*DCF!F$17/(1+H$4)^DCF!F$18+DCF!G$16*DCF!G$17/(1+H$4)^DCF!G$18+DCF!H$16*DCF!H$17/(1+H$4)^DCF!H$18+DCF!I$16*DCF!I$17/(1+H$4)^DCF!I$18+DCF!J$16*DCF!J$17/(1+H$4)^DCF!J$18+DCF!K$16*DCF!K$17/(1+H$4)^DCF!K$18+DCF!L$16*DCF!L$17/(1+H$4)^DCF!L$18+DCF!M$16*DCF!M$17/(1+H$4)^DCF!M$18+DCF!$M$16*(1+$B6)/(H$4-$B6)/(1+H$4)^DCF!$M$18+DCF!$C$31-DCF!$C$32)/DCF!$C$34 | I6: =(DCF!D$16*DCF!D$17/(1+I$4)^DCF!D$18+DCF!E$16*DCF!E$17/(1+I$4)^DCF!E$18+DCF!F$16*DCF!F$17/(1+I$4)^DCF!F$18+DCF!G$16*DCF!G$17/(1+I$4)^DCF!G$18+DCF!H$16*DCF!H$17/(1+I$4)^DCF!H$18+DCF!I$16*DCF!I$17/(1+I$4)^DCF!I$18+DCF!J$16*DCF!J$17/(1+I$4)^DCF!J$18+DCF!K$16*DCF!K$17/(1+I$4)^DCF!K$18+DCF!L$16*DCF!L$17/(1+I$4)^DCF!L$18+DCF!M$16*DCF!M$17/(1+I$4)^DCF!M$18+DCF!$M$16*(1+$B6)/(I$4-$B6)/(1+I$4)^DCF!$M$18+DCF!$C$31-DCF!$C$32)/DCF!$C$34
B7: =Assumptions!$C$65+(0)*Assumptions!$C$70 | C7: =(DCF!D$16*DCF!D$17/(1+C$4)^DCF!D$18+DCF!E$16*DCF!E$17/(1+C$4)^DCF!E$18+DCF!F$16*DCF!F$17/(1+C$4)^DCF!F$18+DCF!G$16*DCF!G$17/(1+C$4)^DCF!G$18+DCF!H$16*DCF!H$17/(1+C$4)^DCF!H$18+DCF!I$16*DCF!I$17/(1+C$4)^DCF!I$18+DCF!J$16*DCF!J$17/(1+C$4)^DCF!J$18+DCF!K$16*DCF!K$17/(1+C$4)^DCF!K$18+DCF!L$16*DCF!L$17/(1+C$4)^DCF!L$18+DCF!M$16*DCF!M$17/(1+C$4)^DCF!M$18+DCF!$M$16*(1+$B7)/(C$4-$B7)/(1+C$4)^DCF!$M$18+DCF!$C$31-DCF!$C$32)/DCF!$C$34 | D7: =(DCF!D$16*DCF!D$17/(1+D$4)^DCF!D$18+DCF!E$16*DCF!E$17/(1+D$4)^DCF!E$18+DCF!F$16*DCF!F$17/(1+D$4)^DCF!F$18+DCF!G$16*DCF!G$17/(1+D$4)^DCF!G$18+DCF!H$16*DCF!H$17/(1+D$4)^DCF!H$18+DCF!I$16*DCF!I$17/(1+D$4)^DCF!I$18+DCF!J$16*DCF!J$17/(1+D$4)^DCF!J$18+DCF!K$16*DCF!K$17/(1+D$4)^DCF!K$18+DCF!L$16*DCF!L$17/(1+D$4)^DCF!L$18+DCF!M$16*DCF!M$17/(1+D$4)^DCF!M$18+DCF!$M$16*(1+$B7)/(D$4-$B7)/(1+D$4)^DCF!$M$18+DCF!$C$31-DCF!$C$32)/DCF!$C$34 | E7: =(DCF!D$16*DCF!D$17/(1+E$4)^DCF!D$18+DCF!E$16*DCF!E$17/(1+E$4)^DCF!E$18+DCF!F$16*DCF!F$17/(1+E$4)^DCF!F$18+DCF!G$16*DCF!G$17/(1+E$4)^DCF!G$18+DCF!H$16*DCF!H$17/(1+E$4)^DCF!H$18+DCF!I$16*DCF!I$17/(1+E$4)^DCF!I$18+DCF!J$16*DCF!J$17/(1+E$4)^DCF!J$18+DCF!K$16*DCF!K$17/(1+E$4)^DCF!K$18+DCF!L$16*DCF!L$17/(1+E$4)^DCF!L$18+DCF!M$16*DCF!M$17/(1+E$4)^DCF!M$18+DCF!$M$16*(1+$B7)/(E$4-$B7)/(1+E$4)^DCF!$M$18+DCF!$C$31-DCF!$C$32)/DCF!$C$34 | F7: =(DCF!D$16*DCF!D$17/(1+F$4)^DCF!D$18+DCF!E$16*DCF!E$17/(1+F$4)^DCF!E$18+DCF!F$16*DCF!F$17/(1+F$4)^DCF!F$18+DCF!G$16*DCF!G$17/(1+F$4)^DCF!G$18+DCF!H$16*DCF!H$17/(1+F$4)^DCF!H$18+DCF!I$16*DCF!I$17/(1+F$4)^DCF!I$18+DCF!J$16*DCF!J$17/(1+F$4)^DCF!J$18+DCF!K$16*DCF!K$17/(1+F$4)^DCF!K$18+DCF!L$16*DCF!L$17/(1+F$4)^DCF!L$18+DCF!M$16*DCF!M$17/(1+F$4)^DCF!M$18+DCF!$M$16*(1+$B7)/(F$4-$B7)/(1+F$4)^DCF!$M$18+DCF!$C$31-DCF!$C$32)/DCF!$C$34 | G7: =(DCF!D$16*DCF!D$17/(1+G$4)^DCF!D$18+DCF!E$16*DCF!E$17/(1+G$4)^DCF!E$18+DCF!F$16*DCF!F$17/(1+G$4)^DCF!F$18+DCF!G$16*DCF!G$17/(1+G$4)^DCF!G$18+DCF!H$16*DCF!H$17/(1+G$4)^DCF!H$18+DCF!I$16*DCF!I$17/(1+G$4)^DCF!I$18+DCF!J$16*DCF!J$17/(1+G$4)^DCF!J$18+DCF!K$16*DCF!K$17/(1+G$4)^DCF!K$18+DCF!L$16*DCF!L$17/(1+G$4)^DCF!L$18+DCF!M$16*DCF!M$17/(1+G$4)^DCF!M$18+DCF!$M$16*(1+$B7)/(G$4-$B7)/(1+G$4)^DCF!$M$18+DCF!$C$31-DCF!$C$32)/DCF!$C$34 | H7: =(DCF!D$16*DCF!D$17/(1+H$4)^DCF!D$18+DCF!E$16*DCF!E$17/(1+H$4)^DCF!E$18+DCF!F$16*DCF!F$17/(1+H$4)^DCF!F$18+DCF!G$16*DCF!G$17/(1+H$4)^DCF!G$18+DCF!H$16*DCF!H$17/(1+H$4)^DCF!H$18+DCF!I$16*DCF!I$17/(1+H$4)^DCF!I$18+DCF!J$16*DCF!J$17/(1+H$4)^DCF!J$18+DCF!K$16*DCF!K$17/(1+H$4)^DCF!K$18+DCF!L$16*DCF!L$17/(1+H$4)^DCF!L$18+DCF!M$16*DCF!M$17/(1+H$4)^DCF!M$18+DCF!$M$16*(1+$B7)/(H$4-$B7)/(1+H$4)^DCF!$M$18+DCF!$C$31-DCF!$C$32)/DCF!$C$34 | I7: =(DCF!D$16*DCF!D$17/(1+I$4)^DCF!D$18+DCF!E$16*DCF!E$17/(1+I$4)^DCF!E$18+DCF!F$16*DCF!F$17/(1+I$4)^DCF!F$18+DCF!G$16*DCF!G$17/(1+I$4)^DCF!G$18+DCF!H$16*DCF!H$17/(1+I$4)^DCF!H$18+DCF!I$16*DCF!I$17/(1+I$4)^DCF!I$18+DCF!J$16*DCF!J$17/(1+I$4)^DCF!J$18+DCF!K$16*DCF!K$17/(1+I$4)^DCF!K$18+DCF!L$16*DCF!L$17/(1+I$4)^DCF!L$18+DCF!M$16*DCF!M$17/(1+I$4)^DCF!M$18+DCF!$M$16*(1+$B7)/(I$4-$B7)/(1+I$4)^DCF!$M$18+DCF!$C$31-DCF!$C$32)/DCF!$C$34
B8: =Assumptions!$C$65+(1)*Assumptions!$C$70 | C8: =(DCF!D$16*DCF!D$17/(1+C$4)^DCF!D$18+DCF!E$16*DCF!E$17/(1+C$4)^DCF!E$18+DCF!F$16*DCF!F$17/(1+C$4)^DCF!F$18+DCF!G$16*DCF!G$17/(1+C$4)^DCF!G$18+DCF!H$16*DCF!H$17/(1+C$4)^DCF!H$18+DCF!I$16*DCF!I$17/(1+C$4)^DCF!I$18+DCF!J$16*DCF!J$17/(1+C$4)^DCF!J$18+DCF!K$16*DCF!K$17/(1+C$4)^DCF!K$18+DCF!L$16*DCF!L$17/(1+C$4)^DCF!L$18+DCF!M$16*DCF!M$17/(1+C$4)^DCF!M$18+DCF!$M$16*(1+$B8)/(C$4-$B8)/(1+C$4)^DCF!$M$18+DCF!$C$31-DCF!$C$32)/DCF!$C$34 | D8: =(DCF!D$16*DCF!D$17/(1+D$4)^DCF!D$18+DCF!E$16*DCF!E$17/(1+D$4)^DCF!E$18+DCF!F$16*DCF!F$17/(1+D$4)^DCF!F$18+DCF!G$16*DCF!G$17/(1+D$4)^DCF!G$18+DCF!H$16*DCF!H$17/(1+D$4)^DCF!H$18+DCF!I$16*DCF!I$17/(1+D$4)^DCF!I$18+DCF!J$16*DCF!J$17/(1+D$4)^DCF!J$18+DCF!K$16*DCF!K$17/(1+D$4)^DCF!K$18+DCF!L$16*DCF!L$17/(1+D$4)^DCF!L$18+DCF!M$16*DCF!M$17/(1+D$4)^DCF!M$18+DCF!$M$16*(1+$B8)/(D$4-$B8)/(1+D$4)^DCF!$M$18+DCF!$C$31-DCF!$C$32)/DCF!$C$34 | E8: =(DCF!D$16*DCF!D$17/(1+E$4)^DCF!D$18+DCF!E$16*DCF!E$17/(1+E$4)^DCF!E$18+DCF!F$16*DCF!F$17/(1+E$4)^DCF!F$18+DCF!G$16*DCF!G$17/(1+E$4)^DCF!G$18+DCF!H$16*DCF!H$17/(1+E$4)^DCF!H$18+DCF!I$16*DCF!I$17/(1+E$4)^DCF!I$18+DCF!J$16*DCF!J$17/(1+E$4)^DCF!J$18+DCF!K$16*DCF!K$17/(1+E$4)^DCF!K$18+DCF!L$16*DCF!L$17/(1+E$4)^DCF!L$18+DCF!M$16*DCF!M$17/(1+E$4)^DCF!M$18+DCF!$M$16*(1+$B8)/(E$4-$B8)/(1+E$4)^DCF!$M$18+DCF!$C$31-DCF!$C$32)/DCF!$C$34 | F8: =(DCF!D$16*DCF!D$17/(1+F$4)^DCF!D$18+DCF!E$16*DCF!E$17/(1+F$4)^DCF!E$18+DCF!F$16*DCF!F$17/(1+F$4)^DCF!F$18+DCF!G$16*DCF!G$17/(1+F$4)^DCF!G$18+DCF!H$16*DCF!H$17/(1+F$4)^DCF!H$18+DCF!I$16*DCF!I$17/(1+F$4)^DCF!I$18+DCF!J$16*DCF!J$17/(1+F$4)^DCF!J$18+DCF!K$16*DCF!K$17/(1+F$4)^DCF!K$18+DCF!L$16*DCF!L$17/(1+F$4)^DCF!L$18+DCF!M$16*DCF!M$17/(1+F$4)^DCF!M$18+DCF!$M$16*(1+$B8)/(F$4-$B8)/(1+F$4)^DCF!$M$18+DCF!$C$31-DCF!$C$32)/DCF!$C$34 | G8: =(DCF!D$16*DCF!D$17/(1+G$4)^DCF!D$18+DCF!E$16*DCF!E$17/(1+G$4)^DCF!E$18+DCF!F$16*DCF!F$17/(1+G$4)^DCF!F$18+DCF!G$16*DCF!G$17/(1+G$4)^DCF!G$18+DCF!H$16*DCF!H$17/(1+G$4)^DCF!H$18+DCF!I$16*DCF!I$17/(1+G$4)^DCF!I$18+DCF!J$16*DCF!J$17/(1+G$4)^DCF!J$18+DCF!K$16*DCF!K$17/(1+G$4)^DCF!K$18+DCF!L$16*DCF!L$17/(1+G$4)^DCF!L$18+DCF!M$16*DCF!M$17/(1+G$4)^DCF!M$18+DCF!$M$16*(1+$B8)/(G$4-$B8)/(1+G$4)^DCF!$M$18+DCF!$C$31-DCF!$C$32)/DCF!$C$34 | H8: =(DCF!D$16*DCF!D$17/(1+H$4)^DCF!D$18+DCF!E$16*DCF!E$17/(1+H$4)^DCF!E$18+DCF!F$16*DCF!F$17/(1+H$4)^DCF!F$18+DCF!G$16*DCF!G$17/(1+H$4)^DCF!G$18+DCF!H$16*DCF!H$17/(1+H$4)^DCF!H$18+DCF!I$16*DCF!I$17/(1+H$4)^DCF!I$18+DCF!J$16*DCF!J$17/(1+H$4)^DCF!J$18+DCF!K$16*DCF!K$17/(1+H$4)^DCF!K$18+DCF!L$16*DCF!L$17/(1+H$4)^DCF!L$18+DCF!M$16*DCF!M$17/(1+H$4)^DCF!M$18+DCF!$M$16*(1+$B8)/(H$4-$B8)/(1+H$4)^DCF!$M$18+DCF!$C$31-DCF!$C$32)/DCF!$C$34 | I8: =(DCF!D$16*DCF!D$17/(1+I$4)^DCF!D$18+DCF!E$16*DCF!E$17/(1+I$4)^DCF!E$18+DCF!F$16*DCF!F$17/(1+I$4)^DCF!F$18+DCF!G$16*DCF!G$17/(1+I$4)^DCF!G$18+DCF!H$16*DCF!H$17/(1+I$4)^DCF!H$18+DCF!I$16*DCF!I$17/(1+I$4)^DCF!I$18+DCF!J$16*DCF!J$17/(1+I$4)^DCF!J$18+DCF!K$16*DCF!K$17/(1+I$4)^DCF!K$18+DCF!L$16*DCF!L$17/(1+I$4)^DCF!L$18+DCF!M$16*DCF!M$17/(1+I$4)^DCF!M$18+DCF!$M$16*(1+$B8)/(I$4-$B8)/(1+I$4)^DCF!$M$18+DCF!$C$31-DCF!$C$32)/DCF!$C$34
B9: =Assumptions!$C$65+(2)*Assumptions!$C$70 | C9: =(DCF!D$16*DCF!D$17/(1+C$4)^DCF!D$18+DCF!E$16*DCF!E$17/(1+C$4)^DCF!E$18+DCF!F$16*DCF!F$17/(1+C$4)^DCF!F$18+DCF!G$16*DCF!G$17/(1+C$4)^DCF!G$18+DCF!H$16*DCF!H$17/(1+C$4)^DCF!H$18+DCF!I$16*DCF!I$17/(1+C$4)^DCF!I$18+DCF!J$16*DCF!J$17/(1+C$4)^DCF!J$18+DCF!K$16*DCF!K$17/(1+C$4)^DCF!K$18+DCF!L$16*DCF!L$17/(1+C$4)^DCF!L$18+DCF!M$16*DCF!M$17/(1+C$4)^DCF!M$18+DCF!$M$16*(1+$B9)/(C$4-$B9)/(1+C$4)^DCF!$M$18+DCF!$C$31-DCF!$C$32)/DCF!$C$34 | D9: =(DCF!D$16*DCF!D$17/(1+D$4)^DCF!D$18+DCF!E$16*DCF!E$17/(1+D$4)^DCF!E$18+DCF!F$16*DCF!F$17/(1+D$4)^DCF!F$18+DCF!G$16*DCF!G$17/(1+D$4)^DCF!G$18+DCF!H$16*DCF!H$17/(1+D$4)^DCF!H$18+DCF!I$16*DCF!I$17/(1+D$4)^DCF!I$18+DCF!J$16*DCF!J$17/(1+D$4)^DCF!J$18+DCF!K$16*DCF!K$17/(1+D$4)^DCF!K$18+DCF!L$16*DCF!L$17/(1+D$4)^DCF!L$18+DCF!M$16*DCF!M$17/(1+D$4)^DCF!M$18+DCF!$M$16*(1+$B9)/(D$4-$B9)/(1+D$4)^DCF!$M$18+DCF!$C$31-DCF!$C$32)/DCF!$C$34 | E9: =(DCF!D$16*DCF!D$17/(1+E$4)^DCF!D$18+DCF!E$16*DCF!E$17/(1+E$4)^DCF!E$18+DCF!F$16*DCF!F$17/(1+E$4)^DCF!F$18+DCF!G$16*DCF!G$17/(1+E$4)^DCF!G$18+DCF!H$16*DCF!H$17/(1+E$4)^DCF!H$18+DCF!I$16*DCF!I$17/(1+E$4)^DCF!I$18+DCF!J$16*DCF!J$17/(1+E$4)^DCF!J$18+DCF!K$16*DCF!K$17/(1+E$4)^DCF!K$18+DCF!L$16*DCF!L$17/(1+E$4)^DCF!L$18+DCF!M$16*DCF!M$17/(1+E$4)^DCF!M$18+DCF!$M$16*(1+$B9)/(E$4-$B9)/(1+E$4)^DCF!$M$18+DCF!$C$31-DCF!$C$32)/DCF!$C$34 | F9: =(DCF!D$16*DCF!D$17/(1+F$4)^DCF!D$18+DCF!E$16*DCF!E$17/(1+F$4)^DCF!E$18+DCF!F$16*DCF!F$17/(1+F$4)^DCF!F$18+DCF!G$16*DCF!G$17/(1+F$4)^DCF!G$18+DCF!H$16*DCF!H$17/(1+F$4)^DCF!H$18+DCF!I$16*DCF!I$17/(1+F$4)^DCF!I$18+DCF!J$16*DCF!J$17/(1+F$4)^DCF!J$18+DCF!K$16*DCF!K$17/(1+F$4)^DCF!K$18+DCF!L$16*DCF!L$17/(1+F$4)^DCF!L$18+DCF!M$16*DCF!M$17/(1+F$4)^DCF!M$18+DCF!$M$16*(1+$B9)/(F$4-$B9)/(1+F$4)^DCF!$M$18+DCF!$C$31-DCF!$C$32)/DCF!$C$34 | G9: =(DCF!D$16*DCF!D$17/(1+G$4)^DCF!D$18+DCF!E$16*DCF!E$17/(1+G$4)^DCF!E$18+DCF!F$16*DCF!F$17/(1+G$4)^DCF!F$18+DCF!G$16*DCF!G$17/(1+G$4)^DCF!G$18+DCF!H$16*DCF!H$17/(1+G$4)^DCF!H$18+DCF!I$16*DCF!I$17/(1+G$4)^DCF!I$18+DCF!J$16*DCF!J$17/(1+G$4)^DCF!J$18+DCF!K$16*DCF!K$17/(1+G$4)^DCF!K$18+DCF!L$16*DCF!L$17/(1+G$4)^DCF!L$18+DCF!M$16*DCF!M$17/(1+G$4)^DCF!M$18+DCF!$M$16*(1+$B9)/(G$4-$B9)/(1+G$4)^DCF!$M$18+DCF!$C$31-DCF!$C$32)/DCF!$C$34 | H9: =(DCF!D$16*DCF!D$17/(1+H$4)^DCF!D$18+DCF!E$16*DCF!E$17/(1+H$4)^DCF!E$18+DCF!F$16*DCF!F$17/(1+H$4)^DCF!F$18+DCF!G$16*DCF!G$17/(1+H$4)^DCF!G$18+DCF!H$16*DCF!H$17/(1+H$4)^DCF!H$18+DCF!I$16*DCF!I$17/(1+H$4)^DCF!I$18+DCF!J$16*DCF!J$17/(1+H$4)^DCF!J$18+DCF!K$16*DCF!K$17/(1+H$4)^DCF!K$18+DCF!L$16*DCF!L$17/(1+H$4)^DCF!L$18+DCF!M$16*DCF!M$17/(1+H$4)^DCF!M$18+DCF!$M$16*(1+$B9)/(H$4-$B9)/(1+H$4)^DCF!$M$18+DCF!$C$31-DCF!$C$32)/DCF!$C$34 | I9: =(DCF!D$16*DCF!D$17/(1+I$4)^DCF!D$18+DCF!E$16*DCF!E$17/(1+I$4)^DCF!E$18+DCF!F$16*DCF!F$17/(1+I$4)^DCF!F$18+DCF!G$16*DCF!G$17/(1+I$4)^DCF!G$18+DCF!H$16*DCF!H$17/(1+I$4)^DCF!H$18+DCF!I$16*DCF!I$17/(1+I$4)^DCF!I$18+DCF!J$16*DCF!J$17/(1+I$4)^DCF!J$18+DCF!K$16*DCF!K$17/(1+I$4)^DCF!K$18+DCF!L$16*DCF!L$17/(1+I$4)^DCF!L$18+DCF!M$16*DCF!M$17/(1+I$4)^DCF!M$18+DCF!$M$16*(1+$B9)/(I$4-$B9)/(1+I$4)^DCF!$M$18+DCF!$C$31-DCF!$C$32)/DCF!$C$34
B10: Centre = base case (DCF!C35).
B12: TABLE 2 — Core business Bear / Base / Bull (quantum at base path)
B13: Metric | C13: Bear | E13: Base | G13: Bull
B14: Revenue CAGR FY2025A–FY2030E | C14: =(H53/C53)^(1/5)-1 | E14: =(H69/C69)^(1/5)-1 | G14: =(H85/C85)^(1/5)-1
B15: FY2030E EBIT margin | C15: =H55/H53 | E15: =H71/H69 | G15: =H87/H85
B16: WACC | C16: =$N$61 | E16: =$N$77 | G16: =$N$93
B17: Terminal growth | C17: =$N$62 | E17: =$N$78 | G17: =$N$94
B18: Value per share | C18: =C63 | E18: =C79 | G18: =C95
B19: vs. current price | C19: =C63/Assumptions!$C$47-1 | E19: =C79/Assumptions!$C$47-1 | G19: =C95/Assumptions!$C$47-1
B20: Check: Base − DCF!C35 (must be 0) | E20: =ROUND(C79-DCF!C35,6)
B32: TABLE 3 — Quantum scenarios → probability-weighted Price Target
B33: Scenario | C33: Quantum rev FY2030E | D33: Quantum rev FY2035E | E33: Value / share | F33: vs. current | G33: Probability | H33: Weighted
B34: Quantum Stalls (×0.25) | C34: =H100 | D34: =M100 | E34: =C111 | F34: =E34/Assumptions!$C$47-1 | G34: =Assumptions!F79 | H34: =E34*G34
B35: Quantum Base (×1) | C35: =H116 | D35: =M116 | E35: =C127 | F35: =E35/Assumptions!$C$47-1 | G35: =Assumptions!G79 | H35: =E35*G35
B36: Quantum Breakout (×3) | C36: =H132 | D36: =M132 | E36: =C143 | F36: =E36/Assumptions!$C$47-1 | G36: =Assumptions!H79 | H36: =E36*G36
B37: Quantum Dominant (×6) | C37: =H148 | D37: =M148 | E37: =C159 | F37: =E37/Assumptions!$C$47-1 | G37: =Assumptions!I79 | H37: =E37*G37
B40: Probability-weighted value per share | C40: =SUMPRODUCT(E34:E37,G34:G37)/SUM(G34:G37)
B41: Price Target → DCF!C41 · Rating → DCF!C44 | C41: =DCF!C41 | D41: =DCF!C44
B42: Market-implied: quantum value needed to justify current price ($/share) | C42: =MAX(0,DCF!C36-DCF!C39)
B43: Market-implied WACC at base g (interpolated on Table 1) | C43: =IF(OR(C44<1,C44>6),NA(),INDEX($C$4:$I$4,C44)+(DCF!C36-INDEX($C$7:$I$7,C44))*(INDEX($C$4:$I$4,C44+1)-INDEX($C$4:$I$4,C44))/(INDEX($C$7:$I$7,C44+1)-INDEX($C$7:$I$7,C44)))
B44: helper: bracket position in Table 1 base-g row | C44: =COUNTIF($C$7:$I$7,">="&DCF!C36)
B46: SCENARIO ENGINE (supporting calculations)
C47: FY2025A | D47: FY2026E | E47: FY2027E | F47: FY2028E | G47: FY2029E | H47: FY2030E | I47: FY2031E | J47: FY2032E | K47: FY2033E | L47: FY2034E | M47: FY2035E | N47: WACC / g
B48: Bear · Software | C48: =Assumptions!$D$11 | D48: =C48*(1+Assumptions!E$5) | E48: =D48*(1+(Assumptions!F$5+Assumptions!$C$74)) | F48: =E48*(1+(Assumptions!G$5+Assumptions!$C$74)) | G48: =F48*(1+(Assumptions!H$5+Assumptions!$C$74)) | H48: =G48*(1+(Assumptions!I$5+Assumptions!$C$74)) | I48: =H48*(1+(Assumptions!J$5+Assumptions!$C$74)) | J48: =I48*(1+(Assumptions!K$5+Assumptions!$C$74)) | K48: =J48*(1+(Assumptions!L$5+Assumptions!$C$74)) | L48: =K48*(1+(Assumptions!M$5+Assumptions!$C$74)) | M48: =L48*(1+(Assumptions!N$5+Assumptions!$C$74))
B49: Consulting | C49: =Assumptions!$D$12 | D49: =C49*(1+Assumptions!E$6) | E49: =D49*(1+(Assumptions!F$6+Assumptions!$C$74)) | F49: =E49*(1+(Assumptions!G$6+Assumptions!$C$74)) | G49: =F49*(1+(Assumptions!H$6+Assumptions!$C$74)) | H49: =G49*(1+(Assumptions!I$6+Assumptions!$C$74)) | I49: =H49*(1+(Assumptions!J$6+Assumptions!$C$74)) | J49: =I49*(1+(Assumptions!K$6+Assumptions!$C$74)) | K49: =J49*(1+(Assumptions!L$6+Assumptions!$C$74)) | L49: =K49*(1+(Assumptions!M$6+Assumptions!$C$74)) | M49: =L49*(1+(Assumptions!N$6+Assumptions!$C$74))
B50: Infrastructure | C50: =Assumptions!$D$13 | D50: =C50*(1+Assumptions!E$7) | E50: =D50*(1+(Assumptions!F$7+Assumptions!$C$74)) | F50: =E50*(1+(Assumptions!G$7+Assumptions!$C$74)) | G50: =F50*(1+(Assumptions!H$7+Assumptions!$C$74)) | H50: =G50*(1+(Assumptions!I$7+Assumptions!$C$74)) | I50: =H50*(1+(Assumptions!J$7+Assumptions!$C$74)) | J50: =I50*(1+(Assumptions!K$7+Assumptions!$C$74)) | K50: =J50*(1+(Assumptions!L$7+Assumptions!$C$74)) | L50: =K50*(1+(Assumptions!M$7+Assumptions!$C$74)) | M50: =L50*(1+(Assumptions!N$7+Assumptions!$C$74))
B51: Financing | C51: =Assumptions!$D$14 | D51: =C51*(1+Assumptions!E$8) | E51: =D51*(1+Assumptions!F$8) | F51: =E51*(1+Assumptions!G$8) | G51: =F51*(1+Assumptions!H$8) | H51: =G51*(1+Assumptions!I$8) | I51: =H51*(1+Assumptions!J$8) | J51: =I51*(1+Assumptions!K$8) | K51: =J51*(1+Assumptions!L$8) | ... M51: =L51*(1+Assumptions!N$8)
B52: Quantum revenue | C52: =0 | D52: =Assumptions!E$15*Assumptions!$C$78 | E52: =Assumptions!F$15*Assumptions!$C$78 | F52: =Assumptions!G$15*Assumptions!$C$78 | G52: =Assumptions!H$15*Assumptions!$C$78 | H52: =Assumptions!I$15*Assumptions!$C$78 | I52: =Assumptions!J$15*Assumptions!$C$78 | J52: =Assumptions!K$15*Assumptions!$C$78 | K52: =Assumptions!L$15*Assumptions!$C$78 | ... M52: =Assumptions!N$15*Assumptions!$C$78
B53: Total revenue | C53: =SUM(C48:C52) | D53: =SUM(D48:D52) | E53: =SUM(E48:E52) | F53: =SUM(F48:F52) | G53: =SUM(G48:G52) | H53: =SUM(H48:H52) | I53: =SUM(I48:I52) | J53: =SUM(J48:J52) | ... M53: =SUM(M48:M52)
B54: Segment profit (incl. quantum) | D54: =D48*(Assumptions!E$19)+D49*(Assumptions!E$20)+D50*(Assumptions!E$21)+D51*(Assumptions!E$22)+D52*Assumptions!E$23-Assumptions!E$24 | E54: =E48*(Assumptions!F$19+Assumptions!$C$75)+E49*(Assumptions!F$20+Assumptions!$C$75)+E50*(Assumptions!F$21+Assumptions!$C$75)+E51*(Assumptions!F$22)+E52*Assumptions!F$23-Assumptions!F$24 | F54: =F48*(Assumptions!G$19+Assumptions!$C$75)+F49*(Assumptions!G$20+Assumptions!$C$75)+F50*(Assumptions!G$21+Assumptions!$C$75)+F51*(Assumptions!G$22)+F52*Assumptions!G$23-Assumptions!G$24 | G54: =G48*(Assumptions!H$19+Assumptions!$C$75)+G49*(Assumptions!H$20+Assumptions!$C$75)+G50*(Assumptions!H$21+Assumptions!$C$75)+G51*(Assumptions!H$22)+G52*Assumptions!H$23-Assumptions!H$24 | H54: =H48*(Assumptions!I$19+Assumptions!$C$75)+H49*(Assumptions!I$20+Assumptions!$C$75)+H50*(Assumptions!I$21+Assumptions!$C$75)+H51*(Assumptions!I$22)+H52*Assumptions!I$23-Assumptions!I$24 | I54: =I48*(Assumptions!J$19+Assumptions!$C$75)+I49*(Assumptions!J$20+Assumptions!$C$75)+I50*(Assumptions!J$21+Assumptions!$C$75)+I51*(Assumptions!J$22)+I52*Assumptions!J$23-Assumptions!J$24 | J54: =J48*(Assumptions!K$19+Assumptions!$C$75)+J49*(Assumptions!K$20+Assumptions!$C$75)+J50*(Assumptions!K$21+Assumptions!$C$75)+J51*(Assumptions!K$22)+J52*Assumptions!K$23-Assumptions!K$24 | K54: =K48*(Assumptions!L$19+Assumptions!$C$75)+K49*(Assumptions!L$20+Assumptions!$C$75)+K50*(Assumptions!L$21+Assumptions!$C$75)+K51*(Assumptions!L$22)+K52*Assumptions!L$23-Assumptions!L$24 | L54: =L48*(Assumptions!M$19+Assumptions!$C$75)+L49*(Assumptions!M$20+Assumptions!$C$75)+L50*(Assumptions!M$21+Assumptions!$C$75)+L51*(Assumptions!M$22)+L52*Assumptions!M$23-Assumptions!M$24 | M54: =M48*(Assumptions!N$19+Assumptions!$C$75)+M49*(Assumptions!N$20+Assumptions!$C$75)+M50*(Assumptions!N$21+Assumptions!$C$75)+M51*(Assumptions!N$22)+M52*Assumptions!N$23-Assumptions!N$24
B55: EBIT | D55: =D54-D53*Assumptions!E$25 | E55: =E54-E53*Assumptions!F$25 | F55: =F54-F53*Assumptions!G$25 | G55: =G54-G53*Assumptions!H$25 | H55: =H54-H53*Assumptions!I$25 | I55: =I54-I53*Assumptions!J$25 | J55: =J54-J53*Assumptions!K$25 | K55: =K54-K53*Assumptions!L$25 | ... M55: =M54-M53*Assumptions!N$25
B56: NOPAT | D56: =D55-MAX(0,D55)*Assumptions!E$31 | E56: =E55-MAX(0,E55)*Assumptions!F$31 | F56: =F55-MAX(0,F55)*Assumptions!G$31 | G56: =G55-MAX(0,G55)*Assumptions!H$31 | H56: =H55-MAX(0,H55)*Assumptions!I$31 | I56: =I55-MAX(0,I55)*Assumptions!J$31 | J56: =J55-MAX(0,J55)*Assumptions!K$31 | K56: =K55-MAX(0,K55)*Assumptions!L$31 | ... M56: =M55-MAX(0,M55)*Assumptions!N$31
B57: D&A | D57: =D53*Assumptions!E$27 | E57: =E53*Assumptions!F$27 | F57: =F53*Assumptions!G$27 | G57: =G53*Assumptions!H$27 | H57: =H53*Assumptions!I$27 | I57: =I53*Assumptions!J$27 | J57: =J53*Assumptions!K$27 | K57: =K53*Assumptions!L$27 | ... M57: =M53*Assumptions!N$27
B58: Capex (core + quantum) | D58: =-D53*Assumptions!E$28-Assumptions!E$29 | E58: =-E53*Assumptions!F$28-Assumptions!F$29 | F58: =-F53*Assumptions!G$28-Assumptions!G$29 | G58: =-G53*Assumptions!H$28-Assumptions!H$29 | H58: =-H53*Assumptions!I$28-Assumptions!I$29 | I58: =-I53*Assumptions!J$28-Assumptions!J$29 | J58: =-J53*Assumptions!K$28-Assumptions!K$29 | K58: =-K53*Assumptions!L$28-Assumptions!L$29 | ... M58: =-M53*Assumptions!N$28-Assumptions!N$29
B59: Δ working capital | D59: =-(D53-C53)*Assumptions!E$30 | E59: =-(E53-D53)*Assumptions!F$30 | F59: =-(F53-E53)*Assumptions!G$30 | G59: =-(G53-F53)*Assumptions!H$30 | H59: =-(H53-G53)*Assumptions!I$30 | I59: =-(I53-H53)*Assumptions!J$30 | J59: =-(J53-I53)*Assumptions!K$30 | K59: =-(K53-J53)*Assumptions!L$30 | ... M59: =-(M53-L53)*Assumptions!N$30
B60: Unlevered FCF | D60: =D56+D57+D58+D59 | E60: =E56+E57+E58+E59 | F60: =F56+F57+F58+F59 | G60: =G56+G57+G58+G59 | H60: =H56+H57+H58+H59 | I60: =I56+I57+I58+I59 | J60: =J56+J57+J58+J59 | K60: =K56+K57+K58+K59 | ... M60: =M56+M57+M58+M59
B61: PV of FCF | D61: =D60*DCF!D$17/(1+$N$61)^DCF!D$18 | E61: =E60*DCF!E$17/(1+$N$61)^DCF!E$18 | F61: =F60*DCF!F$17/(1+$N$61)^DCF!F$18 | G61: =G60*DCF!G$17/(1+$N$61)^DCF!G$18 | H61: =H60*DCF!H$17/(1+$N$61)^DCF!H$18 | I61: =I60*DCF!I$17/(1+$N$61)^DCF!I$18 | J61: =J60*DCF!J$17/(1+$N$61)^DCF!J$18 | K61: =K60*DCF!K$17/(1+$N$61)^DCF!K$18 | ... M61: =M60*DCF!M$17/(1+$N$61)^DCF!M$18 | N61: =DCF!$C$14+Assumptions!$C$76
N62: =Assumptions!$C$77
B63: Bear value per share | C63: =(SUM(D61:M61)+M60*(1+$N$62)/($N$61-$N$62)/(1+$N$61)^DCF!$M$18+DCF!$C$31-DCF!$C$32)/DCF!$C$34
B64: Base · Software | C64: =Assumptions!$D$11 | D64: =C64*(1+Assumptions!E$5) | E64: =D64*(1+(Assumptions!F$5+Assumptions!$D$74)) | F64: =E64*(1+(Assumptions!G$5+Assumptions!$D$74)) | G64: =F64*(1+(Assumptions!H$5+Assumptions!$D$74)) | H64: =G64*(1+(Assumptions!I$5+Assumptions!$D$74)) | I64: =H64*(1+(Assumptions!J$5+Assumptions!$D$74)) | J64: =I64*(1+(Assumptions!K$5+Assumptions!$D$74)) | K64: =J64*(1+(Assumptions!L$5+Assumptions!$D$74)) | L64: =K64*(1+(Assumptions!M$5+Assumptions!$D$74)) | M64: =L64*(1+(Assumptions!N$5+Assumptions!$D$74))
B65: Consulting | C65: =Assumptions!$D$12 | D65: =C65*(1+Assumptions!E$6) | E65: =D65*(1+(Assumptions!F$6+Assumptions!$D$74)) | F65: =E65*(1+(Assumptions!G$6+Assumptions!$D$74)) | G65: =F65*(1+(Assumptions!H$6+Assumptions!$D$74)) | H65: =G65*(1+(Assumptions!I$6+Assumptions!$D$74)) | I65: =H65*(1+(Assumptions!J$6+Assumptions!$D$74)) | J65: =I65*(1+(Assumptions!K$6+Assumptions!$D$74)) | K65: =J65*(1+(Assumptions!L$6+Assumptions!$D$74)) | L65: =K65*(1+(Assumptions!M$6+Assumptions!$D$74)) | M65: =L65*(1+(Assumptions!N$6+Assumptions!$D$74))
B66: Infrastructure | C66: =Assumptions!$D$13 | D66: =C66*(1+Assumptions!E$7) | E66: =D66*(1+(Assumptions!F$7+Assumptions!$D$74)) | F66: =E66*(1+(Assumptions!G$7+Assumptions!$D$74)) | G66: =F66*(1+(Assumptions!H$7+Assumptions!$D$74)) | H66: =G66*(1+(Assumptions!I$7+Assumptions!$D$74)) | I66: =H66*(1+(Assumptions!J$7+Assumptions!$D$74)) | J66: =I66*(1+(Assumptions!K$7+Assumptions!$D$74)) | K66: =J66*(1+(Assumptions!L$7+Assumptions!$D$74)) | L66: =K66*(1+(Assumptions!M$7+Assumptions!$D$74)) | M66: =L66*(1+(Assumptions!N$7+Assumptions!$D$74))
B67: Financing | C67: =Assumptions!$D$14 | D67: =C67*(1+Assumptions!E$8) | E67: =D67*(1+Assumptions!F$8) | F67: =E67*(1+Assumptions!G$8) | G67: =F67*(1+Assumptions!H$8) | H67: =G67*(1+Assumptions!I$8) | I67: =H67*(1+Assumptions!J$8) | J67: =I67*(1+Assumptions!K$8) | K67: =J67*(1+Assumptions!L$8) | ... M67: =L67*(1+Assumptions!N$8)
B68: Quantum revenue | C68: =0 | D68: =Assumptions!E$15*Assumptions!$D$78 | E68: =Assumptions!F$15*Assumptions!$D$78 | F68: =Assumptions!G$15*Assumptions!$D$78 | G68: =Assumptions!H$15*Assumptions!$D$78 | H68: =Assumptions!I$15*Assumptions!$D$78 | I68: =Assumptions!J$15*Assumptions!$D$78 | J68: =Assumptions!K$15*Assumptions!$D$78 | K68: =Assumptions!L$15*Assumptions!$D$78 | ... M68: =Assumptions!N$15*Assumptions!$D$78
B69: Total revenue | C69: =SUM(C64:C68) | D69: =SUM(D64:D68) | E69: =SUM(E64:E68) | F69: =SUM(F64:F68) | G69: =SUM(G64:G68) | H69: =SUM(H64:H68) | I69: =SUM(I64:I68) | J69: =SUM(J64:J68) | ... M69: =SUM(M64:M68)
B70: Segment profit (incl. quantum) | D70: =D64*(Assumptions!E$19)+D65*(Assumptions!E$20)+D66*(Assumptions!E$21)+D67*(Assumptions!E$22)+D68*Assumptions!E$23-Assumptions!E$24 | E70: =E64*(Assumptions!F$19+Assumptions!$D$75)+E65*(Assumptions!F$20+Assumptions!$D$75)+E66*(Assumptions!F$21+Assumptions!$D$75)+E67*(Assumptions!F$22)+E68*Assumptions!F$23-Assumptions!F$24 | F70: =F64*(Assumptions!G$19+Assumptions!$D$75)+F65*(Assumptions!G$20+Assumptions!$D$75)+F66*(Assumptions!G$21+Assumptions!$D$75)+F67*(Assumptions!G$22)+F68*Assumptions!G$23-Assumptions!G$24 | G70: =G64*(Assumptions!H$19+Assumptions!$D$75)+G65*(Assumptions!H$20+Assumptions!$D$75)+G66*(Assumptions!H$21+Assumptions!$D$75)+G67*(Assumptions!H$22)+G68*Assumptions!H$23-Assumptions!H$24 | H70: =H64*(Assumptions!I$19+Assumptions!$D$75)+H65*(Assumptions!I$20+Assumptions!$D$75)+H66*(Assumptions!I$21+Assumptions!$D$75)+H67*(Assumptions!I$22)+H68*Assumptions!I$23-Assumptions!I$24 | I70: =I64*(Assumptions!J$19+Assumptions!$D$75)+I65*(Assumptions!J$20+Assumptions!$D$75)+I66*(Assumptions!J$21+Assumptions!$D$75)+I67*(Assumptions!J$22)+I68*Assumptions!J$23-Assumptions!J$24 | J70: =J64*(Assumptions!K$19+Assumptions!$D$75)+J65*(Assumptions!K$20+Assumptions!$D$75)+J66*(Assumptions!K$21+Assumptions!$D$75)+J67*(Assumptions!K$22)+J68*Assumptions!K$23-Assumptions!K$24 | K70: =K64*(Assumptions!L$19+Assumptions!$D$75)+K65*(Assumptions!L$20+Assumptions!$D$75)+K66*(Assumptions!L$21+Assumptions!$D$75)+K67*(Assumptions!L$22)+K68*Assumptions!L$23-Assumptions!L$24 | L70: =L64*(Assumptions!M$19+Assumptions!$D$75)+L65*(Assumptions!M$20+Assumptions!$D$75)+L66*(Assumptions!M$21+Assumptions!$D$75)+L67*(Assumptions!M$22)+L68*Assumptions!M$23-Assumptions!M$24 | M70: =M64*(Assumptions!N$19+Assumptions!$D$75)+M65*(Assumptions!N$20+Assumptions!$D$75)+M66*(Assumptions!N$21+Assumptions!$D$75)+M67*(Assumptions!N$22)+M68*Assumptions!N$23-Assumptions!N$24
B71: EBIT | D71: =D70-D69*Assumptions!E$25 | E71: =E70-E69*Assumptions!F$25 | F71: =F70-F69*Assumptions!G$25 | G71: =G70-G69*Assumptions!H$25 | H71: =H70-H69*Assumptions!I$25 | I71: =I70-I69*Assumptions!J$25 | J71: =J70-J69*Assumptions!K$25 | K71: =K70-K69*Assumptions!L$25 | ... M71: =M70-M69*Assumptions!N$25
B72: NOPAT | D72: =D71-MAX(0,D71)*Assumptions!E$31 | E72: =E71-MAX(0,E71)*Assumptions!F$31 | F72: =F71-MAX(0,F71)*Assumptions!G$31 | G72: =G71-MAX(0,G71)*Assumptions!H$31 | H72: =H71-MAX(0,H71)*Assumptions!I$31 | I72: =I71-MAX(0,I71)*Assumptions!J$31 | J72: =J71-MAX(0,J71)*Assumptions!K$31 | K72: =K71-MAX(0,K71)*Assumptions!L$31 | ... M72: =M71-MAX(0,M71)*Assumptions!N$31
B73: D&A | D73: =D69*Assumptions!E$27 | E73: =E69*Assumptions!F$27 | F73: =F69*Assumptions!G$27 | G73: =G69*Assumptions!H$27 | H73: =H69*Assumptions!I$27 | I73: =I69*Assumptions!J$27 | J73: =J69*Assumptions!K$27 | K73: =K69*Assumptions!L$27 | ... M73: =M69*Assumptions!N$27
B74: Capex (core + quantum) | D74: =-D69*Assumptions!E$28-Assumptions!E$29 | E74: =-E69*Assumptions!F$28-Assumptions!F$29 | F74: =-F69*Assumptions!G$28-Assumptions!G$29 | G74: =-G69*Assumptions!H$28-Assumptions!H$29 | H74: =-H69*Assumptions!I$28-Assumptions!I$29 | I74: =-I69*Assumptions!J$28-Assumptions!J$29 | J74: =-J69*Assumptions!K$28-Assumptions!K$29 | K74: =-K69*Assumptions!L$28-Assumptions!L$29 | ... M74: =-M69*Assumptions!N$28-Assumptions!N$29
B75: Δ working capital | D75: =-(D69-C69)*Assumptions!E$30 | E75: =-(E69-D69)*Assumptions!F$30 | F75: =-(F69-E69)*Assumptions!G$30 | G75: =-(G69-F69)*Assumptions!H$30 | H75: =-(H69-G69)*Assumptions!I$30 | I75: =-(I69-H69)*Assumptions!J$30 | J75: =-(J69-I69)*Assumptions!K$30 | K75: =-(K69-J69)*Assumptions!L$30 | ... M75: =-(M69-L69)*Assumptions!N$30
B76: Unlevered FCF | D76: =D72+D73+D74+D75 | E76: =E72+E73+E74+E75 | F76: =F72+F73+F74+F75 | G76: =G72+G73+G74+G75 | H76: =H72+H73+H74+H75 | I76: =I72+I73+I74+I75 | J76: =J72+J73+J74+J75 | K76: =K72+K73+K74+K75 | ... M76: =M72+M73+M74+M75
B77: PV of FCF | D77: =D76*DCF!D$17/(1+$N$77)^DCF!D$18 | E77: =E76*DCF!E$17/(1+$N$77)^DCF!E$18 | F77: =F76*DCF!F$17/(1+$N$77)^DCF!F$18 | G77: =G76*DCF!G$17/(1+$N$77)^DCF!G$18 | H77: =H76*DCF!H$17/(1+$N$77)^DCF!H$18 | I77: =I76*DCF!I$17/(1+$N$77)^DCF!I$18 | J77: =J76*DCF!J$17/(1+$N$77)^DCF!J$18 | K77: =K76*DCF!K$17/(1+$N$77)^DCF!K$18 | ... M77: =M76*DCF!M$17/(1+$N$77)^DCF!M$18 | N77: =DCF!$C$14+Assumptions!$D$76
N78: =Assumptions!$D$77
B79: Base value per share | C79: =(SUM(D77:M77)+M76*(1+$N$78)/($N$77-$N$78)/(1+$N$77)^DCF!$M$18+DCF!$C$31-DCF!$C$32)/DCF!$C$34
B80: Bull · Software | C80: =Assumptions!$D$11 | D80: =C80*(1+Assumptions!E$5) | E80: =D80*(1+(Assumptions!F$5+Assumptions!$E$74)) | F80: =E80*(1+(Assumptions!G$5+Assumptions!$E$74)) | G80: =F80*(1+(Assumptions!H$5+Assumptions!$E$74)) | H80: =G80*(1+(Assumptions!I$5+Assumptions!$E$74)) | I80: =H80*(1+(Assumptions!J$5+Assumptions!$E$74)) | J80: =I80*(1+(Assumptions!K$5+Assumptions!$E$74)) | K80: =J80*(1+(Assumptions!L$5+Assumptions!$E$74)) | L80: =K80*(1+(Assumptions!M$5+Assumptions!$E$74)) | M80: =L80*(1+(Assumptions!N$5+Assumptions!$E$74))
B81: Consulting | C81: =Assumptions!$D$12 | D81: =C81*(1+Assumptions!E$6) | E81: =D81*(1+(Assumptions!F$6+Assumptions!$E$74)) | F81: =E81*(1+(Assumptions!G$6+Assumptions!$E$74)) | G81: =F81*(1+(Assumptions!H$6+Assumptions!$E$74)) | H81: =G81*(1+(Assumptions!I$6+Assumptions!$E$74)) | I81: =H81*(1+(Assumptions!J$6+Assumptions!$E$74)) | J81: =I81*(1+(Assumptions!K$6+Assumptions!$E$74)) | K81: =J81*(1+(Assumptions!L$6+Assumptions!$E$74)) | L81: =K81*(1+(Assumptions!M$6+Assumptions!$E$74)) | M81: =L81*(1+(Assumptions!N$6+Assumptions!$E$74))
B82: Infrastructure | C82: =Assumptions!$D$13 | D82: =C82*(1+Assumptions!E$7) | E82: =D82*(1+(Assumptions!F$7+Assumptions!$E$74)) | F82: =E82*(1+(Assumptions!G$7+Assumptions!$E$74)) | G82: =F82*(1+(Assumptions!H$7+Assumptions!$E$74)) | H82: =G82*(1+(Assumptions!I$7+Assumptions!$E$74)) | I82: =H82*(1+(Assumptions!J$7+Assumptions!$E$74)) | J82: =I82*(1+(Assumptions!K$7+Assumptions!$E$74)) | K82: =J82*(1+(Assumptions!L$7+Assumptions!$E$74)) | L82: =K82*(1+(Assumptions!M$7+Assumptions!$E$74)) | M82: =L82*(1+(Assumptions!N$7+Assumptions!$E$74))
B83: Financing | C83: =Assumptions!$D$14 | D83: =C83*(1+Assumptions!E$8) | E83: =D83*(1+Assumptions!F$8) | F83: =E83*(1+Assumptions!G$8) | G83: =F83*(1+Assumptions!H$8) | H83: =G83*(1+Assumptions!I$8) | I83: =H83*(1+Assumptions!J$8) | J83: =I83*(1+Assumptions!K$8) | K83: =J83*(1+Assumptions!L$8) | ... M83: =L83*(1+Assumptions!N$8)
B84: Quantum revenue | C84: =0 | D84: =Assumptions!E$15*Assumptions!$E$78 | E84: =Assumptions!F$15*Assumptions!$E$78 | F84: =Assumptions!G$15*Assumptions!$E$78 | G84: =Assumptions!H$15*Assumptions!$E$78 | H84: =Assumptions!I$15*Assumptions!$E$78 | I84: =Assumptions!J$15*Assumptions!$E$78 | J84: =Assumptions!K$15*Assumptions!$E$78 | K84: =Assumptions!L$15*Assumptions!$E$78 | ... M84: =Assumptions!N$15*Assumptions!$E$78
B85: Total revenue | C85: =SUM(C80:C84) | D85: =SUM(D80:D84) | E85: =SUM(E80:E84) | F85: =SUM(F80:F84) | G85: =SUM(G80:G84) | H85: =SUM(H80:H84) | I85: =SUM(I80:I84) | J85: =SUM(J80:J84) | ... M85: =SUM(M80:M84)
B86: Segment profit (incl. quantum) | D86: =D80*(Assumptions!E$19)+D81*(Assumptions!E$20)+D82*(Assumptions!E$21)+D83*(Assumptions!E$22)+D84*Assumptions!E$23-Assumptions!E$24 | E86: =E80*(Assumptions!F$19+Assumptions!$E$75)+E81*(Assumptions!F$20+Assumptions!$E$75)+E82*(Assumptions!F$21+Assumptions!$E$75)+E83*(Assumptions!F$22)+E84*Assumptions!F$23-Assumptions!F$24 | F86: =F80*(Assumptions!G$19+Assumptions!$E$75)+F81*(Assumptions!G$20+Assumptions!$E$75)+F82*(Assumptions!G$21+Assumptions!$E$75)+F83*(Assumptions!G$22)+F84*Assumptions!G$23-Assumptions!G$24 | G86: =G80*(Assumptions!H$19+Assumptions!$E$75)+G81*(Assumptions!H$20+Assumptions!$E$75)+G82*(Assumptions!H$21+Assumptions!$E$75)+G83*(Assumptions!H$22)+G84*Assumptions!H$23-Assumptions!H$24 | H86: =H80*(Assumptions!I$19+Assumptions!$E$75)+H81*(Assumptions!I$20+Assumptions!$E$75)+H82*(Assumptions!I$21+Assumptions!$E$75)+H83*(Assumptions!I$22)+H84*Assumptions!I$23-Assumptions!I$24 | I86: =I80*(Assumptions!J$19+Assumptions!$E$75)+I81*(Assumptions!J$20+Assumptions!$E$75)+I82*(Assumptions!J$21+Assumptions!$E$75)+I83*(Assumptions!J$22)+I84*Assumptions!J$23-Assumptions!J$24 | J86: =J80*(Assumptions!K$19+Assumptions!$E$75)+J81*(Assumptions!K$20+Assumptions!$E$75)+J82*(Assumptions!K$21+Assumptions!$E$75)+J83*(Assumptions!K$22)+J84*Assumptions!K$23-Assumptions!K$24 | K86: =K80*(Assumptions!L$19+Assumptions!$E$75)+K81*(Assumptions!L$20+Assumptions!$E$75)+K82*(Assumptions!L$21+Assumptions!$E$75)+K83*(Assumptions!L$22)+K84*Assumptions!L$23-Assumptions!L$24 | L86: =L80*(Assumptions!M$19+Assumptions!$E$75)+L81*(Assumptions!M$20+Assumptions!$E$75)+L82*(Assumptions!M$21+Assumptions!$E$75)+L83*(Assumptions!M$22)+L84*Assumptions!M$23-Assumptions!M$24 | M86: =M80*(Assumptions!N$19+Assumptions!$E$75)+M81*(Assumptions!N$20+Assumptions!$E$75)+M82*(Assumptions!N$21+Assumptions!$E$75)+M83*(Assumptions!N$22)+M84*Assumptions!N$23-Assumptions!N$24
B87: EBIT | D87: =D86-D85*Assumptions!E$25 | E87: =E86-E85*Assumptions!F$25 | F87: =F86-F85*Assumptions!G$25 | G87: =G86-G85*Assumptions!H$25 | H87: =H86-H85*Assumptions!I$25 | I87: =I86-I85*Assumptions!J$25 | J87: =J86-J85*Assumptions!K$25 | K87: =K86-K85*Assumptions!L$25 | ... M87: =M86-M85*Assumptions!N$25
B88: NOPAT | D88: =D87-MAX(0,D87)*Assumptions!E$31 | E88: =E87-MAX(0,E87)*Assumptions!F$31 | F88: =F87-MAX(0,F87)*Assumptions!G$31 | G88: =G87-MAX(0,G87)*Assumptions!H$31 | H88: =H87-MAX(0,H87)*Assumptions!I$31 | I88: =I87-MAX(0,I87)*Assumptions!J$31 | J88: =J87-MAX(0,J87)*Assumptions!K$31 | K88: =K87-MAX(0,K87)*Assumptions!L$31 | ... M88: =M87-MAX(0,M87)*Assumptions!N$31
B89: D&A | D89: =D85*Assumptions!E$27 | E89: =E85*Assumptions!F$27 | F89: =F85*Assumptions!G$27 | G89: =G85*Assumptions!H$27 | H89: =H85*Assumptions!I$27 | I89: =I85*Assumptions!J$27 | J89: =J85*Assumptions!K$27 | K89: =K85*Assumptions!L$27 | ... M89: =M85*Assumptions!N$27
B90: Capex (core + quantum) | D90: =-D85*Assumptions!E$28-Assumptions!E$29 | E90: =-E85*Assumptions!F$28-Assumptions!F$29 | F90: =-F85*Assumptions!G$28-Assumptions!G$29 | G90: =-G85*Assumptions!H$28-Assumptions!H$29 | H90: =-H85*Assumptions!I$28-Assumptions!I$29 | I90: =-I85*Assumptions!J$28-Assumptions!J$29 | J90: =-J85*Assumptions!K$28-Assumptions!K$29 | K90: =-K85*Assumptions!L$28-Assumptions!L$29 | ... M90: =-M85*Assumptions!N$28-Assumptions!N$29
B91: Δ working capital | D91: =-(D85-C85)*Assumptions!E$30 | E91: =-(E85-D85)*Assumptions!F$30 | F91: =-(F85-E85)*Assumptions!G$30 | G91: =-(G85-F85)*Assumptions!H$30 | H91: =-(H85-G85)*Assumptions!I$30 | I91: =-(I85-H85)*Assumptions!J$30 | J91: =-(J85-I85)*Assumptions!K$30 | K91: =-(K85-J85)*Assumptions!L$30 | ... M91: =-(M85-L85)*Assumptions!N$30
B92: Unlevered FCF | D92: =D88+D89+D90+D91 | E92: =E88+E89+E90+E91 | F92: =F88+F89+F90+F91 | G92: =G88+G89+G90+G91 | H92: =H88+H89+H90+H91 | I92: =I88+I89+I90+I91 | J92: =J88+J89+J90+J91 | K92: =K88+K89+K90+K91 | ... M92: =M88+M89+M90+M91
B93: PV of FCF | D93: =D92*DCF!D$17/(1+$N$93)^DCF!D$18 | E93: =E92*DCF!E$17/(1+$N$93)^DCF!E$18 | F93: =F92*DCF!F$17/(1+$N$93)^DCF!F$18 | G93: =G92*DCF!G$17/(1+$N$93)^DCF!G$18 | H93: =H92*DCF!H$17/(1+$N$93)^DCF!H$18 | I93: =I92*DCF!I$17/(1+$N$93)^DCF!I$18 | J93: =J92*DCF!J$17/(1+$N$93)^DCF!J$18 | K93: =K92*DCF!K$17/(1+$N$93)^DCF!K$18 | ... M93: =M92*DCF!M$17/(1+$N$93)^DCF!M$18 | N93: =DCF!$C$14+Assumptions!$E$76
N94: =Assumptions!$E$77
B95: Bull value per share | C95: =(SUM(D93:M93)+M92*(1+$N$94)/($N$93-$N$94)/(1+$N$93)^DCF!$M$18+DCF!$C$31-DCF!$C$32)/DCF!$C$34
B96: Q Stalls · Software | C96: =Assumptions!$D$11 | D96: =C96*(1+Assumptions!E$5) | E96: =D96*(1+(Assumptions!F$5+Assumptions!$F$74)) | F96: =E96*(1+(Assumptions!G$5+Assumptions!$F$74)) | G96: =F96*(1+(Assumptions!H$5+Assumptions!$F$74)) | H96: =G96*(1+(Assumptions!I$5+Assumptions!$F$74)) | I96: =H96*(1+(Assumptions!J$5+Assumptions!$F$74)) | J96: =I96*(1+(Assumptions!K$5+Assumptions!$F$74)) | K96: =J96*(1+(Assumptions!L$5+Assumptions!$F$74)) | L96: =K96*(1+(Assumptions!M$5+Assumptions!$F$74)) | M96: =L96*(1+(Assumptions!N$5+Assumptions!$F$74))
B97: Consulting | C97: =Assumptions!$D$12 | D97: =C97*(1+Assumptions!E$6) | E97: =D97*(1+(Assumptions!F$6+Assumptions!$F$74)) | F97: =E97*(1+(Assumptions!G$6+Assumptions!$F$74)) | G97: =F97*(1+(Assumptions!H$6+Assumptions!$F$74)) | H97: =G97*(1+(Assumptions!I$6+Assumptions!$F$74)) | I97: =H97*(1+(Assumptions!J$6+Assumptions!$F$74)) | J97: =I97*(1+(Assumptions!K$6+Assumptions!$F$74)) | K97: =J97*(1+(Assumptions!L$6+Assumptions!$F$74)) | L97: =K97*(1+(Assumptions!M$6+Assumptions!$F$74)) | M97: =L97*(1+(Assumptions!N$6+Assumptions!$F$74))
B98: Infrastructure | C98: =Assumptions!$D$13 | D98: =C98*(1+Assumptions!E$7) | E98: =D98*(1+(Assumptions!F$7+Assumptions!$F$74)) | F98: =E98*(1+(Assumptions!G$7+Assumptions!$F$74)) | G98: =F98*(1+(Assumptions!H$7+Assumptions!$F$74)) | H98: =G98*(1+(Assumptions!I$7+Assumptions!$F$74)) | I98: =H98*(1+(Assumptions!J$7+Assumptions!$F$74)) | J98: =I98*(1+(Assumptions!K$7+Assumptions!$F$74)) | K98: =J98*(1+(Assumptions!L$7+Assumptions!$F$74)) | L98: =K98*(1+(Assumptions!M$7+Assumptions!$F$74)) | M98: =L98*(1+(Assumptions!N$7+Assumptions!$F$74))
B99: Financing | C99: =Assumptions!$D$14 | D99: =C99*(1+Assumptions!E$8) | E99: =D99*(1+Assumptions!F$8) | F99: =E99*(1+Assumptions!G$8) | G99: =F99*(1+Assumptions!H$8) | H99: =G99*(1+Assumptions!I$8) | I99: =H99*(1+Assumptions!J$8) | J99: =I99*(1+Assumptions!K$8) | K99: =J99*(1+Assumptions!L$8) | ... M99: =L99*(1+Assumptions!N$8)
B100: Quantum revenue | C100: =0 | D100: =Assumptions!E$15*Assumptions!$F$78 | E100: =Assumptions!F$15*Assumptions!$F$78 | F100: =Assumptions!G$15*Assumptions!$F$78 | G100: =Assumptions!H$15*Assumptions!$F$78 | H100: =Assumptions!I$15*Assumptions!$F$78 | I100: =Assumptions!J$15*Assumptions!$F$78 | J100: =Assumptions!K$15*Assumptions!$F$78 | K100: =Assumptions!L$15*Assumptions!$F$78 | ... M100: =Assumptions!N$15*Assumptions!$F$78
B101: Total revenue | C101: =SUM(C96:C100) | D101: =SUM(D96:D100) | E101: =SUM(E96:E100) | F101: =SUM(F96:F100) | G101: =SUM(G96:G100) | H101: =SUM(H96:H100) | I101: =SUM(I96:I100) | J101: =SUM(J96:J100) | ... M101: =SUM(M96:M100)
B102: Segment profit (incl. quantum) | D102: =D96*(Assumptions!E$19)+D97*(Assumptions!E$20)+D98*(Assumptions!E$21)+D99*(Assumptions!E$22)+D100*Assumptions!E$23-Assumptions!E$24 | E102: =E96*(Assumptions!F$19+Assumptions!$F$75)+E97*(Assumptions!F$20+Assumptions!$F$75)+E98*(Assumptions!F$21+Assumptions!$F$75)+E99*(Assumptions!F$22)+E100*Assumptions!F$23-Assumptions!F$24 | F102: =F96*(Assumptions!G$19+Assumptions!$F$75)+F97*(Assumptions!G$20+Assumptions!$F$75)+F98*(Assumptions!G$21+Assumptions!$F$75)+F99*(Assumptions!G$22)+F100*Assumptions!G$23-Assumptions!G$24 | G102: =G96*(Assumptions!H$19+Assumptions!$F$75)+G97*(Assumptions!H$20+Assumptions!$F$75)+G98*(Assumptions!H$21+Assumptions!$F$75)+G99*(Assumptions!H$22)+G100*Assumptions!H$23-Assumptions!H$24 | H102: =H96*(Assumptions!I$19+Assumptions!$F$75)+H97*(Assumptions!I$20+Assumptions!$F$75)+H98*(Assumptions!I$21+Assumptions!$F$75)+H99*(Assumptions!I$22)+H100*Assumptions!I$23-Assumptions!I$24 | I102: =I96*(Assumptions!J$19+Assumptions!$F$75)+I97*(Assumptions!J$20+Assumptions!$F$75)+I98*(Assumptions!J$21+Assumptions!$F$75)+I99*(Assumptions!J$22)+I100*Assumptions!J$23-Assumptions!J$24 | J102: =J96*(Assumptions!K$19+Assumptions!$F$75)+J97*(Assumptions!K$20+Assumptions!$F$75)+J98*(Assumptions!K$21+Assumptions!$F$75)+J99*(Assumptions!K$22)+J100*Assumptions!K$23-Assumptions!K$24 | K102: =K96*(Assumptions!L$19+Assumptions!$F$75)+K97*(Assumptions!L$20+Assumptions!$F$75)+K98*(Assumptions!L$21+Assumptions!$F$75)+K99*(Assumptions!L$22)+K100*Assumptions!L$23-Assumptions!L$24 | L102: =L96*(Assumptions!M$19+Assumptions!$F$75)+L97*(Assumptions!M$20+Assumptions!$F$75)+L98*(Assumptions!M$21+Assumptions!$F$75)+L99*(Assumptions!M$22)+L100*Assumptions!M$23-Assumptions!M$24 | M102: =M96*(Assumptions!N$19+Assumptions!$F$75)+M97*(Assumptions!N$20+Assumptions!$F$75)+M98*(Assumptions!N$21+Assumptions!$F$75)+M99*(Assumptions!N$22)+M100*Assumptions!N$23-Assumptions!N$24
B103: EBIT | D103: =D102-D101*Assumptions!E$25 | E103: =E102-E101*Assumptions!F$25 | F103: =F102-F101*Assumptions!G$25 | G103: =G102-G101*Assumptions!H$25 | H103: =H102-H101*Assumptions!I$25 | I103: =I102-I101*Assumptions!J$25 | J103: =J102-J101*Assumptions!K$25 | K103: =K102-K101*Assumptions!L$25 | ... M103: =M102-M101*Assumptions!N$25
B104: NOPAT | D104: =D103-MAX(0,D103)*Assumptions!E$31 | E104: =E103-MAX(0,E103)*Assumptions!F$31 | F104: =F103-MAX(0,F103)*Assumptions!G$31 | G104: =G103-MAX(0,G103)*Assumptions!H$31 | H104: =H103-MAX(0,H103)*Assumptions!I$31 | I104: =I103-MAX(0,I103)*Assumptions!J$31 | J104: =J103-MAX(0,J103)*Assumptions!K$31 | K104: =K103-MAX(0,K103)*Assumptions!L$31 | ... M104: =M103-MAX(0,M103)*Assumptions!N$31
B105: D&A | D105: =D101*Assumptions!E$27 | E105: =E101*Assumptions!F$27 | F105: =F101*Assumptions!G$27 | G105: =G101*Assumptions!H$27 | H105: =H101*Assumptions!I$27 | I105: =I101*Assumptions!J$27 | J105: =J101*Assumptions!K$27 | K105: =K101*Assumptions!L$27 | ... M105: =M101*Assumptions!N$27
B106: Capex (core + quantum) | D106: =-D101*Assumptions!E$28-Assumptions!E$29 | E106: =-E101*Assumptions!F$28-Assumptions!F$29 | F106: =-F101*Assumptions!G$28-Assumptions!G$29 | G106: =-G101*Assumptions!H$28-Assumptions!H$29 | H106: =-H101*Assumptions!I$28-Assumptions!I$29 | I106: =-I101*Assumptions!J$28-Assumptions!J$29 | J106: =-J101*Assumptions!K$28-Assumptions!K$29 | K106: =-K101*Assumptions!L$28-Assumptions!L$29 | ... M106: =-M101*Assumptions!N$28-Assumptions!N$29
B107: Δ working capital | D107: =-(D101-C101)*Assumptions!E$30 | E107: =-(E101-D101)*Assumptions!F$30 | F107: =-(F101-E101)*Assumptions!G$30 | G107: =-(G101-F101)*Assumptions!H$30 | H107: =-(H101-G101)*Assumptions!I$30 | I107: =-(I101-H101)*Assumptions!J$30 | J107: =-(J101-I101)*Assumptions!K$30 | K107: =-(K101-J101)*Assumptions!L$30 | ... M107: =-(M101-L101)*Assumptions!N$30
B108: Unlevered FCF | D108: =D104+D105+D106+D107 | E108: =E104+E105+E106+E107 | F108: =F104+F105+F106+F107 | G108: =G104+G105+G106+G107 | H108: =H104+H105+H106+H107 | I108: =I104+I105+I106+I107 | J108: =J104+J105+J106+J107 | K108: =K104+K105+K106+K107 | ... M108: =M104+M105+M106+M107
B109: PV of FCF | D109: =D108*DCF!D$17/(1+$N$109)^DCF!D$18 | E109: =E108*DCF!E$17/(1+$N$109)^DCF!E$18 | F109: =F108*DCF!F$17/(1+$N$109)^DCF!F$18 | G109: =G108*DCF!G$17/(1+$N$109)^DCF!G$18 | H109: =H108*DCF!H$17/(1+$N$109)^DCF!H$18 | I109: =I108*DCF!I$17/(1+$N$109)^DCF!I$18 | J109: =J108*DCF!J$17/(1+$N$109)^DCF!J$18 | K109: =K108*DCF!K$17/(1+$N$109)^DCF!K$18 | ... M109: =M108*DCF!M$17/(1+$N$109)^DCF!M$18 | N109: =DCF!$C$14+Assumptions!$F$76
N110: =Assumptions!$F$77
B111: Q Stalls value per share | C111: =(SUM(D109:M109)+M108*(1+$N$110)/($N$109-$N$110)/(1+$N$109)^DCF!$M$18+DCF!$C$31-DCF!$C$32)/DCF!$C$34
B112: Q Base · Software | C112: =Assumptions!$D$11 | D112: =C112*(1+Assumptions!E$5) | E112: =D112*(1+(Assumptions!F$5+Assumptions!$G$74)) | F112: =E112*(1+(Assumptions!G$5+Assumptions!$G$74)) | G112: =F112*(1+(Assumptions!H$5+Assumptions!$G$74)) | H112: =G112*(1+(Assumptions!I$5+Assumptions!$G$74)) | I112: =H112*(1+(Assumptions!J$5+Assumptions!$G$74)) | J112: =I112*(1+(Assumptions!K$5+Assumptions!$G$74)) | K112: =J112*(1+(Assumptions!L$5+Assumptions!$G$74)) | L112: =K112*(1+(Assumptions!M$5+Assumptions!$G$74)) | M112: =L112*(1+(Assumptions!N$5+Assumptions!$G$74))
B113: Consulting | C113: =Assumptions!$D$12 | D113: =C113*(1+Assumptions!E$6) | E113: =D113*(1+(Assumptions!F$6+Assumptions!$G$74)) | F113: =E113*(1+(Assumptions!G$6+Assumptions!$G$74)) | G113: =F113*(1+(Assumptions!H$6+Assumptions!$G$74)) | H113: =G113*(1+(Assumptions!I$6+Assumptions!$G$74)) | I113: =H113*(1+(Assumptions!J$6+Assumptions!$G$74)) | J113: =I113*(1+(Assumptions!K$6+Assumptions!$G$74)) | K113: =J113*(1+(Assumptions!L$6+Assumptions!$G$74)) | L113: =K113*(1+(Assumptions!M$6+Assumptions!$G$74)) | M113: =L113*(1+(Assumptions!N$6+Assumptions!$G$74))
B114: Infrastructure | C114: =Assumptions!$D$13 | D114: =C114*(1+Assumptions!E$7) | E114: =D114*(1+(Assumptions!F$7+Assumptions!$G$74)) | F114: =E114*(1+(Assumptions!G$7+Assumptions!$G$74)) | G114: =F114*(1+(Assumptions!H$7+Assumptions!$G$74)) | H114: =G114*(1+(Assumptions!I$7+Assumptions!$G$74)) | I114: =H114*(1+(Assumptions!J$7+Assumptions!$G$74)) | J114: =I114*(1+(Assumptions!K$7+Assumptions!$G$74)) | K114: =J114*(1+(Assumptions!L$7+Assumptions!$G$74)) | L114: =K114*(1+(Assumptions!M$7+Assumptions!$G$74)) | M114: =L114*(1+(Assumptions!N$7+Assumptions!$G$74))
B115: Financing | C115: =Assumptions!$D$14 | D115: =C115*(1+Assumptions!E$8) | E115: =D115*(1+Assumptions!F$8) | F115: =E115*(1+Assumptions!G$8) | G115: =F115*(1+Assumptions!H$8) | H115: =G115*(1+Assumptions!I$8) | I115: =H115*(1+Assumptions!J$8) | J115: =I115*(1+Assumptions!K$8) | K115: =J115*(1+Assumptions!L$8) | ... M115: =L115*(1+Assumptions!N$8)
B116: Quantum revenue | C116: =0 | D116: =Assumptions!E$15*Assumptions!$G$78 | E116: =Assumptions!F$15*Assumptions!$G$78 | F116: =Assumptions!G$15*Assumptions!$G$78 | G116: =Assumptions!H$15*Assumptions!$G$78 | H116: =Assumptions!I$15*Assumptions!$G$78 | I116: =Assumptions!J$15*Assumptions!$G$78 | J116: =Assumptions!K$15*Assumptions!$G$78 | K116: =Assumptions!L$15*Assumptions!$G$78 | ... M116: =Assumptions!N$15*Assumptions!$G$78
...
