Workbook

Sheet Cover
B3: Advanced Micro Devices, Inc. (NASDAQ: AMD)
B4: Equity Research | Coverage Update | October 2026
B5: Semiconductors & Semiconductor Equipment | Francisco Rodriguez
B7: ="RATING"&CHAR(10)&DCF!C41 | D7: ="PRICE TARGET"&CHAR(10)&TEXT(DCF!C39,"$#,##0") | F7: ="CURRENT PRICE"&CHAR(10)&TEXT(DCF!C36,"$#,##0.00") | H7: ="UPSIDE"&CHAR(10)&TEXT(DCF!C40,"+0.0%;-0.0%")
B9: KEY STATISTICS | F9: VALUATION SUMMARY
B10: Fiscal Year End | D10: ="December" | F10: Base DCF Value | H10: =TEXT(DCF!C35,"$#,##0")
B11: Diluted Shares (M) | D11: =TEXT(DCF!C34,"#,##0") | F11: Bull Case Value | H11: =TEXT(Sensitivity!C91,"$#,##0")
B12: Market Cap | D12: ="$"&TEXT(DCF!C36*DCF!C34/1000,"#,##0")&"B" | F12: Bear Case Value | H12: =TEXT(Sensitivity!C61,"$#,##0")
B13: Net Cash | D13: ="$"&TEXT((DCF!C31-DCF!C32)/1000,"0.0")&"B" | F13: Prob.-Weighted Value | H13: =TEXT(Sensitivity!C40,"$#,##0")
B14: FY2025A Revenue | D14: ="$"&TEXT('Income Statement'!F5/1000,"0.0")&"B" | F14: Base WACC | H14: =TEXT(DCF!C14,"0.0%")
B15: FY2026E Revenue | D15: ="$"&TEXT('Income Statement'!G5/1000,"0.0")&"B" | F15: Terminal Growth Rate | H15: =TEXT(DCF!C24,"0.0%")
B16: FY2025A EBITDA (GAAP) | D16: ="$"&TEXT('Income Statement'!F9/1000,"0.0")&"B" | F16: Revenue CAGR '25–'30E | H16: =TEXT(('Income Statement'!K5/'Income Statement'!F5)^(1/5)-1,"0.0%")
B17: EV / FY2027E EBITDA | D17: =TEXT((DCF!C36*DCF!C34+DCF!C32-DCF!C31)/'Income Statement'!H9,"0.0")&"x" | F17: Upside to PT | H17: =TEXT(DCF!C40,"+0.0%;-0.0%")
B19: INVESTMENT THESIS
B20: ="The fundamental thesis has played out — FY2025A revenue grew 34% to $34.6B and Data Center revenue doubled YoY in Q2 2026 as MI350 ramped. Our refreshed 10-year DCF (Data Center "&TEXT(Assumptions!G5,"0%")&" growth in FY2026E, fading to "&TEXT(Assumptions!P5,"0%")&" by FY2035E) yields a "&TEXT(DCF!C39,"$#,##0")&" price target vs. "&TEXT(DCF!C36,"$#,##0")&" today. Rating: "&DCF!C41&". At ~"&TEXT((DCF!C36*DCF!C34+DCF!C32-DCF!C31)/'Income Statement'!H9,"0")&"x FY2027E EBITDA the stock already discounts execution at or above management's Analyst Day targets."
B21: 1. Data Center Is Now the Business | D21: Q2'26 Data Center revenue $6.7B (+107% YoY), 58% of company revenue. MI450 / Helios rack-scale ramp in H2 2026; OpenAI 6GW agreement begins deploying H2 2026.
B22: 2. Valuation Already Prices Success | D22: Market cap near $1T. Our base case assumes ~46% Data Center CAGR FY25–FY30E — below the >60% Analyst Day target — and still sits below the current price. Only our Bull case and the DC Super Bull scenario clear it.
B23: 3. Margin Expansion Is Real | D23: GAAP gross margin 54% in Q2'26 (vs 40% a year earlier); Q3 guide ~56% non-GAAP. We model EBITDA margin rising from 20% (FY2025A) to 35% by FY2030E.
B24: 4. What Changes Our View | D24: Evidence Data Center can compound above 55% through FY2030E (DC Bull), a lower cost of capital, or a pullback toward our probability-weighted value.
B26: KEY RISKS
B27: ▪ Upside risk | D27: AI capex cycle extends; AMD reaches Analyst Day targets early (see DC Bull / Super Bull)
B28: ▪ Nvidia moat | D28: CUDA ecosystem lock-in; ROCm still trails — share gains could stall
B29: ▪ Customer concentration | D29: Hyperscaler / OpenAI orders are lumpy; AI-credit stress (e.g. Oct 2026 neocloud selloff)
B30: ▪ Dilution | D30: OpenAI warrant (up to 160M shares) not in share count — would lower per-share value
B32: All figures in USD millions unless noted. Price as of Oct 14, 2026; balance sheet as of Jun 27, 2026. Every number on this page is formula-linked to the model — change inputs on the Assumptions tab only.
B34: Francisco Rodriguez | Financial Modeling Portfolio | github.com/Azyo1

Sheet Assumptions
B2: AMD — Model Assumptions (ALL HARDCODED INPUTS = BLUE CELLS) · $M unless noted
B3: Metric | C3: FY2022A | D3: FY2023A | E3: FY2024A | F3: FY2025A | G3: FY2026E | H3: FY2027E | I3: FY2028E | J3: FY2029E | K3: FY2030E | L3: FY2031E | M3: FY2032E | N3: FY2033E | O3: FY2034E | P3: FY2035E
B4: REVENUE GROWTH (% YoY — historical = formula, forecast = input)
B5: Data Center | C5: — | D5: =D11/C11-1 | E5: =E11/D11-1 | F5: =F11/E11-1 | G5: 0.75 | H5: 0.6 | I5: 0.45 | J5: 0.32 | K5: 0.25 | L5: 0.2 | M5: 0.16 | N5: 0.12 | O5: 0.09 | P5: 0.06
B6: Client | C6: — | D6: =D12/C12-1 | E6: =E12/D12-1 | F6: =F12/E12-1 | G6: 0.17 | H6: 0.1 | I6: 0.08 | J6: 0.07 | K6: 0.06 | L6: 0.05 | M6: 0.05 | N6: 0.04 | O6: 0.04 | P6: 0.035
B7: Gaming | C7: — | D7: =D13/C13-1 | E7: =E13/D13-1 | F7: =F13/E13-1 | G7: -0.19 | H7: 0 | I7: 0.05 | J7: 0 | K7: 0 | L7: 0.02 | M7: 0.02 | N7: 0.02 | O7: 0.02 | P7: 0.02
B8: Embedded | C8: — | D8: =D14/C14-1 | E8: =E14/D14-1 | F8: =F14/E14-1 | G8: 0.13 | H8: 0.12 | I8: 0.1 | J8: 0.09 | K8: 0.08 | L8: 0.07 | M8: 0.06 | N8: 0.05 | O8: 0.04 | P8: 0.035
B10: REVENUE BY SEGMENT ($M)
B11: Data Center | C11: 6045 | D11: 6496 | E11: 12641 | F11: 16635 | G11: =F11*(1+G5) | H11: =G11*(1+H5) | I11: =H11*(1+I5) | J11: =I11*(1+J5) | K11: =J11*(1+K5) | L11: =K11*(1+L5) | M11: =L11*(1+M5) | N11: =M11*(1+N5) | ... P11: =O11*(1+P5)
B12: Client | C12: 6236 | D12: 4680 | E12: 7003 | F12: 10640 | G12: =F12*(1+G6) | H12: =G12*(1+H6) | I12: =H12*(1+I6) | J12: =I12*(1+J6) | K12: =J12*(1+K6) | L12: =K12*(1+L6) | M12: =L12*(1+M6) | N12: =M12*(1+N6) | ... P12: =O12*(1+P6)
B13: Gaming | C13: 7167 | D13: 6156 | E13: 2551 | F13: 3910 | G13: =F13*(1+G7) | H13: =G13*(1+H7) | I13: =H13*(1+I7) | J13: =I13*(1+J7) | K13: =J13*(1+K7) | L13: =K13*(1+L7) | M13: =L13*(1+M7) | N13: =M13*(1+N7) | ... P13: =O13*(1+P7)
B14: Embedded | C14: 4153 | D14: 5348 | E14: 3590 | F14: 3454 | G14: =F14*(1+G8) | H14: =G14*(1+H8) | I14: =H14*(1+I8) | J14: =I14*(1+J8) | K14: =J14*(1+K8) | L14: =K14*(1+L8) | M14: =L14*(1+M8) | N14: =M14*(1+N8) | ... P14: =O14*(1+P8)
B15: Total Revenue | C15: =C11+C12+C13+C14 | D15: =D11+D12+D13+D14 | E15: =E11+E12+E13+E14 | F15: =F11+F12+F13+F14 | G15: =G11+G12+G13+G14 | H15: =H11+H12+H13+H14 | I15: =I11+I12+I13+I14 | J15: =J11+J12+J13+J14 | ... P15: =P11+P12+P13+P14
B16: YoY Growth % | D16: =D15/C15-1 | E16: =E15/D15-1 | F16: =F15/E15-1 | G16: =G15/F15-1 | H16: =H15/G15-1 | I16: =I15/H15-1 | J16: =J15/I15-1 | K16: =K15/J15-1 | ... P16: =P15/O15-1
B17: MARGIN, CASH FLOW & TAX (GAAP basis — SBC treated as a real expense)
B18: Gross Margin % | C18: 0.445 | D18: 0.461 | E18: 0.49 | F18: 0.5 | G18: 0.54 | H18: 0.55 | I18: 0.56 | J18: 0.565 | K18: 0.57 | L18: 0.57 | M18: 0.57 | N18: 0.57 | O18: 0.57 | P18: 0.57
B19: EBITDA Margin % | C19: 0.162 | D19: 0.191 | E19: 0.216 | F19: 0.203 | G19: 0.25 | H19: 0.29 | I19: 0.32 | J19: 0.34 | K19: 0.35 | L19: 0.36 | M19: 0.36 | N19: 0.36 | O19: 0.36 | P19: 0.36
B20: D&A incl. acquisition amortization ($M) | C20: 3936 | D20: 3936 | E20: 3758 | F20: 3004 | G20: 3050 | H20: 3000 | I20: 3100 | J20: 3300 | K20: 3500 | L20: 3800 | M20: 4100 | N20: 4400 | O20: 4700 | P20: 5000
B21: Cash Tax Rate % | C21: 0.09 | D21: 0.06 | E21: 0.1 | F21: 0.13 | G21: 0.13 | H21: 0.13 | I21: 0.13 | J21: 0.13 | K21: 0.13 | L21: 0.15 | M21: 0.15 | N21: 0.15 | O21: 0.15 | P21: 0.15
B22: Capex ($M) | C22: 450 | D22: 546 | E22: 636 | F22: 974 | G22: 2800 | H22: 3500 | I22: 3900 | J22: 4200 | K22: 4500 | L22: 4800 | M22: 5100 | N22: 5300 | O22: 5500 | P22: 5600
B23: Δ Working Capital — % of Δ Revenue | C23: — | D23: — | E23: — | F23: — | G23: 0.1 | H23: 0.1 | I23: 0.1 | J23: 0.1 | K23: 0.1 | L23: 0.1 | M23: 0.1 | N23: 0.1 | O23: 0.1 | P23: 0.1
B25: VALUATION DATE & MARKET DATA
B26: Valuation Date | C26: 46309 | D26: Oct 14, 2026 close
B27: FY2026 Fiscal Year End | C27: 46382 | D27: Last Saturday of December (Dec 26, 2026)
B28: Stub — Fraction of FY2026E Remaining | C28: =MAX(0,MIN(1,(C27-C26)/365)) | D28: Formula — only the unearned part of FY2026E FCF is valued
B29: Current Share Price ($) | C29: 570.82 | D29: NASDAQ: AMD, Oct 14, 2026 close
B30: Cash & Short-Term Investments | C30: 13100 | D30: Jun 27, 2026 (Q2 FY2026 release)
B31: Total Debt | C31: 3200 | D31: Jun 27, 2026 (Q2 FY2026 release)
B32: Diluted Shares Outstanding (M) | C32: 1667 | D32: Q2 FY2026 diluted (net income $2.3B / EPS $1.38); OpenAI warrant not included
B33: WACC
B34: Risk-Free Rate (10-yr UST) | C34: 0.051 | D34: ~5.1%, mid-Oct 2026
B35: Equity Risk Premium | C35: 0.043 | D35: Implied US ERP
B36: Levered Beta | C36: 1.4 | D36: Adjusted beta (raw 5-yr regression is higher)
B37: Pre-Tax Cost of Debt | C37: 0.045 | D37: Investment-grade senior notes
B38: Tax Rate for Debt Shield | C38: 0.13
B39: Debt / Total Capital | C39: =C31/(C31+C29*C32) | D39: Formula — market-value weights
B40: TERMINAL VALUE, DISCOUNTING & RATING
B41: Terminal Growth Rate (g) | C41: 0.035
B42: Overweight if PT upside ≥ | C42: 0.1
B43: Underweight if PT upside ≤ | C43: -0.1 | D43: Otherwise Equal-Weight
B44: Round Price Target to nearest ($) | C44: 5
B45: Sensitivity Step — WACC | C45: 0.005
B46: Sensitivity Step — Terminal Growth | C46: 0.005
B47: SCENARIO PARAMETERS (adjustments apply FY2027E onward; blank DC override = base path)
B48: Parameter | C48: Bear | D48: Base | E48: Bull | F48: DC Downside | G48: DC Base | H48: DC Bull | I48: DC Super Bull
B49: Revenue growth adj. — all segments (pp) | C49: -0.1 | D49: 0 | E49: 0.06 | F49: 0 | G49: 0 | H49: 0 | I49: 0
B50: EBITDA margin adj. (pp) | C50: -0.05 | D50: 0 | E50: 0.03 | F50: 0 | G50: 0 | H50: 0 | I50: 0
B51: WACC adj. vs. base (pp) | C51: 0.01 | D51: 0 | E51: -0.005 | F51: 0 | G51: 0 | H51: 0 | I51: 0
B52: Terminal growth rate | C52: 0.03 | D52: =$C$41 | E52: 0.04 | F52: =$C$41 | G52: =$C$41 | H52: =$C$41 | I52: =$C$41
B53: Data Center growth override, FY2027E–FY2030E | F53: 0.3 | H53: 0.55 | I53: 0.7
B54: Probability weight (DC scenarios → Price Target) | F54: 0.2 | G54: 0.4 | H54: 0.3 | I54: 0.1
B55: Probability check (must = 100%) | F55: =SUM(F54:I54)
B57: Sources: AMD 10-K FY2022–FY2025; Q4'25 release (Feb 3 2026); Q1'26 and Q2'26 releases; Q3'26 outlook (~$13.0B ±$0.3B); Nov 11 2025 Financial Analyst Day LT model (>35% revenue CAGR, DC >60% CAGR, >35% non-GAAP op. margin). Forecast growth and margins are analyst estimates.
B59: Francisco Rodriguez | Financial Modeling Portfolio | github.com/Azyo1

Sheet Income Statement
B2: AMD — Income Statement & Unlevered Free Cash Flow Build ($M)
C3: FY2022A | D3: FY2023A | E3: FY2024A | F3: FY2025A | G3: FY2026E | H3: FY2027E | I3: FY2028E | J3: FY2029E | K3: FY2030E | L3: FY2031E | M3: FY2032E | N3: FY2033E | O3: FY2034E | P3: FY2035E
B4: INCOME STATEMENT
B5: Revenue | C5: =Assumptions!C15 | D5: =Assumptions!D15 | E5: =Assumptions!E15 | F5: =Assumptions!F15 | G5: =Assumptions!G15 | H5: =Assumptions!H15 | I5: =Assumptions!I15 | J5: =Assumptions!J15 | ... P5: =Assumptions!P15
B6: YoY Growth | D6: =D5/C5-1 | E6: =E5/D5-1 | F6: =F5/E5-1 | G6: =G5/F5-1 | H6: =H5/G5-1 | I6: =I5/H5-1 | J6: =J5/I5-1 | K6: =K5/J5-1 | ... P6: =P5/O5-1
B7: Gross Profit | C7: =C5*Assumptions!C18 | D7: =D5*Assumptions!D18 | E7: =E5*Assumptions!E18 | F7: =F5*Assumptions!F18 | G7: =G5*Assumptions!G18 | H7: =H5*Assumptions!H18 | I7: =I5*Assumptions!I18 | J7: =J5*Assumptions!J18 | ... P7: =P5*Assumptions!P18
B8: Gross Margin % | C8: =C7/C5 | D8: =D7/D5 | E8: =E7/E5 | F8: =F7/F5 | G8: =G7/G5 | H8: =H7/H5 | I8: =I7/I5 | J8: =J7/J5 | ... P8: =P7/P5
B9: EBITDA | C9: =C5*Assumptions!C19 | D9: =D5*Assumptions!D19 | E9: =E5*Assumptions!E19 | F9: =F5*Assumptions!F19 | G9: =G5*Assumptions!G19 | H9: =H5*Assumptions!H19 | I9: =I5*Assumptions!I19 | J9: =J5*Assumptions!J19 | ... P9: =P5*Assumptions!P19
B10: EBITDA Margin % | C10: =C9/C5 | D10: =D9/D5 | E10: =E9/E5 | F10: =F9/F5 | G10: =G9/G5 | H10: =H9/H5 | I10: =I9/I5 | J10: =J9/J5 | ... P10: =P9/P5
B11: Less: D&A (incl. acquisition amortization) | C11: =Assumptions!C20 | D11: =Assumptions!D20 | E11: =Assumptions!E20 | F11: =Assumptions!F20 | G11: =Assumptions!G20 | H11: =Assumptions!H20 | I11: =Assumptions!I20 | J11: =Assumptions!J20 | ... P11: =Assumptions!P20
B12: EBIT (Operating Income) | C12: =C9-C11 | D12: =D9-D11 | E12: =E9-E11 | F12: =F9-F11 | G12: =G9-G11 | H12: =H9-H11 | I12: =I9-I11 | J12: =J9-J11 | ... P12: =P9-P11
B13: EBIT Margin % | C13: =C12/C5 | D13: =D12/D5 | E13: =E12/E5 | F13: =F12/F5 | G13: =G12/G5 | H13: =H12/H5 | I13: =I12/I5 | J13: =J12/J5 | ... P13: =P12/P5
B14: UNLEVERED FREE CASH FLOW BUILD (forecast years)
B15: EBIT | G15: =G12 | H15: =H12 | I15: =I12 | J15: =J12 | K15: =K12 | L15: =L12 | M15: =M12 | N15: =N12 | ... P15: =P12
B16: Less: Cash Taxes | G16: =-MAX(0,G15)*Assumptions!G21 | H16: =-MAX(0,H15)*Assumptions!H21 | I16: =-MAX(0,I15)*Assumptions!I21 | J16: =-MAX(0,J15)*Assumptions!J21 | K16: =-MAX(0,K15)*Assumptions!K21 | L16: =-MAX(0,L15)*Assumptions!L21 | M16: =-MAX(0,M15)*Assumptions!M21 | N16: =-MAX(0,N15)*Assumptions!N21 | ... P16: =-MAX(0,P15)*Assumptions!P21
B17: NOPAT | G17: =G15+G16 | H17: =H15+H16 | I17: =I15+I16 | J17: =J15+J16 | K17: =K15+K16 | L17: =L15+L16 | M17: =M15+M16 | N17: =N15+N16 | ... P17: =P15+P16
B18: Plus: D&A | G18: =G11 | H18: =H11 | I18: =I11 | J18: =J11 | K18: =K11 | L18: =L11 | M18: =M11 | N18: =N11 | ... P18: =P11
B19: Less: Capital Expenditures | G19: =-Assumptions!G22 | H19: =-Assumptions!H22 | I19: =-Assumptions!I22 | J19: =-Assumptions!J22 | K19: =-Assumptions!K22 | L19: =-Assumptions!L22 | M19: =-Assumptions!M22 | N19: =-Assumptions!N22 | ... P19: =-Assumptions!P22
B20: Less: Δ Working Capital | G20: =-(G5-F5)*Assumptions!G23 | H20: =-(H5-G5)*Assumptions!H23 | I20: =-(I5-H5)*Assumptions!I23 | J20: =-(J5-I5)*Assumptions!J23 | K20: =-(K5-J5)*Assumptions!K23 | L20: =-(L5-K5)*Assumptions!L23 | M20: =-(M5-L5)*Assumptions!M23 | N20: =-(N5-M5)*Assumptions!N23 | ... P20: =-(P5-O5)*Assumptions!P23
B21: Unlevered Free Cash Flow | G21: =G17+G18+G19+G20 | H21: =H17+H18+H19+H20 | I21: =I17+I18+I19+I20 | J21: =J17+J18+J19+J20 | K21: =K17+K18+K19+K20 | L21: =L17+L18+L19+L20 | M21: =M17+M18+M19+M20 | N21: =N17+N18+N19+N20 | ... P21: =P17+P18+P19+P20
B24: Francisco Rodriguez | Financial Modeling Portfolio | github.com/Azyo1

Sheet DCF
B2: AMD — Discounted Cash Flow Analysis ($M)
C3: Value | D3: FY2026E | E3: FY2027E | F3: FY2028E | G3: FY2029E | H3: FY2030E | I3: FY2031E | J3: FY2032E | K3: FY2033E | L3: FY2034E | M3: FY2035E
B4: WACC BUILD
B5: Risk-Free Rate | C5: =Assumptions!$C$34
B6: Equity Risk Premium | C6: =Assumptions!$C$35
B7: Levered Beta | C7: =Assumptions!$C$36
B8: Cost of Equity [Rf + β × ERP] | C8: =C5+C7*C6
B9: Pre-Tax Cost of Debt | C9: =Assumptions!$C$37
B10: Tax Rate | C10: =Assumptions!$C$38
B11: After-Tax Cost of Debt | C11: =C9*(1-C10)
B12: Debt / Total Capital | C12: =Assumptions!$C$39
B13: Equity / Total Capital | C13: =1-C12
B14: WACC [Ke×We + Kd×Wd] | C14: =C8*C13+C11*C12
B15: FREE CASH FLOW PROJECTION (mid-year convention, stub-adjusted)
B16: Metric | D16: FY2026E | E16: FY2027E | F16: FY2028E | G16: FY2029E | H16: FY2030E | I16: FY2031E | J16: FY2032E | K16: FY2033E | L16: FY2034E | M16: FY2035E
B17: Unlevered Free Cash Flow | D17: ='Income Statement'!G21 | E17: ='Income Statement'!H21 | F17: ='Income Statement'!I21 | G17: ='Income Statement'!J21 | H17: ='Income Statement'!K21 | I17: ='Income Statement'!L21 | J17: ='Income Statement'!M21 | K17: ='Income Statement'!N21 | ... M17: ='Income Statement'!P21
B18: Fraction of Year Valued | D18: =Assumptions!$C$28 | E18: =1 | F18: =1 | G18: =1 | H18: =1 | I18: =1 | J18: =1 | K18: =1 | L18: =1 | M18: =1
B19: Discount Period (years from valuation date) | D19: =D18/2 | E19: =SUM($D$18:D18)+E18/2 | F19: =SUM($D$18:E18)+F18/2 | G19: =SUM($D$18:F18)+G18/2 | H19: =SUM($D$18:G18)+H18/2 | I19: =SUM($D$18:H18)+I18/2 | J19: =SUM($D$18:I18)+J18/2 | K19: =SUM($D$18:J18)+K18/2 | L19: =SUM($D$18:K18)+L18/2 | M19: =SUM($D$18:L18)+M18/2
B20: Discount Factor [1/(1+WACC)^t] | D20: =1/(1+$C$14)^D19 | E20: =1/(1+$C$14)^E19 | F20: =1/(1+$C$14)^F19 | G20: =1/(1+$C$14)^G19 | H20: =1/(1+$C$14)^H19 | I20: =1/(1+$C$14)^I19 | J20: =1/(1+$C$14)^J19 | K20: =1/(1+$C$14)^K19 | ... M20: =1/(1+$C$14)^M19
B21: PV of Free Cash Flow | D21: =D17*D18*D20 | E21: =E17*E18*E20 | F21: =F17*F18*F20 | G21: =G17*G18*G20 | H21: =H17*H18*H20 | I21: =I17*I18*I20 | J21: =J17*J18*J20 | K21: =K17*K18*K20 | ... M21: =M17*M18*M20
B22: TERMINAL VALUE & EQUITY BRIDGE
B23: Sum of PV (FCFs) | C23: =SUM(D21:M21)
B24: Terminal Growth Rate (g) | C24: =Assumptions!$C$41
B25: Terminal Year FCF (FY2035E × (1+g)) | C25: =M17*(1+C24)
B26: Terminal Value [FCF_T+1 / (WACC−g)] | C26: =C25/($C$14-C24)
B27: PV of Terminal Value | C27: =C26*M20
B28: Enterprise Value | C28: =C23+C27
B29: TV as % of EV | C29: =C27/C28
B30: Implied TV / Terminal-Year EBITDA | C30: =C26/'Income Statement'!P9
B31: Plus: Cash & Short-Term Investments | C31: =Assumptions!$C$30
B32: Less: Total Debt | C32: =Assumptions!$C$31
B33: Equity Value | C33: =C28+C31-C32
B34: Diluted Shares Outstanding (M) | C34: =Assumptions!$C$32
B35: DCF Value per Share (Base Case) | C35: =C33/C34
B36: Current Share Price | C36: =Assumptions!$C$29
B37: DCF Upside / (Downside) | C37: =C35/C36-1
B38: Probability-Weighted Value (Sensitivity) | C38: =Sensitivity!$C$40
B39: ★ PRICE TARGET | C39: =ROUND(C38/Assumptions!$C$44,0)*Assumptions!$C$44
B40: PT Upside / (Downside) | C40: =C39/C36-1
B41: ★ RATING | C41: =IF(C40>=Assumptions!$C$42,"OVERWEIGHT",IF(C40<=Assumptions!$C$43,"UNDERWEIGHT","EQUAL-WEIGHT"))
B44: Francisco Rodriguez | Financial Modeling Portfolio | github.com/Azyo1

Sheet Sensitivity
B2: AMD — Sensitivity & Scenario Analysis (live formulas)
B3: TABLE 1 — Base-Case DCF Value per Share: WACC × Terminal Growth
B4: TGR ↓ | WACC → | C4: =DCF!$C$14+(-3)*Assumptions!$C$45 | D4: =DCF!$C$14+(-2)*Assumptions!$C$45 | E4: =DCF!$C$14+(-1)*Assumptions!$C$45 | F4: =DCF!$C$14+(0)*Assumptions!$C$45 | G4: =DCF!$C$14+(1)*Assumptions!$C$45 | H4: =DCF!$C$14+(2)*Assumptions!$C$45 | I4: =DCF!$C$14+(3)*Assumptions!$C$45
B5: =Assumptions!$C$41+(-2)*Assumptions!$C$46 | C5: =(DCF!D$17*DCF!D$18/(1+C$4)^DCF!D$19+DCF!E$17*DCF!E$18/(1+C$4)^DCF!E$19+DCF!F$17*DCF!F$18/(1+C$4)^DCF!F$19+DCF!G$17*DCF!G$18/(1+C$4)^DCF!G$19+DCF!H$17*DCF!H$18/(1+C$4)^DCF!H$19+DCF!I$17*DCF!I$18/(1+C$4)^DCF!I$19+DCF!J$17*DCF!J$18/(1+C$4)^DCF!J$19+DCF!K$17*DCF!K$18/(1+C$4)^DCF!K$19+DCF!L$17*DCF!L$18/(1+C$4)^DCF!L$19+DCF!M$17*DCF!M$18/(1+C$4)^DCF!M$19+DCF!$M$17*(1+$B5)/(C$4-$B5)/(1+C$4)^DCF!$M$19+DCF!$C$31-DCF!$C$32)/DCF!$C$34 | D5: =(DCF!D$17*DCF!D$18/(1+D$4)^DCF!D$19+DCF!E$17*DCF!E$18/(1+D$4)^DCF!E$19+DCF!F$17*DCF!F$18/(1+D$4)^DCF!F$19+DCF!G$17*DCF!G$18/(1+D$4)^DCF!G$19+DCF!H$17*DCF!H$18/(1+D$4)^DCF!H$19+DCF!I$17*DCF!I$18/(1+D$4)^DCF!I$19+DCF!J$17*DCF!J$18/(1+D$4)^DCF!J$19+DCF!K$17*DCF!K$18/(1+D$4)^DCF!K$19+DCF!L$17*DCF!L$18/(1+D$4)^DCF!L$19+DCF!M$17*DCF!M$18/(1+D$4)^DCF!M$19+DCF!$M$17*(1+$B5)/(D$4-$B5)/(1+D$4)^DCF!$M$19+DCF!$C$31-DCF!$C$32)/DCF!$C$34 | E5: =(DCF!D$17*DCF!D$18/(1+E$4)^DCF!D$19+DCF!E$17*DCF!E$18/(1+E$4)^DCF!E$19+DCF!F$17*DCF!F$18/(1+E$4)^DCF!F$19+DCF!G$17*DCF!G$18/(1+E$4)^DCF!G$19+DCF!H$17*DCF!H$18/(1+E$4)^DCF!H$19+DCF!I$17*DCF!I$18/(1+E$4)^DCF!I$19+DCF!J$17*DCF!J$18/(1+E$4)^DCF!J$19+DCF!K$17*DCF!K$18/(1+E$4)^DCF!K$19+DCF!L$17*DCF!L$18/(1+E$4)^DCF!L$19+DCF!M$17*DCF!M$18/(1+E$4)^DCF!M$19+DCF!$M$17*(1+$B5)/(E$4-$B5)/(1+E$4)^DCF!$M$19+DCF!$C$31-DCF!$C$32)/DCF!$C$34 | F5: =(DCF!D$17*DCF!D$18/(1+F$4)^DCF!D$19+DCF!E$17*DCF!E$18/(1+F$4)^DCF!E$19+DCF!F$17*DCF!F$18/(1+F$4)^DCF!F$19+DCF!G$17*DCF!G$18/(1+F$4)^DCF!G$19+DCF!H$17*DCF!H$18/(1+F$4)^DCF!H$19+DCF!I$17*DCF!I$18/(1+F$4)^DCF!I$19+DCF!J$17*DCF!J$18/(1+F$4)^DCF!J$19+DCF!K$17*DCF!K$18/(1+F$4)^DCF!K$19+DCF!L$17*DCF!L$18/(1+F$4)^DCF!L$19+DCF!M$17*DCF!M$18/(1+F$4)^DCF!M$19+DCF!$M$17*(1+$B5)/(F$4-$B5)/(1+F$4)^DCF!$M$19+DCF!$C$31-DCF!$C$32)/DCF!$C$34 | G5: =(DCF!D$17*DCF!D$18/(1+G$4)^DCF!D$19+DCF!E$17*DCF!E$18/(1+G$4)^DCF!E$19+DCF!F$17*DCF!F$18/(1+G$4)^DCF!F$19+DCF!G$17*DCF!G$18/(1+G$4)^DCF!G$19+DCF!H$17*DCF!H$18/(1+G$4)^DCF!H$19+DCF!I$17*DCF!I$18/(1+G$4)^DCF!I$19+DCF!J$17*DCF!J$18/(1+G$4)^DCF!J$19+DCF!K$17*DCF!K$18/(1+G$4)^DCF!K$19+DCF!L$17*DCF!L$18/(1+G$4)^DCF!L$19+DCF!M$17*DCF!M$18/(1+G$4)^DCF!M$19+DCF!$M$17*(1+$B5)/(G$4-$B5)/(1+G$4)^DCF!$M$19+DCF!$C$31-DCF!$C$32)/DCF!$C$34 | H5: =(DCF!D$17*DCF!D$18/(1+H$4)^DCF!D$19+DCF!E$17*DCF!E$18/(1+H$4)^DCF!E$19+DCF!F$17*DCF!F$18/(1+H$4)^DCF!F$19+DCF!G$17*DCF!G$18/(1+H$4)^DCF!G$19+DCF!H$17*DCF!H$18/(1+H$4)^DCF!H$19+DCF!I$17*DCF!I$18/(1+H$4)^DCF!I$19+DCF!J$17*DCF!J$18/(1+H$4)^DCF!J$19+DCF!K$17*DCF!K$18/(1+H$4)^DCF!K$19+DCF!L$17*DCF!L$18/(1+H$4)^DCF!L$19+DCF!M$17*DCF!M$18/(1+H$4)^DCF!M$19+DCF!$M$17*(1+$B5)/(H$4-$B5)/(1+H$4)^DCF!$M$19+DCF!$C$31-DCF!$C$32)/DCF!$C$34 | I5: =(DCF!D$17*DCF!D$18/(1+I$4)^DCF!D$19+DCF!E$17*DCF!E$18/(1+I$4)^DCF!E$19+DCF!F$17*DCF!F$18/(1+I$4)^DCF!F$19+DCF!G$17*DCF!G$18/(1+I$4)^DCF!G$19+DCF!H$17*DCF!H$18/(1+I$4)^DCF!H$19+DCF!I$17*DCF!I$18/(1+I$4)^DCF!I$19+DCF!J$17*DCF!J$18/(1+I$4)^DCF!J$19+DCF!K$17*DCF!K$18/(1+I$4)^DCF!K$19+DCF!L$17*DCF!L$18/(1+I$4)^DCF!L$19+DCF!M$17*DCF!M$18/(1+I$4)^DCF!M$19+DCF!$M$17*(1+$B5)/(I$4-$B5)/(1+I$4)^DCF!$M$19+DCF!$C$31-DCF!$C$32)/DCF!$C$34
B6: =Assumptions!$C$41+(-1)*Assumptions!$C$46 | C6: =(DCF!D$17*DCF!D$18/(1+C$4)^DCF!D$19+DCF!E$17*DCF!E$18/(1+C$4)^DCF!E$19+DCF!F$17*DCF!F$18/(1+C$4)^DCF!F$19+DCF!G$17*DCF!G$18/(1+C$4)^DCF!G$19+DCF!H$17*DCF!H$18/(1+C$4)^DCF!H$19+DCF!I$17*DCF!I$18/(1+C$4)^DCF!I$19+DCF!J$17*DCF!J$18/(1+C$4)^DCF!J$19+DCF!K$17*DCF!K$18/(1+C$4)^DCF!K$19+DCF!L$17*DCF!L$18/(1+C$4)^DCF!L$19+DCF!M$17*DCF!M$18/(1+C$4)^DCF!M$19+DCF!$M$17*(1+$B6)/(C$4-$B6)/(1+C$4)^DCF!$M$19+DCF!$C$31-DCF!$C$32)/DCF!$C$34 | D6: =(DCF!D$17*DCF!D$18/(1+D$4)^DCF!D$19+DCF!E$17*DCF!E$18/(1+D$4)^DCF!E$19+DCF!F$17*DCF!F$18/(1+D$4)^DCF!F$19+DCF!G$17*DCF!G$18/(1+D$4)^DCF!G$19+DCF!H$17*DCF!H$18/(1+D$4)^DCF!H$19+DCF!I$17*DCF!I$18/(1+D$4)^DCF!I$19+DCF!J$17*DCF!J$18/(1+D$4)^DCF!J$19+DCF!K$17*DCF!K$18/(1+D$4)^DCF!K$19+DCF!L$17*DCF!L$18/(1+D$4)^DCF!L$19+DCF!M$17*DCF!M$18/(1+D$4)^DCF!M$19+DCF!$M$17*(1+$B6)/(D$4-$B6)/(1+D$4)^DCF!$M$19+DCF!$C$31-DCF!$C$32)/DCF!$C$34 | E6: =(DCF!D$17*DCF!D$18/(1+E$4)^DCF!D$19+DCF!E$17*DCF!E$18/(1+E$4)^DCF!E$19+DCF!F$17*DCF!F$18/(1+E$4)^DCF!F$19+DCF!G$17*DCF!G$18/(1+E$4)^DCF!G$19+DCF!H$17*DCF!H$18/(1+E$4)^DCF!H$19+DCF!I$17*DCF!I$18/(1+E$4)^DCF!I$19+DCF!J$17*DCF!J$18/(1+E$4)^DCF!J$19+DCF!K$17*DCF!K$18/(1+E$4)^DCF!K$19+DCF!L$17*DCF!L$18/(1+E$4)^DCF!L$19+DCF!M$17*DCF!M$18/(1+E$4)^DCF!M$19+DCF!$M$17*(1+$B6)/(E$4-$B6)/(1+E$4)^DCF!$M$19+DCF!$C$31-DCF!$C$32)/DCF!$C$34 | F6: =(DCF!D$17*DCF!D$18/(1+F$4)^DCF!D$19+DCF!E$17*DCF!E$18/(1+F$4)^DCF!E$19+DCF!F$17*DCF!F$18/(1+F$4)^DCF!F$19+DCF!G$17*DCF!G$18/(1+F$4)^DCF!G$19+DCF!H$17*DCF!H$18/(1+F$4)^DCF!H$19+DCF!I$17*DCF!I$18/(1+F$4)^DCF!I$19+DCF!J$17*DCF!J$18/(1+F$4)^DCF!J$19+DCF!K$17*DCF!K$18/(1+F$4)^DCF!K$19+DCF!L$17*DCF!L$18/(1+F$4)^DCF!L$19+DCF!M$17*DCF!M$18/(1+F$4)^DCF!M$19+DCF!$M$17*(1+$B6)/(F$4-$B6)/(1+F$4)^DCF!$M$19+DCF!$C$31-DCF!$C$32)/DCF!$C$34 | G6: =(DCF!D$17*DCF!D$18/(1+G$4)^DCF!D$19+DCF!E$17*DCF!E$18/(1+G$4)^DCF!E$19+DCF!F$17*DCF!F$18/(1+G$4)^DCF!F$19+DCF!G$17*DCF!G$18/(1+G$4)^DCF!G$19+DCF!H$17*DCF!H$18/(1+G$4)^DCF!H$19+DCF!I$17*DCF!I$18/(1+G$4)^DCF!I$19+DCF!J$17*DCF!J$18/(1+G$4)^DCF!J$19+DCF!K$17*DCF!K$18/(1+G$4)^DCF!K$19+DCF!L$17*DCF!L$18/(1+G$4)^DCF!L$19+DCF!M$17*DCF!M$18/(1+G$4)^DCF!M$19+DCF!$M$17*(1+$B6)/(G$4-$B6)/(1+G$4)^DCF!$M$19+DCF!$C$31-DCF!$C$32)/DCF!$C$34 | H6: =(DCF!D$17*DCF!D$18/(1+H$4)^DCF!D$19+DCF!E$17*DCF!E$18/(1+H$4)^DCF!E$19+DCF!F$17*DCF!F$18/(1+H$4)^DCF!F$19+DCF!G$17*DCF!G$18/(1+H$4)^DCF!G$19+DCF!H$17*DCF!H$18/(1+H$4)^DCF!H$19+DCF!I$17*DCF!I$18/(1+H$4)^DCF!I$19+DCF!J$17*DCF!J$18/(1+H$4)^DCF!J$19+DCF!K$17*DCF!K$18/(1+H$4)^DCF!K$19+DCF!L$17*DCF!L$18/(1+H$4)^DCF!L$19+DCF!M$17*DCF!M$18/(1+H$4)^DCF!M$19+DCF!$M$17*(1+$B6)/(H$4-$B6)/(1+H$4)^DCF!$M$19+DCF!$C$31-DCF!$C$32)/DCF!$C$34 | I6: =(DCF!D$17*DCF!D$18/(1+I$4)^DCF!D$19+DCF!E$17*DCF!E$18/(1+I$4)^DCF!E$19+DCF!F$17*DCF!F$18/(1+I$4)^DCF!F$19+DCF!G$17*DCF!G$18/(1+I$4)^DCF!G$19+DCF!H$17*DCF!H$18/(1+I$4)^DCF!H$19+DCF!I$17*DCF!I$18/(1+I$4)^DCF!I$19+DCF!J$17*DCF!J$18/(1+I$4)^DCF!J$19+DCF!K$17*DCF!K$18/(1+I$4)^DCF!K$19+DCF!L$17*DCF!L$18/(1+I$4)^DCF!L$19+DCF!M$17*DCF!M$18/(1+I$4)^DCF!M$19+DCF!$M$17*(1+$B6)/(I$4-$B6)/(1+I$4)^DCF!$M$19+DCF!$C$31-DCF!$C$32)/DCF!$C$34
B7: =Assumptions!$C$41+(0)*Assumptions!$C$46 | C7: =(DCF!D$17*DCF!D$18/(1+C$4)^DCF!D$19+DCF!E$17*DCF!E$18/(1+C$4)^DCF!E$19+DCF!F$17*DCF!F$18/(1+C$4)^DCF!F$19+DCF!G$17*DCF!G$18/(1+C$4)^DCF!G$19+DCF!H$17*DCF!H$18/(1+C$4)^DCF!H$19+DCF!I$17*DCF!I$18/(1+C$4)^DCF!I$19+DCF!J$17*DCF!J$18/(1+C$4)^DCF!J$19+DCF!K$17*DCF!K$18/(1+C$4)^DCF!K$19+DCF!L$17*DCF!L$18/(1+C$4)^DCF!L$19+DCF!M$17*DCF!M$18/(1+C$4)^DCF!M$19+DCF!$M$17*(1+$B7)/(C$4-$B7)/(1+C$4)^DCF!$M$19+DCF!$C$31-DCF!$C$32)/DCF!$C$34 | D7: =(DCF!D$17*DCF!D$18/(1+D$4)^DCF!D$19+DCF!E$17*DCF!E$18/(1+D$4)^DCF!E$19+DCF!F$17*DCF!F$18/(1+D$4)^DCF!F$19+DCF!G$17*DCF!G$18/(1+D$4)^DCF!G$19+DCF!H$17*DCF!H$18/(1+D$4)^DCF!H$19+DCF!I$17*DCF!I$18/(1+D$4)^DCF!I$19+DCF!J$17*DCF!J$18/(1+D$4)^DCF!J$19+DCF!K$17*DCF!K$18/(1+D$4)^DCF!K$19+DCF!L$17*DCF!L$18/(1+D$4)^DCF!L$19+DCF!M$17*DCF!M$18/(1+D$4)^DCF!M$19+DCF!$M$17*(1+$B7)/(D$4-$B7)/(1+D$4)^DCF!$M$19+DCF!$C$31-DCF!$C$32)/DCF!$C$34 | E7: =(DCF!D$17*DCF!D$18/(1+E$4)^DCF!D$19+DCF!E$17*DCF!E$18/(1+E$4)^DCF!E$19+DCF!F$17*DCF!F$18/(1+E$4)^DCF!F$19+DCF!G$17*DCF!G$18/(1+E$4)^DCF!G$19+DCF!H$17*DCF!H$18/(1+E$4)^DCF!H$19+DCF!I$17*DCF!I$18/(1+E$4)^DCF!I$19+DCF!J$17*DCF!J$18/(1+E$4)^DCF!J$19+DCF!K$17*DCF!K$18/(1+E$4)^DCF!K$19+DCF!L$17*DCF!L$18/(1+E$4)^DCF!L$19+DCF!M$17*DCF!M$18/(1+E$4)^DCF!M$19+DCF!$M$17*(1+$B7)/(E$4-$B7)/(1+E$4)^DCF!$M$19+DCF!$C$31-DCF!$C$32)/DCF!$C$34 | F7: =(DCF!D$17*DCF!D$18/(1+F$4)^DCF!D$19+DCF!E$17*DCF!E$18/(1+F$4)^DCF!E$19+DCF!F$17*DCF!F$18/(1+F$4)^DCF!F$19+DCF!G$17*DCF!G$18/(1+F$4)^DCF!G$19+DCF!H$17*DCF!H$18/(1+F$4)^DCF!H$19+DCF!I$17*DCF!I$18/(1+F$4)^DCF!I$19+DCF!J$17*DCF!J$18/(1+F$4)^DCF!J$19+DCF!K$17*DCF!K$18/(1+F$4)^DCF!K$19+DCF!L$17*DCF!L$18/(1+F$4)^DCF!L$19+DCF!M$17*DCF!M$18/(1+F$4)^DCF!M$19+DCF!$M$17*(1+$B7)/(F$4-$B7)/(1+F$4)^DCF!$M$19+DCF!$C$31-DCF!$C$32)/DCF!$C$34 | G7: =(DCF!D$17*DCF!D$18/(1+G$4)^DCF!D$19+DCF!E$17*DCF!E$18/(1+G$4)^DCF!E$19+DCF!F$17*DCF!F$18/(1+G$4)^DCF!F$19+DCF!G$17*DCF!G$18/(1+G$4)^DCF!G$19+DCF!H$17*DCF!H$18/(1+G$4)^DCF!H$19+DCF!I$17*DCF!I$18/(1+G$4)^DCF!I$19+DCF!J$17*DCF!J$18/(1+G$4)^DCF!J$19+DCF!K$17*DCF!K$18/(1+G$4)^DCF!K$19+DCF!L$17*DCF!L$18/(1+G$4)^DCF!L$19+DCF!M$17*DCF!M$18/(1+G$4)^DCF!M$19+DCF!$M$17*(1+$B7)/(G$4-$B7)/(1+G$4)^DCF!$M$19+DCF!$C$31-DCF!$C$32)/DCF!$C$34 | H7: =(DCF!D$17*DCF!D$18/(1+H$4)^DCF!D$19+DCF!E$17*DCF!E$18/(1+H$4)^DCF!E$19+DCF!F$17*DCF!F$18/(1+H$4)^DCF!F$19+DCF!G$17*DCF!G$18/(1+H$4)^DCF!G$19+DCF!H$17*DCF!H$18/(1+H$4)^DCF!H$19+DCF!I$17*DCF!I$18/(1+H$4)^DCF!I$19+DCF!J$17*DCF!J$18/(1+H$4)^DCF!J$19+DCF!K$17*DCF!K$18/(1+H$4)^DCF!K$19+DCF!L$17*DCF!L$18/(1+H$4)^DCF!L$19+DCF!M$17*DCF!M$18/(1+H$4)^DCF!M$19+DCF!$M$17*(1+$B7)/(H$4-$B7)/(1+H$4)^DCF!$M$19+DCF!$C$31-DCF!$C$32)/DCF!$C$34 | I7: =(DCF!D$17*DCF!D$18/(1+I$4)^DCF!D$19+DCF!E$17*DCF!E$18/(1+I$4)^DCF!E$19+DCF!F$17*DCF!F$18/(1+I$4)^DCF!F$19+DCF!G$17*DCF!G$18/(1+I$4)^DCF!G$19+DCF!H$17*DCF!H$18/(1+I$4)^DCF!H$19+DCF!I$17*DCF!I$18/(1+I$4)^DCF!I$19+DCF!J$17*DCF!J$18/(1+I$4)^DCF!J$19+DCF!K$17*DCF!K$18/(1+I$4)^DCF!K$19+DCF!L$17*DCF!L$18/(1+I$4)^DCF!L$19+DCF!M$17*DCF!M$18/(1+I$4)^DCF!M$19+DCF!$M$17*(1+$B7)/(I$4-$B7)/(1+I$4)^DCF!$M$19+DCF!$C$31-DCF!$C$32)/DCF!$C$34
B8: =Assumptions!$C$41+(1)*Assumptions!$C$46 | C8: =(DCF!D$17*DCF!D$18/(1+C$4)^DCF!D$19+DCF!E$17*DCF!E$18/(1+C$4)^DCF!E$19+DCF!F$17*DCF!F$18/(1+C$4)^DCF!F$19+DCF!G$17*DCF!G$18/(1+C$4)^DCF!G$19+DCF!H$17*DCF!H$18/(1+C$4)^DCF!H$19+DCF!I$17*DCF!I$18/(1+C$4)^DCF!I$19+DCF!J$17*DCF!J$18/(1+C$4)^DCF!J$19+DCF!K$17*DCF!K$18/(1+C$4)^DCF!K$19+DCF!L$17*DCF!L$18/(1+C$4)^DCF!L$19+DCF!M$17*DCF!M$18/(1+C$4)^DCF!M$19+DCF!$M$17*(1+$B8)/(C$4-$B8)/(1+C$4)^DCF!$M$19+DCF!$C$31-DCF!$C$32)/DCF!$C$34 | D8: =(DCF!D$17*DCF!D$18/(1+D$4)^DCF!D$19+DCF!E$17*DCF!E$18/(1+D$4)^DCF!E$19+DCF!F$17*DCF!F$18/(1+D$4)^DCF!F$19+DCF!G$17*DCF!G$18/(1+D$4)^DCF!G$19+DCF!H$17*DCF!H$18/(1+D$4)^DCF!H$19+DCF!I$17*DCF!I$18/(1+D$4)^DCF!I$19+DCF!J$17*DCF!J$18/(1+D$4)^DCF!J$19+DCF!K$17*DCF!K$18/(1+D$4)^DCF!K$19+DCF!L$17*DCF!L$18/(1+D$4)^DCF!L$19+DCF!M$17*DCF!M$18/(1+D$4)^DCF!M$19+DCF!$M$17*(1+$B8)/(D$4-$B8)/(1+D$4)^DCF!$M$19+DCF!$C$31-DCF!$C$32)/DCF!$C$34 | E8: =(DCF!D$17*DCF!D$18/(1+E$4)^DCF!D$19+DCF!E$17*DCF!E$18/(1+E$4)^DCF!E$19+DCF!F$17*DCF!F$18/(1+E$4)^DCF!F$19+DCF!G$17*DCF!G$18/(1+E$4)^DCF!G$19+DCF!H$17*DCF!H$18/(1+E$4)^DCF!H$19+DCF!I$17*DCF!I$18/(1+E$4)^DCF!I$19+DCF!J$17*DCF!J$18/(1+E$4)^DCF!J$19+DCF!K$17*DCF!K$18/(1+E$4)^DCF!K$19+DCF!L$17*DCF!L$18/(1+E$4)^DCF!L$19+DCF!M$17*DCF!M$18/(1+E$4)^DCF!M$19+DCF!$M$17*(1+$B8)/(E$4-$B8)/(1+E$4)^DCF!$M$19+DCF!$C$31-DCF!$C$32)/DCF!$C$34 | F8: =(DCF!D$17*DCF!D$18/(1+F$4)^DCF!D$19+DCF!E$17*DCF!E$18/(1+F$4)^DCF!E$19+DCF!F$17*DCF!F$18/(1+F$4)^DCF!F$19+DCF!G$17*DCF!G$18/(1+F$4)^DCF!G$19+DCF!H$17*DCF!H$18/(1+F$4)^DCF!H$19+DCF!I$17*DCF!I$18/(1+F$4)^DCF!I$19+DCF!J$17*DCF!J$18/(1+F$4)^DCF!J$19+DCF!K$17*DCF!K$18/(1+F$4)^DCF!K$19+DCF!L$17*DCF!L$18/(1+F$4)^DCF!L$19+DCF!M$17*DCF!M$18/(1+F$4)^DCF!M$19+DCF!$M$17*(1+$B8)/(F$4-$B8)/(1+F$4)^DCF!$M$19+DCF!$C$31-DCF!$C$32)/DCF!$C$34 | G8: =(DCF!D$17*DCF!D$18/(1+G$4)^DCF!D$19+DCF!E$17*DCF!E$18/(1+G$4)^DCF!E$19+DCF!F$17*DCF!F$18/(1+G$4)^DCF!F$19+DCF!G$17*DCF!G$18/(1+G$4)^DCF!G$19+DCF!H$17*DCF!H$18/(1+G$4)^DCF!H$19+DCF!I$17*DCF!I$18/(1+G$4)^DCF!I$19+DCF!J$17*DCF!J$18/(1+G$4)^DCF!J$19+DCF!K$17*DCF!K$18/(1+G$4)^DCF!K$19+DCF!L$17*DCF!L$18/(1+G$4)^DCF!L$19+DCF!M$17*DCF!M$18/(1+G$4)^DCF!M$19+DCF!$M$17*(1+$B8)/(G$4-$B8)/(1+G$4)^DCF!$M$19+DCF!$C$31-DCF!$C$32)/DCF!$C$34 | H8: =(DCF!D$17*DCF!D$18/(1+H$4)^DCF!D$19+DCF!E$17*DCF!E$18/(1+H$4)^DCF!E$19+DCF!F$17*DCF!F$18/(1+H$4)^DCF!F$19+DCF!G$17*DCF!G$18/(1+H$4)^DCF!G$19+DCF!H$17*DCF!H$18/(1+H$4)^DCF!H$19+DCF!I$17*DCF!I$18/(1+H$4)^DCF!I$19+DCF!J$17*DCF!J$18/(1+H$4)^DCF!J$19+DCF!K$17*DCF!K$18/(1+H$4)^DCF!K$19+DCF!L$17*DCF!L$18/(1+H$4)^DCF!L$19+DCF!M$17*DCF!M$18/(1+H$4)^DCF!M$19+DCF!$M$17*(1+$B8)/(H$4-$B8)/(1+H$4)^DCF!$M$19+DCF!$C$31-DCF!$C$32)/DCF!$C$34 | I8: =(DCF!D$17*DCF!D$18/(1+I$4)^DCF!D$19+DCF!E$17*DCF!E$18/(1+I$4)^DCF!E$19+DCF!F$17*DCF!F$18/(1+I$4)^DCF!F$19+DCF!G$17*DCF!G$18/(1+I$4)^DCF!G$19+DCF!H$17*DCF!H$18/(1+I$4)^DCF!H$19+DCF!I$17*DCF!I$18/(1+I$4)^DCF!I$19+DCF!J$17*DCF!J$18/(1+I$4)^DCF!J$19+DCF!K$17*DCF!K$18/(1+I$4)^DCF!K$19+DCF!L$17*DCF!L$18/(1+I$4)^DCF!L$19+DCF!M$17*DCF!M$18/(1+I$4)^DCF!M$19+DCF!$M$17*(1+$B8)/(I$4-$B8)/(1+I$4)^DCF!$M$19+DCF!$C$31-DCF!$C$32)/DCF!$C$34
B9: =Assumptions!$C$41+(2)*Assumptions!$C$46 | C9: =(DCF!D$17*DCF!D$18/(1+C$4)^DCF!D$19+DCF!E$17*DCF!E$18/(1+C$4)^DCF!E$19+DCF!F$17*DCF!F$18/(1+C$4)^DCF!F$19+DCF!G$17*DCF!G$18/(1+C$4)^DCF!G$19+DCF!H$17*DCF!H$18/(1+C$4)^DCF!H$19+DCF!I$17*DCF!I$18/(1+C$4)^DCF!I$19+DCF!J$17*DCF!J$18/(1+C$4)^DCF!J$19+DCF!K$17*DCF!K$18/(1+C$4)^DCF!K$19+DCF!L$17*DCF!L$18/(1+C$4)^DCF!L$19+DCF!M$17*DCF!M$18/(1+C$4)^DCF!M$19+DCF!$M$17*(1+$B9)/(C$4-$B9)/(1+C$4)^DCF!$M$19+DCF!$C$31-DCF!$C$32)/DCF!$C$34 | D9: =(DCF!D$17*DCF!D$18/(1+D$4)^DCF!D$19+DCF!E$17*DCF!E$18/(1+D$4)^DCF!E$19+DCF!F$17*DCF!F$18/(1+D$4)^DCF!F$19+DCF!G$17*DCF!G$18/(1+D$4)^DCF!G$19+DCF!H$17*DCF!H$18/(1+D$4)^DCF!H$19+DCF!I$17*DCF!I$18/(1+D$4)^DCF!I$19+DCF!J$17*DCF!J$18/(1+D$4)^DCF!J$19+DCF!K$17*DCF!K$18/(1+D$4)^DCF!K$19+DCF!L$17*DCF!L$18/(1+D$4)^DCF!L$19+DCF!M$17*DCF!M$18/(1+D$4)^DCF!M$19+DCF!$M$17*(1+$B9)/(D$4-$B9)/(1+D$4)^DCF!$M$19+DCF!$C$31-DCF!$C$32)/DCF!$C$34 | E9: =(DCF!D$17*DCF!D$18/(1+E$4)^DCF!D$19+DCF!E$17*DCF!E$18/(1+E$4)^DCF!E$19+DCF!F$17*DCF!F$18/(1+E$4)^DCF!F$19+DCF!G$17*DCF!G$18/(1+E$4)^DCF!G$19+DCF!H$17*DCF!H$18/(1+E$4)^DCF!H$19+DCF!I$17*DCF!I$18/(1+E$4)^DCF!I$19+DCF!J$17*DCF!J$18/(1+E$4)^DCF!J$19+DCF!K$17*DCF!K$18/(1+E$4)^DCF!K$19+DCF!L$17*DCF!L$18/(1+E$4)^DCF!L$19+DCF!M$17*DCF!M$18/(1+E$4)^DCF!M$19+DCF!$M$17*(1+$B9)/(E$4-$B9)/(1+E$4)^DCF!$M$19+DCF!$C$31-DCF!$C$32)/DCF!$C$34 | F9: =(DCF!D$17*DCF!D$18/(1+F$4)^DCF!D$19+DCF!E$17*DCF!E$18/(1+F$4)^DCF!E$19+DCF!F$17*DCF!F$18/(1+F$4)^DCF!F$19+DCF!G$17*DCF!G$18/(1+F$4)^DCF!G$19+DCF!H$17*DCF!H$18/(1+F$4)^DCF!H$19+DCF!I$17*DCF!I$18/(1+F$4)^DCF!I$19+DCF!J$17*DCF!J$18/(1+F$4)^DCF!J$19+DCF!K$17*DCF!K$18/(1+F$4)^DCF!K$19+DCF!L$17*DCF!L$18/(1+F$4)^DCF!L$19+DCF!M$17*DCF!M$18/(1+F$4)^DCF!M$19+DCF!$M$17*(1+$B9)/(F$4-$B9)/(1+F$4)^DCF!$M$19+DCF!$C$31-DCF!$C$32)/DCF!$C$34 | G9: =(DCF!D$17*DCF!D$18/(1+G$4)^DCF!D$19+DCF!E$17*DCF!E$18/(1+G$4)^DCF!E$19+DCF!F$17*DCF!F$18/(1+G$4)^DCF!F$19+DCF!G$17*DCF!G$18/(1+G$4)^DCF!G$19+DCF!H$17*DCF!H$18/(1+G$4)^DCF!H$19+DCF!I$17*DCF!I$18/(1+G$4)^DCF!I$19+DCF!J$17*DCF!J$18/(1+G$4)^DCF!J$19+DCF!K$17*DCF!K$18/(1+G$4)^DCF!K$19+DCF!L$17*DCF!L$18/(1+G$4)^DCF!L$19+DCF!M$17*DCF!M$18/(1+G$4)^DCF!M$19+DCF!$M$17*(1+$B9)/(G$4-$B9)/(1+G$4)^DCF!$M$19+DCF!$C$31-DCF!$C$32)/DCF!$C$34 | H9: =(DCF!D$17*DCF!D$18/(1+H$4)^DCF!D$19+DCF!E$17*DCF!E$18/(1+H$4)^DCF!E$19+DCF!F$17*DCF!F$18/(1+H$4)^DCF!F$19+DCF!G$17*DCF!G$18/(1+H$4)^DCF!G$19+DCF!H$17*DCF!H$18/(1+H$4)^DCF!H$19+DCF!I$17*DCF!I$18/(1+H$4)^DCF!I$19+DCF!J$17*DCF!J$18/(1+H$4)^DCF!J$19+DCF!K$17*DCF!K$18/(1+H$4)^DCF!K$19+DCF!L$17*DCF!L$18/(1+H$4)^DCF!L$19+DCF!M$17*DCF!M$18/(1+H$4)^DCF!M$19+DCF!$M$17*(1+$B9)/(H$4-$B9)/(1+H$4)^DCF!$M$19+DCF!$C$31-DCF!$C$32)/DCF!$C$34 | I9: =(DCF!D$17*DCF!D$18/(1+I$4)^DCF!D$19+DCF!E$17*DCF!E$18/(1+I$4)^DCF!E$19+DCF!F$17*DCF!F$18/(1+I$4)^DCF!F$19+DCF!G$17*DCF!G$18/(1+I$4)^DCF!G$19+DCF!H$17*DCF!H$18/(1+I$4)^DCF!H$19+DCF!I$17*DCF!I$18/(1+I$4)^DCF!I$19+DCF!J$17*DCF!J$18/(1+I$4)^DCF!J$19+DCF!K$17*DCF!K$18/(1+I$4)^DCF!K$19+DCF!L$17*DCF!L$18/(1+I$4)^DCF!L$19+DCF!M$17*DCF!M$18/(1+I$4)^DCF!M$19+DCF!$M$17*(1+$B9)/(I$4-$B9)/(1+I$4)^DCF!$M$19+DCF!$C$31-DCF!$C$32)/DCF!$C$34
B10: Centre cell = base case (DCF!C35). Axis steps set on Assumptions.
B12: TABLE 2 — Bear / Base / Bull (full re-projection in scenario engine below)
B13: Metric | C13: Bear Case | E13: Base Case | G13: Bull Case
B14: Revenue CAGR FY2025A–FY2030E | C14: =(H52/C52)^(1/5)-1 | E14: =(H67/C67)^(1/5)-1 | G14: =(H82/C82)^(1/5)-1
B15: FY2030E EBITDA Margin | C15: =H53/H52 | E15: =H68/H67 | G15: =H83/H82
B16: WACC | C16: =N59 | E16: =N74 | G16: =N89
B17: Terminal Growth | C17: =N60 | E17: =N75 | G17: =N90
B18: Value per Share | C18: =C61 | E18: =C76 | G18: =C91
B19: Upside / (Downside) vs Current | C19: =C61/Assumptions!$C$29-1 | E19: =C76/Assumptions!$C$29-1 | G19: =C91/Assumptions!$C$29-1
B20: Check: Base value − DCF!C35 (must be 0) | E20: =ROUND(C76-DCF!C35,6)
B32: TABLE 3 — Data Center Growth Scenarios → Probability-Weighted Price Target
B33: Scenario | C33: DC Growth FY27–30E | D33: DC Rev FY2030E | E33: Value / Share | F33: Upside | G33: Probability | H33: Weighted
B34: Downside | C34: =IF(ISNUMBER(Assumptions!F53),Assumptions!F53,(H93/D93)^(1/4)-1) | D34: =H93 | E34: =C106 | F34: =E34/Assumptions!$C$29-1 | G34: =Assumptions!F54 | H34: =E34*G34
B35: Base | C35: =IF(ISNUMBER(Assumptions!G53),Assumptions!G53,(H108/D108)^(1/4)-1) | D35: =H108 | E35: =C121 | F35: =E35/Assumptions!$C$29-1 | G35: =Assumptions!G54 | H35: =E35*G35
B36: Bull | C36: =IF(ISNUMBER(Assumptions!H53),Assumptions!H53,(H123/D123)^(1/4)-1) | D36: =H123 | E36: =C136 | F36: =E36/Assumptions!$C$29-1 | G36: =Assumptions!H54 | H36: =E36*G36
B37: Super Bull | C37: =IF(ISNUMBER(Assumptions!I53),Assumptions!I53,(H138/D138)^(1/4)-1) | D37: =H138 | E37: =C151 | F37: =E37/Assumptions!$C$29-1 | G37: =Assumptions!I54 | H37: =E37*G37
B40: Probability-Weighted Value per Share | C40: =SUMPRODUCT(E34:E37,G34:G37)/SUM(G34:G37)
B41: Price Target (rounded) → DCF!C39 | C41: =DCF!C39
B42: Rating → DCF!C41 | C42: =DCF!C41
B46: SCENARIO ENGINE — full re-projection per scenario (supporting calculations)
C47: FY2025A | D47: FY2026E | E47: FY2027E | F47: FY2028E | G47: FY2029E | H47: FY2030E | I47: FY2031E | J47: FY2032E | K47: FY2033E | L47: FY2034E | M47: FY2035E | N47: WACC / g
B48: Bear · Data Center revenue | C48: =Assumptions!$F$11 | D48: =C48*(1+Assumptions!G$5) | E48: =D48*(1+IF(ISNUMBER(Assumptions!$C$53),Assumptions!$C$53,(Assumptions!H$5+Assumptions!$C$49))) | F48: =E48*(1+IF(ISNUMBER(Assumptions!$C$53),Assumptions!$C$53,(Assumptions!I$5+Assumptions!$C$49))) | G48: =F48*(1+IF(ISNUMBER(Assumptions!$C$53),Assumptions!$C$53,(Assumptions!J$5+Assumptions!$C$49))) | H48: =G48*(1+IF(ISNUMBER(Assumptions!$C$53),Assumptions!$C$53,(Assumptions!K$5+Assumptions!$C$49))) | I48: =H48*(1+(Assumptions!L$5+Assumptions!$C$49)) | J48: =I48*(1+(Assumptions!M$5+Assumptions!$C$49)) | K48: =J48*(1+(Assumptions!N$5+Assumptions!$C$49)) | L48: =K48*(1+(Assumptions!O$5+Assumptions!$C$49)) | M48: =L48*(1+(Assumptions!P$5+Assumptions!$C$49))
B49: Client revenue | C49: =Assumptions!$F$12 | D49: =C49*(1+Assumptions!G$6) | E49: =D49*(1+(Assumptions!H$6+Assumptions!$C$49)) | F49: =E49*(1+(Assumptions!I$6+Assumptions!$C$49)) | G49: =F49*(1+(Assumptions!J$6+Assumptions!$C$49)) | H49: =G49*(1+(Assumptions!K$6+Assumptions!$C$49)) | I49: =H49*(1+(Assumptions!L$6+Assumptions!$C$49)) | J49: =I49*(1+(Assumptions!M$6+Assumptions!$C$49)) | K49: =J49*(1+(Assumptions!N$6+Assumptions!$C$49)) | L49: =K49*(1+(Assumptions!O$6+Assumptions!$C$49)) | M49: =L49*(1+(Assumptions!P$6+Assumptions!$C$49))
B50: Gaming revenue | C50: =Assumptions!$F$13 | D50: =C50*(1+Assumptions!G$7) | E50: =D50*(1+(Assumptions!H$7+Assumptions!$C$49)) | F50: =E50*(1+(Assumptions!I$7+Assumptions!$C$49)) | G50: =F50*(1+(Assumptions!J$7+Assumptions!$C$49)) | H50: =G50*(1+(Assumptions!K$7+Assumptions!$C$49)) | I50: =H50*(1+(Assumptions!L$7+Assumptions!$C$49)) | J50: =I50*(1+(Assumptions!M$7+Assumptions!$C$49)) | K50: =J50*(1+(Assumptions!N$7+Assumptions!$C$49)) | L50: =K50*(1+(Assumptions!O$7+Assumptions!$C$49)) | M50: =L50*(1+(Assumptions!P$7+Assumptions!$C$49))
B51: Embedded revenue | C51: =Assumptions!$F$14 | D51: =C51*(1+Assumptions!G$8) | E51: =D51*(1+(Assumptions!H$8+Assumptions!$C$49)) | F51: =E51*(1+(Assumptions!I$8+Assumptions!$C$49)) | G51: =F51*(1+(Assumptions!J$8+Assumptions!$C$49)) | H51: =G51*(1+(Assumptions!K$8+Assumptions!$C$49)) | I51: =H51*(1+(Assumptions!L$8+Assumptions!$C$49)) | J51: =I51*(1+(Assumptions!M$8+Assumptions!$C$49)) | K51: =J51*(1+(Assumptions!N$8+Assumptions!$C$49)) | L51: =K51*(1+(Assumptions!O$8+Assumptions!$C$49)) | M51: =L51*(1+(Assumptions!P$8+Assumptions!$C$49))
B52: Total revenue | C52: =SUM(C48:C51) | D52: =SUM(D48:D51) | E52: =SUM(E48:E51) | F52: =SUM(F48:F51) | G52: =SUM(G48:G51) | H52: =SUM(H48:H51) | I52: =SUM(I48:I51) | J52: =SUM(J48:J51) | ... M52: =SUM(M48:M51)
B53: EBITDA | D53: =D52*(Assumptions!G$19) | E53: =E52*(Assumptions!H$19+Assumptions!$C$50) | F53: =F52*(Assumptions!I$19+Assumptions!$C$50) | G53: =G52*(Assumptions!J$19+Assumptions!$C$50) | H53: =H52*(Assumptions!K$19+Assumptions!$C$50) | I53: =I52*(Assumptions!L$19+Assumptions!$C$50) | J53: =J52*(Assumptions!M$19+Assumptions!$C$50) | K53: =K52*(Assumptions!N$19+Assumptions!$C$50) | L53: =L52*(Assumptions!O$19+Assumptions!$C$50) | M53: =M52*(Assumptions!P$19+Assumptions!$C$50)
B54: D&A | D54: =Assumptions!G$20 | E54: =Assumptions!H$20 | F54: =Assumptions!I$20 | G54: =Assumptions!J$20 | H54: =Assumptions!K$20 | I54: =Assumptions!L$20 | J54: =Assumptions!M$20 | K54: =Assumptions!N$20 | ... M54: =Assumptions!P$20
B55: EBIT | D55: =D53-D54 | E55: =E53-E54 | F55: =F53-F54 | G55: =G53-G54 | H55: =H53-H54 | I55: =I53-I54 | J55: =J53-J54 | K55: =K53-K54 | ... M55: =M53-M54
B56: Cash taxes | D56: =-MAX(0,D55)*Assumptions!G$21 | E56: =-MAX(0,E55)*Assumptions!H$21 | F56: =-MAX(0,F55)*Assumptions!I$21 | G56: =-MAX(0,G55)*Assumptions!J$21 | H56: =-MAX(0,H55)*Assumptions!K$21 | I56: =-MAX(0,I55)*Assumptions!L$21 | J56: =-MAX(0,J55)*Assumptions!M$21 | K56: =-MAX(0,K55)*Assumptions!N$21 | ... M56: =-MAX(0,M55)*Assumptions!P$21
B57: Capex | D57: =-Assumptions!G$22 | E57: =-Assumptions!H$22 | F57: =-Assumptions!I$22 | G57: =-Assumptions!J$22 | H57: =-Assumptions!K$22 | I57: =-Assumptions!L$22 | J57: =-Assumptions!M$22 | K57: =-Assumptions!N$22 | ... M57: =-Assumptions!P$22
B58: Δ Working capital | D58: =-(D52-C52)*Assumptions!G$23 | E58: =-(E52-D52)*Assumptions!H$23 | F58: =-(F52-E52)*Assumptions!I$23 | G58: =-(G52-F52)*Assumptions!J$23 | H58: =-(H52-G52)*Assumptions!K$23 | I58: =-(I52-H52)*Assumptions!L$23 | J58: =-(J52-I52)*Assumptions!M$23 | K58: =-(K52-J52)*Assumptions!N$23 | ... M58: =-(M52-L52)*Assumptions!P$23
B59: Unlevered FCF | D59: =D55+D56+D54+D57+D58 | E59: =E55+E56+E54+E57+E58 | F59: =F55+F56+F54+F57+F58 | G59: =G55+G56+G54+G57+G58 | H59: =H55+H56+H54+H57+H58 | I59: =I55+I56+I54+I57+I58 | J59: =J55+J56+J54+J57+J58 | K59: =K55+K56+K54+K57+K58 | ... M59: =M55+M56+M54+M57+M58 | N59: =DCF!$C$14+Assumptions!$C$51
B60: PV of FCF (stub & mid-year) | D60: =D59*DCF!D$18/(1+$N$59)^DCF!D$19 | E60: =E59*DCF!E$18/(1+$N$59)^DCF!E$19 | F60: =F59*DCF!F$18/(1+$N$59)^DCF!F$19 | G60: =G59*DCF!G$18/(1+$N$59)^DCF!G$19 | H60: =H59*DCF!H$18/(1+$N$59)^DCF!H$19 | I60: =I59*DCF!I$18/(1+$N$59)^DCF!I$19 | J60: =J59*DCF!J$18/(1+$N$59)^DCF!J$19 | K60: =K59*DCF!K$18/(1+$N$59)^DCF!K$19 | ... M60: =M59*DCF!M$18/(1+$N$59)^DCF!M$19 | N60: =Assumptions!$C$52
B61: Bear value per share | C61: =(SUM(D60:M60)+M59*(1+$N$60)/($N$59-$N$60)/(1+$N$59)^DCF!$M$19+DCF!$C$31-DCF!$C$32)/DCF!$C$34
B63: Base · Data Center revenue | C63: =Assumptions!$F$11 | D63: =C63*(1+Assumptions!G$5) | E63: =D63*(1+IF(ISNUMBER(Assumptions!$D$53),Assumptions!$D$53,(Assumptions!H$5+Assumptions!$D$49))) | F63: =E63*(1+IF(ISNUMBER(Assumptions!$D$53),Assumptions!$D$53,(Assumptions!I$5+Assumptions!$D$49))) | G63: =F63*(1+IF(ISNUMBER(Assumptions!$D$53),Assumptions!$D$53,(Assumptions!J$5+Assumptions!$D$49))) | H63: =G63*(1+IF(ISNUMBER(Assumptions!$D$53),Assumptions!$D$53,(Assumptions!K$5+Assumptions!$D$49))) | I63: =H63*(1+(Assumptions!L$5+Assumptions!$D$49)) | J63: =I63*(1+(Assumptions!M$5+Assumptions!$D$49)) | K63: =J63*(1+(Assumptions!N$5+Assumptions!$D$49)) | L63: =K63*(1+(Assumptions!O$5+Assumptions!$D$49)) | M63: =L63*(1+(Assumptions!P$5+Assumptions!$D$49))
B64: Client revenue | C64: =Assumptions!$F$12 | D64: =C64*(1+Assumptions!G$6) | E64: =D64*(1+(Assumptions!H$6+Assumptions!$D$49)) | F64: =E64*(1+(Assumptions!I$6+Assumptions!$D$49)) | G64: =F64*(1+(Assumptions!J$6+Assumptions!$D$49)) | H64: =G64*(1+(Assumptions!K$6+Assumptions!$D$49)) | I64: =H64*(1+(Assumptions!L$6+Assumptions!$D$49)) | J64: =I64*(1+(Assumptions!M$6+Assumptions!$D$49)) | K64: =J64*(1+(Assumptions!N$6+Assumptions!$D$49)) | L64: =K64*(1+(Assumptions!O$6+Assumptions!$D$49)) | M64: =L64*(1+(Assumptions!P$6+Assumptions!$D$49))
B65: Gaming revenue | C65: =Assumptions!$F$13 | D65: =C65*(1+Assumptions!G$7) | E65: =D65*(1+(Assumptions!H$7+Assumptions!$D$49)) | F65: =E65*(1+(Assumptions!I$7+Assumptions!$D$49)) | G65: =F65*(1+(Assumptions!J$7+Assumptions!$D$49)) | H65: =G65*(1+(Assumptions!K$7+Assumptions!$D$49)) | I65: =H65*(1+(Assumptions!L$7+Assumptions!$D$49)) | J65: =I65*(1+(Assumptions!M$7+Assumptions!$D$49)) | K65: =J65*(1+(Assumptions!N$7+Assumptions!$D$49)) | L65: =K65*(1+(Assumptions!O$7+Assumptions!$D$49)) | M65: =L65*(1+(Assumptions!P$7+Assumptions!$D$49))
B66: Embedded revenue | C66: =Assumptions!$F$14 | D66: =C66*(1+Assumptions!G$8) | E66: =D66*(1+(Assumptions!H$8+Assumptions!$D$49)) | F66: =E66*(1+(Assumptions!I$8+Assumptions!$D$49)) | G66: =F66*(1+(Assumptions!J$8+Assumptions!$D$49)) | H66: =G66*(1+(Assumptions!K$8+Assumptions!$D$49)) | I66: =H66*(1+(Assumptions!L$8+Assumptions!$D$49)) | J66: =I66*(1+(Assumptions!M$8+Assumptions!$D$49)) | K66: =J66*(1+(Assumptions!N$8+Assumptions!$D$49)) | L66: =K66*(1+(Assumptions!O$8+Assumptions!$D$49)) | M66: =L66*(1+(Assumptions!P$8+Assumptions!$D$49))
B67: Total revenue | C67: =SUM(C63:C66) | D67: =SUM(D63:D66) | E67: =SUM(E63:E66) | F67: =SUM(F63:F66) | G67: =SUM(G63:G66) | H67: =SUM(H63:H66) | I67: =SUM(I63:I66) | J67: =SUM(J63:J66) | ... M67: =SUM(M63:M66)
B68: EBITDA | D68: =D67*(Assumptions!G$19) | E68: =E67*(Assumptions!H$19+Assumptions!$D$50) | F68: =F67*(Assumptions!I$19+Assumptions!$D$50) | G68: =G67*(Assumptions!J$19+Assumptions!$D$50) | H68: =H67*(Assumptions!K$19+Assumptions!$D$50) | I68: =I67*(Assumptions!L$19+Assumptions!$D$50) | J68: =J67*(Assumptions!M$19+Assumptions!$D$50) | K68: =K67*(Assumptions!N$19+Assumptions!$D$50) | L68: =L67*(Assumptions!O$19+Assumptions!$D$50) | M68: =M67*(Assumptions!P$19+Assumptions!$D$50)
B69: D&A | D69: =Assumptions!G$20 | E69: =Assumptions!H$20 | F69: =Assumptions!I$20 | G69: =Assumptions!J$20 | H69: =Assumptions!K$20 | I69: =Assumptions!L$20 | J69: =Assumptions!M$20 | K69: =Assumptions!N$20 | ... M69: =Assumptions!P$20
B70: EBIT | D70: =D68-D69 | E70: =E68-E69 | F70: =F68-F69 | G70: =G68-G69 | H70: =H68-H69 | I70: =I68-I69 | J70: =J68-J69 | K70: =K68-K69 | ... M70: =M68-M69
B71: Cash taxes | D71: =-MAX(0,D70)*Assumptions!G$21 | E71: =-MAX(0,E70)*Assumptions!H$21 | F71: =-MAX(0,F70)*Assumptions!I$21 | G71: =-MAX(0,G70)*Assumptions!J$21 | H71: =-MAX(0,H70)*Assumptions!K$21 | I71: =-MAX(0,I70)*Assumptions!L$21 | J71: =-MAX(0,J70)*Assumptions!M$21 | K71: =-MAX(0,K70)*Assumptions!N$21 | ... M71: =-MAX(0,M70)*Assumptions!P$21
B72: Capex | D72: =-Assumptions!G$22 | E72: =-Assumptions!H$22 | F72: =-Assumptions!I$22 | G72: =-Assumptions!J$22 | H72: =-Assumptions!K$22 | I72: =-Assumptions!L$22 | J72: =-Assumptions!M$22 | K72: =-Assumptions!N$22 | ... M72: =-Assumptions!P$22
B73: Δ Working capital | D73: =-(D67-C67)*Assumptions!G$23 | E73: =-(E67-D67)*Assumptions!H$23 | F73: =-(F67-E67)*Assumptions!I$23 | G73: =-(G67-F67)*Assumptions!J$23 | H73: =-(H67-G67)*Assumptions!K$23 | I73: =-(I67-H67)*Assumptions!L$23 | J73: =-(J67-I67)*Assumptions!M$23 | K73: =-(K67-J67)*Assumptions!N$23 | ... M73: =-(M67-L67)*Assumptions!P$23
B74: Unlevered FCF | D74: =D70+D71+D69+D72+D73 | E74: =E70+E71+E69+E72+E73 | F74: =F70+F71+F69+F72+F73 | G74: =G70+G71+G69+G72+G73 | H74: =H70+H71+H69+H72+H73 | I74: =I70+I71+I69+I72+I73 | J74: =J70+J71+J69+J72+J73 | K74: =K70+K71+K69+K72+K73 | ... M74: =M70+M71+M69+M72+M73 | N74: =DCF!$C$14+Assumptions!$D$51
B75: PV of FCF (stub & mid-year) | D75: =D74*DCF!D$18/(1+$N$74)^DCF!D$19 | E75: =E74*DCF!E$18/(1+$N$74)^DCF!E$19 | F75: =F74*DCF!F$18/(1+$N$74)^DCF!F$19 | G75: =G74*DCF!G$18/(1+$N$74)^DCF!G$19 | H75: =H74*DCF!H$18/(1+$N$74)^DCF!H$19 | I75: =I74*DCF!I$18/(1+$N$74)^DCF!I$19 | J75: =J74*DCF!J$18/(1+$N$74)^DCF!J$19 | K75: =K74*DCF!K$18/(1+$N$74)^DCF!K$19 | ... M75: =M74*DCF!M$18/(1+$N$74)^DCF!M$19 | N75: =Assumptions!$D$52
B76: Base value per share | C76: =(SUM(D75:M75)+M74*(1+$N$75)/($N$74-$N$75)/(1+$N$74)^DCF!$M$19+DCF!$C$31-DCF!$C$32)/DCF!$C$34
B78: Bull · Data Center revenue | C78: =Assumptions!$F$11 | D78: =C78*(1+Assumptions!G$5) | E78: =D78*(1+IF(ISNUMBER(Assumptions!$E$53),Assumptions!$E$53,(Assumptions!H$5+Assumptions!$E$49))) | F78: =E78*(1+IF(ISNUMBER(Assumptions!$E$53),Assumptions!$E$53,(Assumptions!I$5+Assumptions!$E$49))) | G78: =F78*(1+IF(ISNUMBER(Assumptions!$E$53),Assumptions!$E$53,(Assumptions!J$5+Assumptions!$E$49))) | H78: =G78*(1+IF(ISNUMBER(Assumptions!$E$53),Assumptions!$E$53,(Assumptions!K$5+Assumptions!$E$49))) | I78: =H78*(1+(Assumptions!L$5+Assumptions!$E$49)) | J78: =I78*(1+(Assumptions!M$5+Assumptions!$E$49)) | K78: =J78*(1+(Assumptions!N$5+Assumptions!$E$49)) | L78: =K78*(1+(Assumptions!O$5+Assumptions!$E$49)) | M78: =L78*(1+(Assumptions!P$5+Assumptions!$E$49))
B79: Client revenue | C79: =Assumptions!$F$12 | D79: =C79*(1+Assumptions!G$6) | E79: =D79*(1+(Assumptions!H$6+Assumptions!$E$49)) | F79: =E79*(1+(Assumptions!I$6+Assumptions!$E$49)) | G79: =F79*(1+(Assumptions!J$6+Assumptions!$E$49)) | H79: =G79*(1+(Assumptions!K$6+Assumptions!$E$49)) | I79: =H79*(1+(Assumptions!L$6+Assumptions!$E$49)) | J79: =I79*(1+(Assumptions!M$6+Assumptions!$E$49)) | K79: =J79*(1+(Assumptions!N$6+Assumptions!$E$49)) | L79: =K79*(1+(Assumptions!O$6+Assumptions!$E$49)) | M79: =L79*(1+(Assumptions!P$6+Assumptions!$E$49))
B80: Gaming revenue | C80: =Assumptions!$F$13 | D80: =C80*(1+Assumptions!G$7) | E80: =D80*(1+(Assumptions!H$7+Assumptions!$E$49)) | F80: =E80*(1+(Assumptions!I$7+Assumptions!$E$49)) | G80: =F80*(1+(Assumptions!J$7+Assumptions!$E$49)) | H80: =G80*(1+(Assumptions!K$7+Assumptions!$E$49)) | I80: =H80*(1+(Assumptions!L$7+Assumptions!$E$49)) | J80: =I80*(1+(Assumptions!M$7+Assumptions!$E$49)) | K80: =J80*(1+(Assumptions!N$7+Assumptions!$E$49)) | L80: =K80*(1+(Assumptions!O$7+Assumptions!$E$49)) | M80: =L80*(1+(Assumptions!P$7+Assumptions!$E$49))
B81: Embedded revenue | C81: =Assumptions!$F$14 | D81: =C81*(1+Assumptions!G$8) | E81: =D81*(1+(Assumptions!H$8+Assumptions!$E$49)) | F81: =E81*(1+(Assumptions!I$8+Assumptions!$E$49)) | G81: =F81*(1+(Assumptions!J$8+Assumptions!$E$49)) | H81: =G81*(1+(Assumptions!K$8+Assumptions!$E$49)) | I81: =H81*(1+(Assumptions!L$8+Assumptions!$E$49)) | J81: =I81*(1+(Assumptions!M$8+Assumptions!$E$49)) | K81: =J81*(1+(Assumptions!N$8+Assumptions!$E$49)) | L81: =K81*(1+(Assumptions!O$8+Assumptions!$E$49)) | M81: =L81*(1+(Assumptions!P$8+Assumptions!$E$49))
B82: Total revenue | C82: =SUM(C78:C81) | D82: =SUM(D78:D81) | E82: =SUM(E78:E81) | F82: =SUM(F78:F81) | G82: =SUM(G78:G81) | H82: =SUM(H78:H81) | I82: =SUM(I78:I81) | J82: =SUM(J78:J81) | ... M82: =SUM(M78:M81)
B83: EBITDA | D83: =D82*(Assumptions!G$19) | E83: =E82*(Assumptions!H$19+Assumptions!$E$50) | F83: =F82*(Assumptions!I$19+Assumptions!$E$50) | G83: =G82*(Assumptions!J$19+Assumptions!$E$50) | H83: =H82*(Assumptions!K$19+Assumptions!$E$50) | I83: =I82*(Assumptions!L$19+Assumptions!$E$50) | J83: =J82*(Assumptions!M$19+Assumptions!$E$50) | K83: =K82*(Assumptions!N$19+Assumptions!$E$50) | L83: =L82*(Assumptions!O$19+Assumptions!$E$50) | M83: =M82*(Assumptions!P$19+Assumptions!$E$50)
B84: D&A | D84: =Assumptions!G$20 | E84: =Assumptions!H$20 | F84: =Assumptions!I$20 | G84: =Assumptions!J$20 | H84: =Assumptions!K$20 | I84: =Assumptions!L$20 | J84: =Assumptions!M$20 | K84: =Assumptions!N$20 | ... M84: =Assumptions!P$20
B85: EBIT | D85: =D83-D84 | E85: =E83-E84 | F85: =F83-F84 | G85: =G83-G84 | H85: =H83-H84 | I85: =I83-I84 | J85: =J83-J84 | K85: =K83-K84 | ... M85: =M83-M84
B86: Cash taxes | D86: =-MAX(0,D85)*Assumptions!G$21 | E86: =-MAX(0,E85)*Assumptions!H$21 | F86: =-MAX(0,F85)*Assumptions!I$21 | G86: =-MAX(0,G85)*Assumptions!J$21 | H86: =-MAX(0,H85)*Assumptions!K$21 | I86: =-MAX(0,I85)*Assumptions!L$21 | J86: =-MAX(0,J85)*Assumptions!M$21 | K86: =-MAX(0,K85)*Assumptions!N$21 | ... M86: =-MAX(0,M85)*Assumptions!P$21
B87: Capex | D87: =-Assumptions!G$22 | E87: =-Assumptions!H$22 | F87: =-Assumptions!I$22 | G87: =-Assumptions!J$22 | H87: =-Assumptions!K$22 | I87: =-Assumptions!L$22 | J87: =-Assumptions!M$22 | K87: =-Assumptions!N$22 | ... M87: =-Assumptions!P$22
B88: Δ Working capital | D88: =-(D82-C82)*Assumptions!G$23 | E88: =-(E82-D82)*Assumptions!H$23 | F88: =-(F82-E82)*Assumptions!I$23 | G88: =-(G82-F82)*Assumptions!J$23 | H88: =-(H82-G82)*Assumptions!K$23 | I88: =-(I82-H82)*Assumptions!L$23 | J88: =-(J82-I82)*Assumptions!M$23 | K88: =-(K82-J82)*Assumptions!N$23 | ... M88: =-(M82-L82)*Assumptions!P$23
B89: Unlevered FCF | D89: =D85+D86+D84+D87+D88 | E89: =E85+E86+E84+E87+E88 | F89: =F85+F86+F84+F87+F88 | G89: =G85+G86+G84+G87+G88 | H89: =H85+H86+H84+H87+H88 | I89: =I85+I86+I84+I87+I88 | J89: =J85+J86+J84+J87+J88 | K89: =K85+K86+K84+K87+K88 | ... M89: =M85+M86+M84+M87+M88 | N89: =DCF!$C$14+Assumptions!$E$51
B90: PV of FCF (stub & mid-year) | D90: =D89*DCF!D$18/(1+$N$89)^DCF!D$19 | E90: =E89*DCF!E$18/(1+$N$89)^DCF!E$19 | F90: =F89*DCF!F$18/(1+$N$89)^DCF!F$19 | G90: =G89*DCF!G$18/(1+$N$89)^DCF!G$19 | H90: =H89*DCF!H$18/(1+$N$89)^DCF!H$19 | I90: =I89*DCF!I$18/(1+$N$89)^DCF!I$19 | J90: =J89*DCF!J$18/(1+$N$89)^DCF!J$19 | K90: =K89*DCF!K$18/(1+$N$89)^DCF!K$19 | ... M90: =M89*DCF!M$18/(1+$N$89)^DCF!M$19 | N90: =Assumptions!$E$52
B91: Bull value per share | C91: =(SUM(D90:M90)+M89*(1+$N$90)/($N$89-$N$90)/(1+$N$89)^DCF!$M$19+DCF!$C$31-DCF!$C$32)/DCF!$C$34
B93: DC Downside · Data Center revenue | C93: =Assumptions!$F$11 | D93: =C93*(1+Assumptions!G$5) | E93: =D93*(1+IF(ISNUMBER(Assumptions!$F$53),Assumptions!$F$53,(Assumptions!H$5+Assumptions!$F$49))) | F93: =E93*(1+IF(ISNUMBER(Assumptions!$F$53),Assumptions!$F$53,(Assumptions!I$5+Assumptions!$F$49))) | G93: =F93*(1+IF(ISNUMBER(Assumptions!$F$53),Assumptions!$F$53,(Assumptions!J$5+Assumptions!$F$49))) | H93: =G93*(1+IF(ISNUMBER(Assumptions!$F$53),Assumptions!$F$53,(Assumptions!K$5+Assumptions!$F$49))) | I93: =H93*(1+(Assumptions!L$5+Assumptions!$F$49)) | J93: =I93*(1+(Assumptions!M$5+Assumptions!$F$49)) | K93: =J93*(1+(Assumptions!N$5+Assumptions!$F$49)) | L93: =K93*(1+(Assumptions!O$5+Assumptions!$F$49)) | M93: =L93*(1+(Assumptions!P$5+Assumptions!$F$49))
B94: Client revenue | C94: =Assumptions!$F$12 | D94: =C94*(1+Assumptions!G$6) | E94: =D94*(1+(Assumptions!H$6+Assumptions!$F$49)) | F94: =E94*(1+(Assumptions!I$6+Assumptions!$F$49)) | G94: =F94*(1+(Assumptions!J$6+Assumptions!$F$49)) | H94: =G94*(1+(Assumptions!K$6+Assumptions!$F$49)) | I94: =H94*(1+(Assumptions!L$6+Assumptions!$F$49)) | J94: =I94*(1+(Assumptions!M$6+Assumptions!$F$49)) | K94: =J94*(1+(Assumptions!N$6+Assumptions!$F$49)) | L94: =K94*(1+(Assumptions!O$6+Assumptions!$F$49)) | M94: =L94*(1+(Assumptions!P$6+Assumptions!$F$49))
B95: Gaming revenue | C95: =Assumptions!$F$13 | D95: =C95*(1+Assumptions!G$7) | E95: =D95*(1+(Assumptions!H$7+Assumptions!$F$49)) | F95: =E95*(1+(Assumptions!I$7+Assumptions!$F$49)) | G95: =F95*(1+(Assumptions!J$7+Assumptions!$F$49)) | H95: =G95*(1+(Assumptions!K$7+Assumptions!$F$49)) | I95: =H95*(1+(Assumptions!L$7+Assumptions!$F$49)) | J95: =I95*(1+(Assumptions!M$7+Assumptions!$F$49)) | K95: =J95*(1+(Assumptions!N$7+Assumptions!$F$49)) | L95: =K95*(1+(Assumptions!O$7+Assumptions!$F$49)) | M95: =L95*(1+(Assumptions!P$7+Assumptions!$F$49))
B96: Embedded revenue | C96: =Assumptions!$F$14 | D96: =C96*(1+Assumptions!G$8) | E96: =D96*(1+(Assumptions!H$8+Assumptions!$F$49)) | F96: =E96*(1+(Assumptions!I$8+Assumptions!$F$49)) | G96: =F96*(1+(Assumptions!J$8+Assumptions!$F$49)) | H96: =G96*(1+(Assumptions!K$8+Assumptions!$F$49)) | I96: =H96*(1+(Assumptions!L$8+Assumptions!$F$49)) | J96: =I96*(1+(Assumptions!M$8+Assumptions!$F$49)) | K96: =J96*(1+(Assumptions!N$8+Assumptions!$F$49)) | L96: =K96*(1+(Assumptions!O$8+Assumptions!$F$49)) | M96: =L96*(1+(Assumptions!P$8+Assumptions!$F$49))
B97: Total revenue | C97: =SUM(C93:C96) | D97: =SUM(D93:D96) | E97: =SUM(E93:E96) | F97: =SUM(F93:F96) | G97: =SUM(G93:G96) | H97: =SUM(H93:H96) | I97: =SUM(I93:I96) | J97: =SUM(J93:J96) | ... M97: =SUM(M93:M96)
B98: EBITDA | D98: =D97*(Assumptions!G$19) | E98: =E97*(Assumptions!H$19+Assumptions!$F$50) | F98: =F97*(Assumptions!I$19+Assumptions!$F$50) | G98: =G97*(Assumptions!J$19+Assumptions!$F$50) | H98: =H97*(Assumptions!K$19+Assumptions!$F$50) | I98: =I97*(Assumptions!L$19+Assumptions!$F$50) | J98: =J97*(Assumptions!M$19+Assumptions!$F$50) | K98: =K97*(Assumptions!N$19+Assumptions!$F$50) | L98: =L97*(Assumptions!O$19+Assumptions!$F$50) | M98: =M97*(Assumptions!P$19+Assumptions!$F$50)
B99: D&A | D99: =Assumptions!G$20 | E99: =Assumptions!H$20 | F99: =Assumptions!I$20 | G99: =Assumptions!J$20 | H99: =Assumptions!K$20 | I99: =Assumptions!L$20 | J99: =Assumptions!M$20 | K99: =Assumptions!N$20 | ... M99: =Assumptions!P$20
B100: EBIT | D100: =D98-D99 | E100: =E98-E99 | F100: =F98-F99 | G100: =G98-G99 | H100: =H98-H99 | I100: =I98-I99 | J100: =J98-J99 | K100: =K98-K99 | ... M100: =M98-M99
B101: Cash taxes | D101: =-MAX(0,D100)*Assumptions!G$21 | E101: =-MAX(0,E100)*Assumptions!H$21 | F101: =-MAX(0,F100)*Assumptions!I$21 | G101: =-MAX(0,G100)*Assumptions!J$21 | H101: =-MAX(0,H100)*Assumptions!K$21 | I101: =-MAX(0,I100)*Assumptions!L$21 | J101: =-MAX(0,J100)*Assumptions!M$21 | K101: =-MAX(0,K100)*Assumptions!N$21 | ... M101: =-MAX(0,M100)*Assumptions!P$21
B102: Capex | D102: =-Assumptions!G$22 | E102: =-Assumptions!H$22 | F102: =-Assumptions!I$22 | G102: =-Assumptions!J$22 | H102: =-Assumptions!K$22 | I102: =-Assumptions!L$22 | J102: =-Assumptions!M$22 | K102: =-Assumptions!N$22 | ... M102: =-Assumptions!P$22
B103: Δ Working capital | D103: =-(D97-C97)*Assumptions!G$23 | E103: =-(E97-D97)*Assumptions!H$23 | F103: =-(F97-E97)*Assumptions!I$23 | G103: =-(G97-F97)*Assumptions!J$23 | H103: =-(H97-G97)*Assumptions!K$23 | I103: =-(I97-H97)*Assumptions!L$23 | J103: =-(J97-I97)*Assumptions!M$23 | K103: =-(K97-J97)*Assumptions!N$23 | ... M103: =-(M97-L97)*Assumptions!P$23
B104: Unlevered FCF | D104: =D100+D101+D99+D102+D103 | E104: =E100+E101+E99+E102+E103 | F104: =F100+F101+F99+F102+F103 | G104: =G100+G101+G99+G102+G103 | H104: =H100+H101+H99+H102+H103 | I104: =I100+I101+I99+I102+I103 | J104: =J100+J101+J99+J102+J103 | K104: =K100+K101+K99+K102+K103 | ... M104: =M100+M101+M99+M102+M103 | N104: =DCF!$C$14+Assumptions!$F$51
B105: PV of FCF (stub & mid-year) | D105: =D104*DCF!D$18/(1+$N$104)^DCF!D$19 | E105: =E104*DCF!E$18/(1+$N$104)^DCF!E$19 | F105: =F104*DCF!F$18/(1+$N$104)^DCF!F$19 | G105: =G104*DCF!G$18/(1+$N$104)^DCF!G$19 | H105: =H104*DCF!H$18/(1+$N$104)^DCF!H$19 | I105: =I104*DCF!I$18/(1+$N$104)^DCF!I$19 | J105: =J104*DCF!J$18/(1+$N$104)^DCF!J$19 | K105: =K104*DCF!K$18/(1+$N$104)^DCF!K$19 | ... M105: =M104*DCF!M$18/(1+$N$104)^DCF!M$19 | N105: =Assumptions!$F$52
B106: DC Downside value per share | C106: =(SUM(D105:M105)+M104*(1+$N$105)/($N$104-$N$105)/(1+$N$104)^DCF!$M$19+DCF!$C$31-DCF!$C$32)/DCF!$C$34
B108: DC Base · Data Center revenue | C108: =Assumptions!$F$11 | D108: =C108*(1+Assumptions!G$5) | E108: =D108*(1+IF(ISNUMBER(Assumptions!$G$53),Assumptions!$G$53,(Assumptions!H$5+Assumptions!$G$49))) | F108: =E108*(1+IF(ISNUMBER(Assumptions!$G$53),Assumptions!$G$53,(Assumptions!I$5+Assumptions!$G$49))) | G108: =F108*(1+IF(ISNUMBER(Assumptions!$G$53),Assumptions!$G$53,(Assumptions!J$5+Assumptions!$G$49))) | H108: =G108*(1+IF(ISNUMBER(Assumptions!$G$53),Assumptions!$G$53,(Assumptions!K$5+Assumptions!$G$49))) | I108: =H108*(1+(Assumptions!L$5+Assumptions!$G$49)) | J108: =I108*(1+(Assumptions!M$5+Assumptions!$G$49)) | K108: =J108*(1+(Assumptions!N$5+Assumptions!$G$49)) | L108: =K108*(1+(Assumptions!O$5+Assumptions!$G$49)) | M108: =L108*(1+(Assumptions!P$5+Assumptions!$G$49))
B109: Client revenue | C109: =Assumptions!$F$12 | D109: =C109*(1+Assumptions!G$6) | E109: =D109*(1+(Assumptions!H$6+Assumptions!$G$49)) | F109: =E109*(1+(Assumptions!I$6+Assumptions!$G$49)) | G109: =F109*(1+(Assumptions!J$6+Assumptions!$G$49)) | H109: =G109*(1+(Assumptions!K$6+Assumptions!$G$49)) | I109: =H109*(1+(Assumptions!L$6+Assumptions!$G$49)) | J109: =I109*(1+(Assumptions!M$6+Assumptions!$G$49)) | K109: =J109*(1+(Assumptions!N$6+Assumptions!$G$49)) | L109: =K109*(1+(Assumptions!O$6+Assumptions!$G$49)) | M109: =L109*(1+(Assumptions!P$6+Assumptions!$G$49))
B110: Gaming revenue | C110: =Assumptions!$F$13 | D110: =C110*(1+Assumptions!G$7) | E110: =D110*(1+(Assumptions!H$7+Assumptions!$G$49)) | F110: =E110*(1+(Assumptions!I$7+Assumptions!$G$49)) | G110: =F110*(1+(Assumptions!J$7+Assumptions!$G$49)) | H110: =G110*(1+(Assumptions!K$7+Assumptions!$G$49)) | I110: =H110*(1+(Assumptions!L$7+Assumptions!$G$49)) | J110: =I110*(1+(Assumptions!M$7+Assumptions!$G$49)) | K110: =J110*(1+(Assumptions!N$7+Assumptions!$G$49)) | L110: =K110*(1+(Assumptions!O$7+Assumptions!$G$49)) | M110: =L110*(1+(Assumptions!P$7+Assumptions!$G$49))
B111: Embedded revenue | C111: =Assumptions!$F$14 | D111: =C111*(1+Assumptions!G$8) | E111: =D111*(1+(Assumptions!H$8+Assumptions!$G$49)) | F111: =E111*(1+(Assumptions!I$8+Assumptions!$G$49)) | G111: =F111*(1+(Assumptions!J$8+Assumptions!$G$49)) | H111: =G111*(1+(Assumptions!K$8+Assumptions!$G$49)) | I111: =H111*(1+(Assumptions!L$8+Assumptions!$G$49)) | J111: =I111*(1+(Assumptions!M$8+Assumptions!$G$49)) | K111: =J111*(1+(Assumptions!N$8+Assumptions!$G$49)) | L111: =K111*(1+(Assumptions!O$8+Assumptions!$G$49)) | M111: =L111*(1+(Assumptions!P$8+Assumptions!$G$49))
B112: Total revenue | C112: =SUM(C108:C111) | D112: =SUM(D108:D111) | E112: =SUM(E108:E111) | F112: =SUM(F108:F111) | G112: =SUM(G108:G111) | H112: =SUM(H108:H111) | I112: =SUM(I108:I111) | J112: =SUM(J108:J111) | ... M112: =SUM(M108:M111)
B113: EBITDA | D113: =D112*(Assumptions!G$19) | E113: =E112*(Assumptions!H$19+Assumptions!$G$50) | F113: =F112*(Assumptions!I$19+Assumptions!$G$50) | G113: =G112*(Assumptions!J$19+Assumptions!$G$50) | H113: =H112*(Assumptions!K$19+Assumptions!$G$50) | I113: =I112*(Assumptions!L$19+Assumptions!$G$50) | J113: =J112*(Assumptions!M$19+Assumptions!$G$50) | K113: =K112*(Assumptions!N$19+Assumptions!$G$50) | L113: =L112*(Assumptions!O$19+Assumptions!$G$50) | M113: =M112*(Assumptions!P$19+Assumptions!$G$50)
B114: D&A | D114: =Assumptions!G$20 | E114: =Assumptions!H$20 | F114: =Assumptions!I$20 | G114: =Assumptions!J$20 | H114: =Assumptions!K$20 | I114: =Assumptions!L$20 | J114: =Assumptions!M$20 | K114: =Assumptions!N$20 | ... M114: =Assumptions!P$20
B115: EBIT | D115: =D113-D114 | E115: =E113-E114 | F115: =F113-F114 | G115: =G113-G114 | H115: =H113-H114 | I115: =I113-I114 | J115: =J113-J114 | K115: =K113-K114 | ... M115: =M113-M114
B116: Cash taxes | D116: =-MAX(0,D115)*Assumptions!G$21 | E116: =-MAX(0,E115)*Assumptions!H$21 | F116: =-MAX(0,F115)*Assumptions!I$21 | G116: =-MAX(0,G115)*Assumptions!J$21 | H116: =-MAX(0,H115)*Assumptions!K$21 | I116: =-MAX(0,I115)*Assumptions!L$21 | J116: =-MAX(0,J115)*Assumptions!M$21 | K116: =-MAX(0,K115)*Assumptions!N$21 | ... M116: =-MAX(0,M115)*Assumptions!P$21
B117: Capex | D117: =-Assumptions!G$22 | E117: =-Assumptions!H$22 | F117: =-Assumptions!I$22 | G117: =-Assumptions!J$22 | H117: =-Assumptions!K$22 | I117: =-Assumptions!L$22 | J117: =-Assumptions!M$22 | K117: =-Assumptions!N$22 | ... M117: =-Assumptions!P$22
B118: Δ Working capital | D118: =-(D112-C112)*Assumptions!G$23 | E118: =-(E112-D112)*Assumptions!H$23 | F118: =-(F112-E112)*Assumptions!I$23 | G118: =-(G112-F112)*Assumptions!J$23 | H118: =-(H112-G112)*Assumptions!K$23 | I118: =-(I112-H112)*Assumptions!L$23 | J118: =-(J112-I112)*Assumptions!M$23 | K118: =-(K112-J112)*Assumptions!N$23 | ... M118: =-(M112-L112)*Assumptions!P$23
B119: Unlevered FCF | D119: =D115+D116+D114+D117+D118 | E119: =E115+E116+E114+E117+E118 | F119: =F115+F116+F114+F117+F118 | G119: =G115+G116+G114+G117+G118 | H119: =H115+H116+H114+H117+H118 | I119: =I115+I116+I114+I117+I118 | J119: =J115+J116+J114+J117+J118 | K119: =K115+K116+K114+K117+K118 | ... M119: =M115+M116+M114+M117+M118 | N119: =DCF!$C$14+Assumptions!$G$51
B120: PV of FCF (stub & mid-year) | D120: =D119*DCF!D$18/(1+$N$119)^DCF!D$19 | E120: =E119*DCF!E$18/(1+$N$119)^DCF!E$19 | F120: =F119*DCF!F$18/(1+$N$119)^DCF!F$19 | G120: =G119*DCF!G$18/(1+$N$119)^DCF!G$19 | H120: =H119*DCF!H$18/(1+$N$119)^DCF!H$19 | I120: =I119*DCF!I$18/(1+$N$119)^DCF!I$19 | J120: =J119*DCF!J$18/(1+$N$119)^DCF!J$19 | K120: =K119*DCF!K$18/(1+$N$119)^DCF!K$19 | ... M120: =M119*DCF!M$18/(1+$N$119)^DCF!M$19 | N120: =Assumptions!$G$52
B121: DC Base value per share | C121: =(SUM(D120:M120)+M119*(1+$N$120)/($N$119-$N$120)/(1+$N$119)^DCF!$M$19+DCF!$C$31-DCF!$C$32)/DCF!$C$34
B123: DC Bull · Data Center revenue | C123: =Assumptions!$F$11 | D123: =C123*(1+Assumptions!G$5) | E123: =D123*(1+IF(ISNUMBER(Assumptions!$H$53),Assumptions!$H$53,(Assumptions!H$5+Assumptions!$H$49))) | F123: =E123*(1+IF(ISNUMBER(Assumptions!$H$53),Assumptions!$H$53,(Assumptions!I$5+Assumptions!$H$49))) | G123: =F123*(1+IF(ISNUMBER(Assumptions!$H$53),Assumptions!$H$53,(Assumptions!J$5+Assumptions!$H$49))) | H123: =G123*(1+IF(ISNUMBER(Assumptions!$H$53),Assumptions!$H$53,(Assumptions!K$5+Assumptions!$H$49))) | I123: =H123*(1+(Assumptions!L$5+Assumptions!$H$49)) | J123: =I123*(1+(Assumptions!M$5+Assumptions!$H$49)) | K123: =J123*(1+(Assumptions!N$5+Assumptions!$H$49)) | L123: =K123*(1+(Assumptions!O$5+Assumptions!$H$49)) | M123: =L123*(1+(Assumptions!P$5+Assumptions!$H$49))
...
